package com.ut.b;

import android.content.Context;
import android.content.SharedPreferences;
import android.content.SharedPreferences.Editor;
import android.os.Environment;
import com.ut.c.g;
import java.io.File;
import java.util.Iterator;
import java.util.Map;
import java.util.Map.Entry;
import java.util.Set;

public class c
{
  private String ak;
  private String al;
  private boolean am;
  private boolean an;
  private boolean ao;
  private SharedPreferences ap;
  private b aq;
  private SharedPreferences.Editor ar;
  private b.a as;
  private d at;
  private boolean au;
  private Context mContext;

  // ERROR //
  public c(Context paramContext, String paramString1, String paramString2, boolean paramBoolean1, boolean paramBoolean2)
  {
    // Byte code:
    //   0: aload_0
    //   1: invokespecial 31	java/lang/Object:<init>	()V
    //   4: aload_0
    //   5: ldc 33
    //   7: putfield 35	com/ut/b/c:ak	Ljava/lang/String;
    //   10: aload_0
    //   11: ldc 33
    //   13: putfield 37	com/ut/b/c:al	Ljava/lang/String;
    //   16: aload_0
    //   17: iconst_0
    //   18: putfield 39	com/ut/b/c:am	Z
    //   21: aload_0
    //   22: iconst_0
    //   23: putfield 41	com/ut/b/c:an	Z
    //   26: aload_0
    //   27: iconst_0
    //   28: putfield 43	com/ut/b/c:ao	Z
    //   31: aload_0
    //   32: aconst_null
    //   33: putfield 45	com/ut/b/c:ap	Landroid/content/SharedPreferences;
    //   36: aload_0
    //   37: aconst_null
    //   38: putfield 47	com/ut/b/c:aq	Lcom/ut/b/b;
    //   41: aload_0
    //   42: aconst_null
    //   43: putfield 49	com/ut/b/c:ar	Landroid/content/SharedPreferences$Editor;
    //   46: aload_0
    //   47: aconst_null
    //   48: putfield 51	com/ut/b/c:as	Lcom/ut/b/b$a;
    //   51: aload_0
    //   52: aconst_null
    //   53: putfield 53	com/ut/b/c:mContext	Landroid/content/Context;
    //   56: aload_0
    //   57: aconst_null
    //   58: putfield 55	com/ut/b/c:at	Lcom/ut/b/d;
    //   61: aload_0
    //   62: iconst_0
    //   63: putfield 57	com/ut/b/c:au	Z
    //   66: aload_0
    //   67: iload 4
    //   69: putfield 39	com/ut/b/c:am	Z
    //   72: aload_0
    //   73: iload 5
    //   75: putfield 57	com/ut/b/c:au	Z
    //   78: aload_0
    //   79: aload_3
    //   80: putfield 35	com/ut/b/c:ak	Ljava/lang/String;
    //   83: aload_0
    //   84: aload_2
    //   85: putfield 37	com/ut/b/c:al	Ljava/lang/String;
    //   88: aload_0
    //   89: aload_1
    //   90: putfield 53	com/ut/b/c:mContext	Landroid/content/Context;
    //   93: lconst_0
    //   94: lstore 6
    //   96: lconst_0
    //   97: lstore 8
    //   99: aload_1
    //   100: ifnull +27 -> 127
    //   103: aload_0
    //   104: aload_1
    //   105: aload_3
    //   106: iconst_0
    //   107: invokevirtual 63	android/content/Context:getSharedPreferences	(Ljava/lang/String;I)Landroid/content/SharedPreferences;
    //   110: putfield 45	com/ut/b/c:ap	Landroid/content/SharedPreferences;
    //   113: aload_0
    //   114: getfield 45	com/ut/b/c:ap	Landroid/content/SharedPreferences;
    //   117: ldc 65
    //   119: lconst_0
    //   120: invokeinterface 71 4 0
    //   125: lstore 6
    //   127: invokestatic 77	android/os/Environment:getExternalStorageState	()Ljava/lang/String;
    //   130: astore 10
    //   132: aload 10
    //   134: invokestatic 83	com/ut/c/g:D	(Ljava/lang/String;)Z
    //   137: ifne +284 -> 421
    //   140: aload 10
    //   142: ldc 85
    //   144: invokevirtual 91	java/lang/String:equals	(Ljava/lang/Object;)Z
    //   147: ifeq +251 -> 398
    //   150: aload_0
    //   151: iconst_1
    //   152: putfield 43	com/ut/b/c:ao	Z
    //   155: aload_0
    //   156: iconst_1
    //   157: putfield 41	com/ut/b/c:an	Z
    //   160: aload_0
    //   161: getfield 41	com/ut/b/c:an	Z
    //   164: ifne +10 -> 174
    //   167: aload_0
    //   168: getfield 43	com/ut/b/c:ao	Z
    //   171: ifeq +95 -> 266
    //   174: aload_1
    //   175: ifnull +91 -> 266
    //   178: aload_2
    //   179: invokestatic 83	com/ut/c/g:D	(Ljava/lang/String;)Z
    //   182: ifne +84 -> 266
    //   185: aload_0
    //   186: aload_0
    //   187: aload_2
    //   188: invokespecial 95	com/ut/b/c:z	(Ljava/lang/String;)Lcom/ut/b/d;
    //   191: putfield 55	com/ut/b/c:at	Lcom/ut/b/d;
    //   194: aload_0
    //   195: getfield 55	com/ut/b/c:at	Lcom/ut/b/d;
    //   198: ifnull +68 -> 266
    //   201: aload_0
    //   202: aload_0
    //   203: getfield 55	com/ut/b/c:at	Lcom/ut/b/d;
    //   206: aload_3
    //   207: iconst_0
    //   208: invokevirtual 101	com/ut/b/d:b	(Ljava/lang/String;I)Lcom/ut/b/b;
    //   211: putfield 47	com/ut/b/c:aq	Lcom/ut/b/b;
    //   214: aload_0
    //   215: getfield 47	com/ut/b/c:aq	Lcom/ut/b/b;
    //   218: ldc 65
    //   220: lconst_0
    //   221: invokeinterface 104 4 0
    //   226: lstore 8
    //   228: iload 5
    //   230: ifne +273 -> 503
    //   233: lload 6
    //   235: lload 8
    //   237: lcmp
    //   238: ifle +196 -> 434
    //   241: aload_0
    //   242: aload_0
    //   243: getfield 45	com/ut/b/c:ap	Landroid/content/SharedPreferences;
    //   246: aload_0
    //   247: getfield 47	com/ut/b/c:aq	Lcom/ut/b/b;
    //   250: invokespecial 108	com/ut/b/c:a	(Landroid/content/SharedPreferences;Lcom/ut/b/b;)V
    //   253: aload_0
    //   254: aload_0
    //   255: getfield 55	com/ut/b/c:at	Lcom/ut/b/d;
    //   258: aload_3
    //   259: iconst_0
    //   260: invokevirtual 101	com/ut/b/d:b	(Ljava/lang/String;I)Lcom/ut/b/b;
    //   263: putfield 47	com/ut/b/c:aq	Lcom/ut/b/b;
    //   266: lload 6
    //   268: lload 8
    //   270: lcmp
    //   271: ifne +17 -> 288
    //   274: lload 6
    //   276: lconst_0
    //   277: lcmp
    //   278: ifne +119 -> 397
    //   281: lload 8
    //   283: lconst_0
    //   284: lcmp
    //   285: ifne +112 -> 397
    //   288: invokestatic 114	java/lang/System:currentTimeMillis	()J
    //   291: lstore 11
    //   293: aload_0
    //   294: getfield 57	com/ut/b/c:au	Z
    //   297: ifeq +24 -> 321
    //   300: aload_0
    //   301: getfield 57	com/ut/b/c:au	Z
    //   304: ifeq +93 -> 397
    //   307: lload 6
    //   309: lconst_0
    //   310: lcmp
    //   311: ifne +86 -> 397
    //   314: lload 8
    //   316: lconst_0
    //   317: lcmp
    //   318: ifne +79 -> 397
    //   321: aload_0
    //   322: getfield 45	com/ut/b/c:ap	Landroid/content/SharedPreferences;
    //   325: ifnull +34 -> 359
    //   328: aload_0
    //   329: getfield 45	com/ut/b/c:ap	Landroid/content/SharedPreferences;
    //   332: invokeinterface 118 1 0
    //   337: astore 17
    //   339: aload 17
    //   341: ldc 120
    //   343: lload 11
    //   345: invokeinterface 126 4 0
    //   350: pop
    //   351: aload 17
    //   353: invokeinterface 130 1 0
    //   358: pop
    //   359: aload_0
    //   360: getfield 47	com/ut/b/c:aq	Lcom/ut/b/b;
    //   363: ifnull +34 -> 397
    //   366: aload_0
    //   367: getfield 47	com/ut/b/c:aq	Lcom/ut/b/b;
    //   370: invokeinterface 134 1 0
    //   375: astore 14
    //   377: aload 14
    //   379: ldc 120
    //   381: lload 11
    //   383: invokeinterface 139 4 0
    //   388: pop
    //   389: aload 14
    //   391: invokeinterface 140 1 0
    //   396: pop
    //   397: return
    //   398: aload 10
    //   400: ldc 142
    //   402: invokevirtual 91	java/lang/String:equals	(Ljava/lang/Object;)Z
    //   405: ifeq +16 -> 421
    //   408: aload_0
    //   409: iconst_1
    //   410: putfield 41	com/ut/b/c:an	Z
    //   413: aload_0
    //   414: iconst_0
    //   415: putfield 43	com/ut/b/c:ao	Z
    //   418: goto -258 -> 160
    //   421: aload_0
    //   422: iconst_0
    //   423: putfield 43	com/ut/b/c:ao	Z
    //   426: aload_0
    //   427: iconst_0
    //   428: putfield 41	com/ut/b/c:an	Z
    //   431: goto -271 -> 160
    //   434: lload 6
    //   436: lload 8
    //   438: lcmp
    //   439: ifge +28 -> 467
    //   442: aload_0
    //   443: aload_0
    //   444: getfield 47	com/ut/b/c:aq	Lcom/ut/b/b;
    //   447: aload_0
    //   448: getfield 45	com/ut/b/c:ap	Landroid/content/SharedPreferences;
    //   451: invokespecial 145	com/ut/b/c:a	(Lcom/ut/b/b;Landroid/content/SharedPreferences;)V
    //   454: aload_0
    //   455: aload_1
    //   456: aload_3
    //   457: iconst_0
    //   458: invokevirtual 63	android/content/Context:getSharedPreferences	(Ljava/lang/String;I)Landroid/content/SharedPreferences;
    //   461: putfield 45	com/ut/b/c:ap	Landroid/content/SharedPreferences;
    //   464: goto -198 -> 266
    //   467: lload 6
    //   469: lload 8
    //   471: lcmp
    //   472: ifne +332 -> 804
    //   475: aload_0
    //   476: aload_0
    //   477: getfield 45	com/ut/b/c:ap	Landroid/content/SharedPreferences;
    //   480: aload_0
    //   481: getfield 47	com/ut/b/c:aq	Lcom/ut/b/b;
    //   484: invokespecial 108	com/ut/b/c:a	(Landroid/content/SharedPreferences;Lcom/ut/b/b;)V
    //   487: aload_0
    //   488: aload_0
    //   489: getfield 55	com/ut/b/c:at	Lcom/ut/b/d;
    //   492: aload_3
    //   493: iconst_0
    //   494: invokevirtual 101	com/ut/b/d:b	(Ljava/lang/String;I)Lcom/ut/b/b;
    //   497: putfield 47	com/ut/b/c:aq	Lcom/ut/b/b;
    //   500: goto -234 -> 266
    //   503: aload_0
    //   504: getfield 45	com/ut/b/c:ap	Landroid/content/SharedPreferences;
    //   507: ldc 120
    //   509: lconst_0
    //   510: invokeinterface 71 4 0
    //   515: lstore 25
    //   517: lload 25
    //   519: lstore 21
    //   521: aload_0
    //   522: getfield 47	com/ut/b/c:aq	Lcom/ut/b/b;
    //   525: ldc 120
    //   527: lconst_0
    //   528: invokeinterface 104 4 0
    //   533: lstore 28
    //   535: lload 28
    //   537: lstore 23
    //   539: lload 21
    //   541: lload 23
    //   543: lcmp
    //   544: ifge +46 -> 590
    //   547: lload 21
    //   549: lconst_0
    //   550: lcmp
    //   551: ifle +39 -> 590
    //   554: aload_0
    //   555: aload_0
    //   556: getfield 45	com/ut/b/c:ap	Landroid/content/SharedPreferences;
    //   559: aload_0
    //   560: getfield 47	com/ut/b/c:aq	Lcom/ut/b/b;
    //   563: invokespecial 108	com/ut/b/c:a	(Landroid/content/SharedPreferences;Lcom/ut/b/b;)V
    //   566: aload_0
    //   567: aload_0
    //   568: getfield 55	com/ut/b/c:at	Lcom/ut/b/d;
    //   571: aload_3
    //   572: iconst_0
    //   573: invokevirtual 101	com/ut/b/d:b	(Ljava/lang/String;I)Lcom/ut/b/b;
    //   576: putfield 47	com/ut/b/c:aq	Lcom/ut/b/b;
    //   579: lload 23
    //   581: lstore 8
    //   583: lload 21
    //   585: lstore 6
    //   587: goto -321 -> 266
    //   590: lload 21
    //   592: lload 23
    //   594: lcmp
    //   595: ifle +43 -> 638
    //   598: lload 23
    //   600: lconst_0
    //   601: lcmp
    //   602: ifle +36 -> 638
    //   605: aload_0
    //   606: aload_0
    //   607: getfield 47	com/ut/b/c:aq	Lcom/ut/b/b;
    //   610: aload_0
    //   611: getfield 45	com/ut/b/c:ap	Landroid/content/SharedPreferences;
    //   614: invokespecial 145	com/ut/b/c:a	(Lcom/ut/b/b;Landroid/content/SharedPreferences;)V
    //   617: aload_0
    //   618: aload_1
    //   619: aload_3
    //   620: iconst_0
    //   621: invokevirtual 63	android/content/Context:getSharedPreferences	(Ljava/lang/String;I)Landroid/content/SharedPreferences;
    //   624: putfield 45	com/ut/b/c:ap	Landroid/content/SharedPreferences;
    //   627: lload 23
    //   629: lstore 8
    //   631: lload 21
    //   633: lstore 6
    //   635: goto -369 -> 266
    //   638: lload 21
    //   640: lconst_0
    //   641: lcmp
    //   642: ifne +43 -> 685
    //   645: lload 23
    //   647: lconst_0
    //   648: lcmp
    //   649: ifle +36 -> 685
    //   652: aload_0
    //   653: aload_0
    //   654: getfield 47	com/ut/b/c:aq	Lcom/ut/b/b;
    //   657: aload_0
    //   658: getfield 45	com/ut/b/c:ap	Landroid/content/SharedPreferences;
    //   661: invokespecial 145	com/ut/b/c:a	(Lcom/ut/b/b;Landroid/content/SharedPreferences;)V
    //   664: aload_0
    //   665: aload_1
    //   666: aload_3
    //   667: iconst_0
    //   668: invokevirtual 63	android/content/Context:getSharedPreferences	(Ljava/lang/String;I)Landroid/content/SharedPreferences;
    //   671: putfield 45	com/ut/b/c:ap	Landroid/content/SharedPreferences;
    //   674: lload 23
    //   676: lstore 8
    //   678: lload 21
    //   680: lstore 6
    //   682: goto -416 -> 266
    //   685: lload 23
    //   687: lconst_0
    //   688: lcmp
    //   689: ifne +46 -> 735
    //   692: lload 21
    //   694: lconst_0
    //   695: lcmp
    //   696: ifle +39 -> 735
    //   699: aload_0
    //   700: aload_0
    //   701: getfield 45	com/ut/b/c:ap	Landroid/content/SharedPreferences;
    //   704: aload_0
    //   705: getfield 47	com/ut/b/c:aq	Lcom/ut/b/b;
    //   708: invokespecial 108	com/ut/b/c:a	(Landroid/content/SharedPreferences;Lcom/ut/b/b;)V
    //   711: aload_0
    //   712: aload_0
    //   713: getfield 55	com/ut/b/c:at	Lcom/ut/b/d;
    //   716: aload_3
    //   717: iconst_0
    //   718: invokevirtual 101	com/ut/b/d:b	(Ljava/lang/String;I)Lcom/ut/b/b;
    //   721: putfield 47	com/ut/b/c:aq	Lcom/ut/b/b;
    //   724: lload 23
    //   726: lstore 8
    //   728: lload 21
    //   730: lstore 6
    //   732: goto -466 -> 266
    //   735: lload 21
    //   737: lload 23
    //   739: lcmp
    //   740: ifne +28 -> 768
    //   743: aload_0
    //   744: aload_0
    //   745: getfield 45	com/ut/b/c:ap	Landroid/content/SharedPreferences;
    //   748: aload_0
    //   749: getfield 47	com/ut/b/c:aq	Lcom/ut/b/b;
    //   752: invokespecial 108	com/ut/b/c:a	(Landroid/content/SharedPreferences;Lcom/ut/b/b;)V
    //   755: aload_0
    //   756: aload_0
    //   757: getfield 55	com/ut/b/c:at	Lcom/ut/b/d;
    //   760: aload_3
    //   761: iconst_0
    //   762: invokevirtual 101	com/ut/b/d:b	(Ljava/lang/String;I)Lcom/ut/b/b;
    //   765: putfield 47	com/ut/b/c:aq	Lcom/ut/b/b;
    //   768: lload 21
    //   770: lstore 31
    //   772: lload 23
    //   774: lstore 33
    //   776: lload 31
    //   778: lstore 6
    //   780: lload 33
    //   782: lstore 8
    //   784: goto -518 -> 266
    //   787: astore 13
    //   789: return
    //   790: astore 27
    //   792: lload 8
    //   794: lstore 23
    //   796: goto +33 -> 829
    //   799: astore 30
    //   801: goto +28 -> 829
    //   804: lload 8
    //   806: lstore 35
    //   808: lload 6
    //   810: lstore 31
    //   812: lload 35
    //   814: lstore 23
    //   816: goto -44 -> 772
    //   819: astore 20
    //   821: lload 6
    //   823: lstore 21
    //   825: lload 8
    //   827: lstore 23
    //   829: lload 23
    //   831: lstore 8
    //   833: lload 21
    //   835: lstore 6
    //   837: goto -571 -> 266
    //
    // Exception table:
    //   from	to	target	type
    //   359	397	787	java/lang/Exception
    //   521	535	790	java/lang/Exception
    //   554	579	799	java/lang/Exception
    //   605	627	799	java/lang/Exception
    //   652	674	799	java/lang/Exception
    //   699	724	799	java/lang/Exception
    //   743	768	799	java/lang/Exception
    //   201	228	819	java/lang/Exception
    //   241	266	819	java/lang/Exception
    //   442	464	819	java/lang/Exception
    //   475	500	819	java/lang/Exception
    //   503	517	819	java/lang/Exception
  }

  private File A(String paramString)
  {
    File localFile1 = Environment.getExternalStorageDirectory();
    if (localFile1 != null)
    {
      Object[] arrayOfObject = new Object[3];
      arrayOfObject[0] = localFile1.getAbsolutePath();
      arrayOfObject[1] = File.separator;
      arrayOfObject[2] = paramString;
      File localFile2 = new File(String.format("%s%s%s", arrayOfObject));
      if (!localFile2.exists())
        localFile2.mkdirs();
      return localFile2;
    }
    return null;
  }

  private void a(SharedPreferences paramSharedPreferences, b paramb)
  {
    if ((paramSharedPreferences != null) && (paramb != null))
    {
      b.a locala = paramb.q();
      if (locala != null)
      {
        locala.r();
        Iterator localIterator = paramSharedPreferences.getAll().entrySet().iterator();
        while (localIterator.hasNext())
        {
          Map.Entry localEntry = (Map.Entry)localIterator.next();
          String str = (String)localEntry.getKey();
          Object localObject = localEntry.getValue();
          if ((localObject instanceof String))
            locala.a(str, (String)localObject);
          else if ((localObject instanceof Integer))
            locala.a(str, ((Integer)localObject).intValue());
          else if ((localObject instanceof Long))
            locala.a(str, ((Long)localObject).longValue());
          else if ((localObject instanceof Float))
            locala.a(str, ((Float)localObject).floatValue());
          else if ((localObject instanceof Boolean))
            locala.a(str, ((Boolean)localObject).booleanValue());
        }
        locala.commit();
      }
    }
  }

  private void a(b paramb, SharedPreferences paramSharedPreferences)
  {
    if ((paramb != null) && (paramSharedPreferences != null))
    {
      SharedPreferences.Editor localEditor = paramSharedPreferences.edit();
      if (localEditor != null)
      {
        localEditor.clear();
        Iterator localIterator = paramb.getAll().entrySet().iterator();
        while (localIterator.hasNext())
        {
          Map.Entry localEntry = (Map.Entry)localIterator.next();
          String str = (String)localEntry.getKey();
          Object localObject = localEntry.getValue();
          if ((localObject instanceof String))
            localEditor.putString(str, (String)localObject);
          else if ((localObject instanceof Integer))
            localEditor.putInt(str, ((Integer)localObject).intValue());
          else if ((localObject instanceof Long))
            localEditor.putLong(str, ((Long)localObject).longValue());
          else if ((localObject instanceof Float))
            localEditor.putFloat(str, ((Float)localObject).floatValue());
          else if ((localObject instanceof Boolean))
            localEditor.putBoolean(str, ((Boolean)localObject).booleanValue());
        }
        localEditor.commit();
      }
    }
  }

  private boolean s()
  {
    if (this.aq != null)
    {
      boolean bool = this.aq.p();
      if (!bool)
        commit();
      return bool;
    }
    return false;
  }

  private void t()
  {
    if ((this.ar == null) && (this.ap != null))
      this.ar = this.ap.edit();
    if ((this.ao) && (this.as == null) && (this.aq != null))
      this.as = this.aq.q();
    s();
  }

  private d z(String paramString)
  {
    File localFile = A(paramString);
    if (localFile != null)
    {
      this.at = new d(localFile.getAbsolutePath());
      return this.at;
    }
    return null;
  }

  public void clear()
  {
    t();
    long l = System.currentTimeMillis();
    if (this.ar != null)
    {
      this.ar.clear();
      this.ar.putLong("t", l);
    }
    if (this.as != null)
    {
      this.as.r();
      this.as.a("t", l);
    }
  }

  public boolean commit()
  {
    boolean bool = true;
    long l = System.currentTimeMillis();
    if (this.ar != null)
    {
      if ((!this.au) && (this.ap != null))
        this.ar.putLong("t", l);
      if (!this.ar.commit())
        bool = false;
    }
    if ((this.ap != null) && (this.mContext != null))
      this.ap = this.mContext.getSharedPreferences(this.ak, 0);
    String str = Environment.getExternalStorageState();
    if (!g.D(str))
      if (str.equals("mounted"))
      {
        if (this.aq != null)
          break label242;
        d locald = z(this.al);
        if (locald != null)
        {
          this.aq = locald.b(this.ak, 0);
          if (this.au)
            break label227;
          a(this.ap, this.aq);
        }
      }
    while (true)
    {
      this.as = this.aq.q();
      label175: if ((str.equals("mounted")) || ((str.equals("mounted_ro")) && (this.aq != null)));
      try
      {
        if (this.at != null)
          this.aq = this.at.b(this.ak, 0);
        return bool;
        label227: a(this.aq, this.ap);
        continue;
        label242: if ((this.as == null) || (this.as.commit()))
          break label175;
        bool = false;
      }
      catch (Exception localException)
      {
      }
    }
    return bool;
  }

  public long getLong(String paramString)
  {
    long l = 0L;
    s();
    if (this.ap != null)
      l = this.ap.getLong(paramString, l);
    while (this.aq == null)
      return l;
    return this.aq.getLong(paramString, l);
  }

  public String getString(String paramString)
  {
    s();
    if (this.ap != null)
    {
      String str = this.ap.getString(paramString, "");
      if (!g.D(str))
        return str;
    }
    if (this.aq != null)
      return this.aq.getString(paramString, "");
    return "";
  }

  public void putLong(String paramString, long paramLong)
  {
    if ((!g.D(paramString)) && (!paramString.equals("t")))
    {
      t();
      if (this.ar != null)
        this.ar.putLong(paramString, paramLong);
      if (this.as != null)
        this.as.a(paramString, paramLong);
    }
  }

  public void putString(String paramString1, String paramString2)
  {
    if ((!g.D(paramString1)) && (!paramString1.equals("t")))
    {
      t();
      if (this.ar != null)
        this.ar.putString(paramString1, paramString2);
      if (this.as != null)
        this.as.a(paramString1, paramString2);
    }
  }
}

/* Location:           /Users/don/DeSources/alipay/backup/zhifubaoqianbao_52/classes-dex2jar.jar
 * Qualified Name:     com.ut.b.c
 * JD-Core Version:    0.6.2
 */