package com.alipay.mobile.longlink.service;

final class h
  implements Runnable
{
  final a a;

  private h(a parama)
  {
    this.a = parama;
  }

  // ERROR //
  public final void run()
  {
    // Byte code:
    //   0: iconst_3
    //   1: invokestatic 32	com/alipay/mobile/longlink/service/a:x	()Ljava/lang/String;
    //   4: ldc 34
    //   6: invokestatic 39	com/alipay/mobile/longlink/c/a:a	(ILjava/lang/String;Ljava/lang/String;)V
    //   9: aload_0
    //   10: getfield 18	com/alipay/mobile/longlink/service/h:a	Lcom/alipay/mobile/longlink/service/a;
    //   13: invokevirtual 43	com/alipay/mobile/longlink/service/a:p	()Z
    //   16: ifne +259 -> 275
    //   19: aload_0
    //   20: getfield 13	com/alipay/mobile/longlink/service/h:b	Lcom/alipay/mobile/longlink/service/a;
    //   23: invokestatic 47	com/alipay/mobile/longlink/service/a:i	(Lcom/alipay/mobile/longlink/service/a;)I
    //   26: invokestatic 52	com/alipay/mobile/longlink/b/c/c:a	(I)Lcom/alipay/mobile/longlink/b/c/a;
    //   29: astore_2
    //   30: aload_2
    //   31: iconst_0
    //   32: invokevirtual 57	com/alipay/mobile/longlink/b/c/a:a	(I)V
    //   35: aload_2
    //   36: iconst_0
    //   37: invokevirtual 59	com/alipay/mobile/longlink/b/c/a:b	(I)V
    //   40: new 61	org/json/JSONObject
    //   43: dup
    //   44: invokespecial 62	org/json/JSONObject:<init>	()V
    //   47: astore_3
    //   48: invokestatic 67	com/alipay/mobile/longlink/service/l:a	()Lcom/alipay/mobile/longlink/service/l;
    //   51: astore 5
    //   53: aload_3
    //   54: ldc 69
    //   56: aload 5
    //   58: invokevirtual 72	com/alipay/mobile/longlink/service/l:c	()Ljava/lang/String;
    //   61: invokevirtual 76	org/json/JSONObject:put	(Ljava/lang/String;Ljava/lang/Object;)Lorg/json/JSONObject;
    //   64: pop
    //   65: aload_3
    //   66: ldc 78
    //   68: aload 5
    //   70: invokevirtual 81	com/alipay/mobile/longlink/service/l:e	()Ljava/lang/String;
    //   73: invokevirtual 76	org/json/JSONObject:put	(Ljava/lang/String;Ljava/lang/Object;)Lorg/json/JSONObject;
    //   76: pop
    //   77: aload_3
    //   78: ldc 83
    //   80: ldc 85
    //   82: invokevirtual 76	org/json/JSONObject:put	(Ljava/lang/String;Ljava/lang/Object;)Lorg/json/JSONObject;
    //   85: pop
    //   86: aload_3
    //   87: ldc 87
    //   89: aload_0
    //   90: getfield 18	com/alipay/mobile/longlink/service/h:a	Lcom/alipay/mobile/longlink/service/a;
    //   93: invokestatic 91	com/alipay/mobile/longlink/service/a:j	(Lcom/alipay/mobile/longlink/service/a;)Ljava/lang/String;
    //   96: invokevirtual 76	org/json/JSONObject:put	(Ljava/lang/String;Ljava/lang/Object;)Lorg/json/JSONObject;
    //   99: pop
    //   100: aload_3
    //   101: ldc 93
    //   103: ldc 95
    //   105: invokevirtual 76	org/json/JSONObject:put	(Ljava/lang/String;Ljava/lang/Object;)Lorg/json/JSONObject;
    //   108: pop
    //   109: iconst_4
    //   110: invokestatic 32	com/alipay/mobile/longlink/service/a:x	()Ljava/lang/String;
    //   113: new 97	java/lang/StringBuilder
    //   116: dup
    //   117: ldc 99
    //   119: invokespecial 102	java/lang/StringBuilder:<init>	(Ljava/lang/String;)V
    //   122: aload_3
    //   123: invokevirtual 105	org/json/JSONObject:toString	()Ljava/lang/String;
    //   126: invokevirtual 109	java/lang/StringBuilder:append	(Ljava/lang/String;)Ljava/lang/StringBuilder;
    //   129: invokevirtual 110	java/lang/StringBuilder:toString	()Ljava/lang/String;
    //   132: invokestatic 39	com/alipay/mobile/longlink/c/a:a	(ILjava/lang/String;Ljava/lang/String;)V
    //   135: aload_3
    //   136: ldc 112
    //   138: aload 5
    //   140: invokevirtual 115	com/alipay/mobile/longlink/service/l:d	()Ljava/lang/String;
    //   143: invokevirtual 76	org/json/JSONObject:put	(Ljava/lang/String;Ljava/lang/Object;)Lorg/json/JSONObject;
    //   146: pop
    //   147: aload_2
    //   148: aload_3
    //   149: invokevirtual 105	org/json/JSONObject:toString	()Ljava/lang/String;
    //   152: invokevirtual 117	com/alipay/mobile/longlink/b/c/a:a	(Ljava/lang/String;)V
    //   155: aload_0
    //   156: getfield 13	com/alipay/mobile/longlink/service/h:b	Lcom/alipay/mobile/longlink/service/a;
    //   159: invokestatic 120	com/alipay/mobile/longlink/service/a:a	(Lcom/alipay/mobile/longlink/service/a;)Lcom/alipay/mobile/longlink/b/a/k;
    //   162: aload_0
    //   163: getfield 18	com/alipay/mobile/longlink/service/h:a	Lcom/alipay/mobile/longlink/service/a;
    //   166: invokevirtual 123	com/alipay/mobile/longlink/service/a:i	()Lcom/alipay/mobile/longlink/b/d/c;
    //   169: invokevirtual 128	com/alipay/mobile/longlink/b/a/k:a	(Lcom/alipay/mobile/longlink/b/d/c;)V
    //   172: aload_0
    //   173: getfield 13	com/alipay/mobile/longlink/service/h:b	Lcom/alipay/mobile/longlink/service/a;
    //   176: invokestatic 120	com/alipay/mobile/longlink/service/a:a	(Lcom/alipay/mobile/longlink/service/a;)Lcom/alipay/mobile/longlink/b/a/k;
    //   179: aload_0
    //   180: getfield 18	com/alipay/mobile/longlink/service/h:a	Lcom/alipay/mobile/longlink/service/a;
    //   183: invokevirtual 130	com/alipay/mobile/longlink/service/a:j	()Lcom/alipay/mobile/longlink/b/d/c;
    //   186: invokevirtual 128	com/alipay/mobile/longlink/b/a/k:a	(Lcom/alipay/mobile/longlink/b/d/c;)V
    //   189: aload_0
    //   190: getfield 13	com/alipay/mobile/longlink/service/h:b	Lcom/alipay/mobile/longlink/service/a;
    //   193: invokestatic 120	com/alipay/mobile/longlink/service/a:a	(Lcom/alipay/mobile/longlink/service/a;)Lcom/alipay/mobile/longlink/b/a/k;
    //   196: aload_0
    //   197: getfield 18	com/alipay/mobile/longlink/service/h:a	Lcom/alipay/mobile/longlink/service/a;
    //   200: invokevirtual 133	com/alipay/mobile/longlink/service/a:k	()Lcom/alipay/mobile/longlink/b/d/c;
    //   203: invokevirtual 128	com/alipay/mobile/longlink/b/a/k:a	(Lcom/alipay/mobile/longlink/b/d/c;)V
    //   206: aload_0
    //   207: getfield 13	com/alipay/mobile/longlink/service/h:b	Lcom/alipay/mobile/longlink/service/a;
    //   210: invokestatic 120	com/alipay/mobile/longlink/service/a:a	(Lcom/alipay/mobile/longlink/service/a;)Lcom/alipay/mobile/longlink/b/a/k;
    //   213: aload_0
    //   214: getfield 18	com/alipay/mobile/longlink/service/h:a	Lcom/alipay/mobile/longlink/service/a;
    //   217: invokevirtual 136	com/alipay/mobile/longlink/service/a:l	()Lcom/alipay/mobile/longlink/b/d/c;
    //   220: invokevirtual 128	com/alipay/mobile/longlink/b/a/k:a	(Lcom/alipay/mobile/longlink/b/d/c;)V
    //   223: iconst_4
    //   224: invokestatic 32	com/alipay/mobile/longlink/service/a:x	()Ljava/lang/String;
    //   227: new 97	java/lang/StringBuilder
    //   230: dup
    //   231: ldc 138
    //   233: invokespecial 102	java/lang/StringBuilder:<init>	(Ljava/lang/String;)V
    //   236: aload_2
    //   237: invokevirtual 141	com/alipay/mobile/longlink/b/c/a:c	()I
    //   240: invokevirtual 144	java/lang/StringBuilder:append	(I)Ljava/lang/StringBuilder;
    //   243: invokevirtual 110	java/lang/StringBuilder:toString	()Ljava/lang/String;
    //   246: invokestatic 39	com/alipay/mobile/longlink/c/a:a	(ILjava/lang/String;Ljava/lang/String;)V
    //   249: aload_0
    //   250: getfield 18	com/alipay/mobile/longlink/service/h:a	Lcom/alipay/mobile/longlink/service/a;
    //   253: invokevirtual 147	com/alipay/mobile/longlink/service/a:d	()Lcom/alipay/mobile/longlink/b/a/k;
    //   256: aload_2
    //   257: invokevirtual 150	com/alipay/mobile/longlink/b/a/k:a	(Lcom/alipay/mobile/longlink/b/c/a;)V
    //   260: return
    //   261: astore_1
    //   262: aload_1
    //   263: invokevirtual 153	java/lang/Exception:printStackTrace	()V
    //   266: return
    //   267: astore 4
    //   269: aload 4
    //   271: invokevirtual 154	org/json/JSONException:printStackTrace	()V
    //   274: return
    //   275: iconst_3
    //   276: invokestatic 32	com/alipay/mobile/longlink/service/a:x	()Ljava/lang/String;
    //   279: ldc 156
    //   281: invokestatic 39	com/alipay/mobile/longlink/c/a:a	(ILjava/lang/String;Ljava/lang/String;)V
    //   284: return
    //
    // Exception table:
    //   from	to	target	type
    //   19	40	261	java/lang/Exception
    //   48	155	267	org/json/JSONException
  }
}

/* Location:           /Users/don/DeSources/alipay/backup/zhifubaoqianbao_52/classes-dex2jar.jar
 * Qualified Name:     com.alipay.mobile.longlink.service.h
 * JD-Core Version:    0.6.2
 */