package com.alipay.android.widget.security.app;

import android.os.Bundle;
import com.alipay.mobile.framework.MicroApplicationContext;
import com.alipay.mobile.framework.app.ActivityApplication;
import com.alipay.mobile.framework.service.ext.security.AuthService;
import com.alipay.mobile.framework.service.ext.security.bean.UserInfo;
import com.alipay.mobile.security.authcenter.a.e;

public class ForgotMobilePwdApp extends ActivityApplication
{
  protected AuthService a;
  private String b;
  private MicroApplicationContext c;
  private e d;
  private UserInfo e = null;
  private Bundle f;

  public String getEntryClassName()
  {
    return null;
  }

  public Bundle getParams()
  {
    return this.f;
  }

  protected void onCreate(Bundle paramBundle)
  {
    this.f = paramBundle;
    this.c = getMicroApplicationContext();
    this.d = new e();
    this.a = ((AuthService)this.c.getExtServiceByInterface(AuthService.class.getName()));
  }

  protected void onDestroy(Bundle paramBundle)
  {
  }

  protected void onRestart(Bundle paramBundle)
  {
    this.f = paramBundle;
    new Thread(new a((byte)0)).start();
  }

  protected void onStart()
  {
    new Thread(new a((byte)0)).start();
  }

  protected void onStop()
  {
  }

  public void setParams(Bundle paramBundle)
  {
    this.f = paramBundle;
  }

  private final class a
    implements Runnable
  {
    private a()
    {
    }

    // ERROR //
    public final void run()
    {
      // Byte code:
      //   0: aload_0
      //   1: getfield 12	com/alipay/android/widget/security/app/ForgotMobilePwdApp$a:a	Lcom/alipay/android/widget/security/app/ForgotMobilePwdApp;
      //   4: invokestatic 29	com/alipay/android/widget/security/app/ForgotMobilePwdApp:access$100	(Lcom/alipay/android/widget/security/app/ForgotMobilePwdApp;)Landroid/os/Bundle;
      //   7: ifnull +589 -> 596
      //   10: aload_0
      //   11: getfield 12	com/alipay/android/widget/security/app/ForgotMobilePwdApp$a:a	Lcom/alipay/android/widget/security/app/ForgotMobilePwdApp;
      //   14: invokestatic 29	com/alipay/android/widget/security/app/ForgotMobilePwdApp:access$100	(Lcom/alipay/android/widget/security/app/ForgotMobilePwdApp;)Landroid/os/Bundle;
      //   17: ldc 31
      //   19: invokevirtual 37	android/os/Bundle:getString	(Ljava/lang/String;)Ljava/lang/String;
      //   22: invokestatic 42	com/alipay/mobile/security/securitycommon/SecurityUtil:a	(Ljava/lang/String;)Z
      //   25: ifne +571 -> 596
      //   28: aload_0
      //   29: getfield 12	com/alipay/android/widget/security/app/ForgotMobilePwdApp$a:a	Lcom/alipay/android/widget/security/app/ForgotMobilePwdApp;
      //   32: invokestatic 29	com/alipay/android/widget/security/app/ForgotMobilePwdApp:access$100	(Lcom/alipay/android/widget/security/app/ForgotMobilePwdApp;)Landroid/os/Bundle;
      //   35: ldc 31
      //   37: invokevirtual 37	android/os/Bundle:getString	(Ljava/lang/String;)Ljava/lang/String;
      //   40: astore_1
      //   41: aload_0
      //   42: getfield 12	com/alipay/android/widget/security/app/ForgotMobilePwdApp$a:a	Lcom/alipay/android/widget/security/app/ForgotMobilePwdApp;
      //   45: invokestatic 29	com/alipay/android/widget/security/app/ForgotMobilePwdApp:access$100	(Lcom/alipay/android/widget/security/app/ForgotMobilePwdApp;)Landroid/os/Bundle;
      //   48: ldc 44
      //   50: invokevirtual 37	android/os/Bundle:getString	(Ljava/lang/String;)Ljava/lang/String;
      //   53: invokestatic 42	com/alipay/mobile/security/securitycommon/SecurityUtil:a	(Ljava/lang/String;)Z
      //   56: ifeq +119 -> 175
      //   59: aload_0
      //   60: getfield 12	com/alipay/android/widget/security/app/ForgotMobilePwdApp$a:a	Lcom/alipay/android/widget/security/app/ForgotMobilePwdApp;
      //   63: ldc 46
      //   65: invokestatic 50	com/alipay/android/widget/security/app/ForgotMobilePwdApp:access$202	(Lcom/alipay/android/widget/security/app/ForgotMobilePwdApp;Ljava/lang/String;)Ljava/lang/String;
      //   68: pop
      //   69: aload_0
      //   70: getfield 12	com/alipay/android/widget/security/app/ForgotMobilePwdApp$a:a	Lcom/alipay/android/widget/security/app/ForgotMobilePwdApp;
      //   73: invokestatic 54	com/alipay/android/widget/security/app/ForgotMobilePwdApp:access$300	(Lcom/alipay/android/widget/security/app/ForgotMobilePwdApp;)Lcom/alipay/mobile/framework/MicroApplicationContext;
      //   76: aconst_null
      //   77: invokeinterface 60 2 0
      //   82: aload_0
      //   83: getfield 12	com/alipay/android/widget/security/app/ForgotMobilePwdApp$a:a	Lcom/alipay/android/widget/security/app/ForgotMobilePwdApp;
      //   86: invokestatic 64	com/alipay/android/widget/security/app/ForgotMobilePwdApp:access$400	(Lcom/alipay/android/widget/security/app/ForgotMobilePwdApp;)Lcom/alipay/mobile/security/authcenter/a/e;
      //   89: aload_1
      //   90: invokevirtual 70	com/alipay/mobile/security/authcenter/a/e:b	(Ljava/lang/String;)Lcom/alipay/mobileapp/biz/rpc/user/MobileUserResult;
      //   93: astore 5
      //   95: aload_0
      //   96: getfield 12	com/alipay/android/widget/security/app/ForgotMobilePwdApp$a:a	Lcom/alipay/android/widget/security/app/ForgotMobilePwdApp;
      //   99: invokestatic 54	com/alipay/android/widget/security/app/ForgotMobilePwdApp:access$300	(Lcom/alipay/android/widget/security/app/ForgotMobilePwdApp;)Lcom/alipay/mobile/framework/MicroApplicationContext;
      //   102: invokeinterface 73 1 0
      //   107: aload 5
      //   109: ifnull +65 -> 174
      //   112: aload 5
      //   114: invokevirtual 79	com/alipay/mobileapp/biz/rpc/user/MobileUserResult:isMobileUser	()Z
      //   117: ifeq +81 -> 198
      //   120: new 33	android/os/Bundle
      //   123: dup
      //   124: invokespecial 80	android/os/Bundle:<init>	()V
      //   127: astore 6
      //   129: aload 6
      //   131: ldc 31
      //   133: aload_1
      //   134: invokevirtual 84	android/os/Bundle:putString	(Ljava/lang/String;Ljava/lang/String;)V
      //   137: aload 6
      //   139: ldc 44
      //   141: aload_0
      //   142: getfield 12	com/alipay/android/widget/security/app/ForgotMobilePwdApp$a:a	Lcom/alipay/android/widget/security/app/ForgotMobilePwdApp;
      //   145: invokestatic 88	com/alipay/android/widget/security/app/ForgotMobilePwdApp:access$200	(Lcom/alipay/android/widget/security/app/ForgotMobilePwdApp;)Ljava/lang/String;
      //   148: invokevirtual 84	android/os/Bundle:putString	(Ljava/lang/String;Ljava/lang/String;)V
      //   151: aload_0
      //   152: getfield 12	com/alipay/android/widget/security/app/ForgotMobilePwdApp$a:a	Lcom/alipay/android/widget/security/app/ForgotMobilePwdApp;
      //   155: invokestatic 54	com/alipay/android/widget/security/app/ForgotMobilePwdApp:access$300	(Lcom/alipay/android/widget/security/app/ForgotMobilePwdApp;)Lcom/alipay/mobile/framework/MicroApplicationContext;
      //   158: aload_0
      //   159: getfield 12	com/alipay/android/widget/security/app/ForgotMobilePwdApp$a:a	Lcom/alipay/android/widget/security/app/ForgotMobilePwdApp;
      //   162: invokevirtual 92	com/alipay/android/widget/security/app/ForgotMobilePwdApp:getAppId	()Ljava/lang/String;
      //   165: ldc 94
      //   167: aload 6
      //   169: invokeinterface 98 4 0
      //   174: return
      //   175: aload_0
      //   176: getfield 12	com/alipay/android/widget/security/app/ForgotMobilePwdApp$a:a	Lcom/alipay/android/widget/security/app/ForgotMobilePwdApp;
      //   179: aload_0
      //   180: getfield 12	com/alipay/android/widget/security/app/ForgotMobilePwdApp$a:a	Lcom/alipay/android/widget/security/app/ForgotMobilePwdApp;
      //   183: invokestatic 29	com/alipay/android/widget/security/app/ForgotMobilePwdApp:access$100	(Lcom/alipay/android/widget/security/app/ForgotMobilePwdApp;)Landroid/os/Bundle;
      //   186: ldc 44
      //   188: invokevirtual 37	android/os/Bundle:getString	(Ljava/lang/String;)Ljava/lang/String;
      //   191: invokestatic 50	com/alipay/android/widget/security/app/ForgotMobilePwdApp:access$202	(Lcom/alipay/android/widget/security/app/ForgotMobilePwdApp;Ljava/lang/String;)Ljava/lang/String;
      //   194: pop
      //   195: goto -126 -> 69
      //   198: aload_0
      //   199: getfield 12	com/alipay/android/widget/security/app/ForgotMobilePwdApp$a:a	Lcom/alipay/android/widget/security/app/ForgotMobilePwdApp;
      //   202: getfield 101	com/alipay/android/widget/security/app/ForgotMobilePwdApp:a	Lcom/alipay/mobile/framework/service/ext/security/AuthService;
      //   205: ifnonnull +50 -> 255
      //   208: aload_0
      //   209: getfield 12	com/alipay/android/widget/security/app/ForgotMobilePwdApp$a:a	Lcom/alipay/android/widget/security/app/ForgotMobilePwdApp;
      //   212: invokestatic 54	com/alipay/android/widget/security/app/ForgotMobilePwdApp:access$300	(Lcom/alipay/android/widget/security/app/ForgotMobilePwdApp;)Lcom/alipay/mobile/framework/MicroApplicationContext;
      //   215: aload_0
      //   216: getfield 12	com/alipay/android/widget/security/app/ForgotMobilePwdApp$a:a	Lcom/alipay/android/widget/security/app/ForgotMobilePwdApp;
      //   219: invokevirtual 92	com/alipay/android/widget/security/app/ForgotMobilePwdApp:getAppId	()Ljava/lang/String;
      //   222: aload_0
      //   223: getfield 12	com/alipay/android/widget/security/app/ForgotMobilePwdApp$a:a	Lcom/alipay/android/widget/security/app/ForgotMobilePwdApp;
      //   226: invokevirtual 92	com/alipay/android/widget/security/app/ForgotMobilePwdApp:getAppId	()Ljava/lang/String;
      //   229: aconst_null
      //   230: invokeinterface 104 4 0
      //   235: return
      //   236: astore_3
      //   237: aload_3
      //   238: invokevirtual 107	com/alipay/mobile/common/rpc/RpcException:getMessage	()Ljava/lang/String;
      //   241: pop
      //   242: aload_0
      //   243: getfield 12	com/alipay/android/widget/security/app/ForgotMobilePwdApp$a:a	Lcom/alipay/android/widget/security/app/ForgotMobilePwdApp;
      //   246: invokestatic 54	com/alipay/android/widget/security/app/ForgotMobilePwdApp:access$300	(Lcom/alipay/android/widget/security/app/ForgotMobilePwdApp;)Lcom/alipay/mobile/framework/MicroApplicationContext;
      //   249: invokeinterface 73 1 0
      //   254: return
      //   255: aload_0
      //   256: getfield 12	com/alipay/android/widget/security/app/ForgotMobilePwdApp$a:a	Lcom/alipay/android/widget/security/app/ForgotMobilePwdApp;
      //   259: aload_0
      //   260: getfield 12	com/alipay/android/widget/security/app/ForgotMobilePwdApp$a:a	Lcom/alipay/android/widget/security/app/ForgotMobilePwdApp;
      //   263: getfield 101	com/alipay/android/widget/security/app/ForgotMobilePwdApp:a	Lcom/alipay/mobile/framework/service/ext/security/AuthService;
      //   266: invokevirtual 113	com/alipay/mobile/framework/service/ext/security/AuthService:getUserInfo	()Lcom/alipay/mobile/framework/service/ext/security/bean/UserInfo;
      //   269: invokestatic 117	com/alipay/android/widget/security/app/ForgotMobilePwdApp:access$502	(Lcom/alipay/android/widget/security/app/ForgotMobilePwdApp;Lcom/alipay/mobile/framework/service/ext/security/bean/UserInfo;)Lcom/alipay/mobile/framework/service/ext/security/bean/UserInfo;
      //   272: pop
      //   273: aload_0
      //   274: getfield 12	com/alipay/android/widget/security/app/ForgotMobilePwdApp$a:a	Lcom/alipay/android/widget/security/app/ForgotMobilePwdApp;
      //   277: invokestatic 121	com/alipay/android/widget/security/app/ForgotMobilePwdApp:access$500	(Lcom/alipay/android/widget/security/app/ForgotMobilePwdApp;)Lcom/alipay/mobile/framework/service/ext/security/bean/UserInfo;
      //   280: ifnonnull +51 -> 331
      //   283: aload_0
      //   284: getfield 12	com/alipay/android/widget/security/app/ForgotMobilePwdApp$a:a	Lcom/alipay/android/widget/security/app/ForgotMobilePwdApp;
      //   287: getfield 101	com/alipay/android/widget/security/app/ForgotMobilePwdApp:a	Lcom/alipay/mobile/framework/service/ext/security/AuthService;
      //   290: new 33	android/os/Bundle
      //   293: dup
      //   294: invokespecial 80	android/os/Bundle:<init>	()V
      //   297: invokevirtual 125	com/alipay/mobile/framework/service/ext/security/AuthService:auth	(Landroid/os/Bundle;)Z
      //   300: ifne +148 -> 448
      //   303: aload_0
      //   304: getfield 12	com/alipay/android/widget/security/app/ForgotMobilePwdApp$a:a	Lcom/alipay/android/widget/security/app/ForgotMobilePwdApp;
      //   307: invokestatic 54	com/alipay/android/widget/security/app/ForgotMobilePwdApp:access$300	(Lcom/alipay/android/widget/security/app/ForgotMobilePwdApp;)Lcom/alipay/mobile/framework/MicroApplicationContext;
      //   310: aload_0
      //   311: getfield 12	com/alipay/android/widget/security/app/ForgotMobilePwdApp$a:a	Lcom/alipay/android/widget/security/app/ForgotMobilePwdApp;
      //   314: invokevirtual 92	com/alipay/android/widget/security/app/ForgotMobilePwdApp:getAppId	()Ljava/lang/String;
      //   317: aload_0
      //   318: getfield 12	com/alipay/android/widget/security/app/ForgotMobilePwdApp$a:a	Lcom/alipay/android/widget/security/app/ForgotMobilePwdApp;
      //   321: invokevirtual 92	com/alipay/android/widget/security/app/ForgotMobilePwdApp:getAppId	()Ljava/lang/String;
      //   324: aconst_null
      //   325: invokeinterface 104 4 0
      //   330: return
      //   331: aload_1
      //   332: aload_0
      //   333: getfield 12	com/alipay/android/widget/security/app/ForgotMobilePwdApp$a:a	Lcom/alipay/android/widget/security/app/ForgotMobilePwdApp;
      //   336: invokestatic 121	com/alipay/android/widget/security/app/ForgotMobilePwdApp:access$500	(Lcom/alipay/android/widget/security/app/ForgotMobilePwdApp;)Lcom/alipay/mobile/framework/service/ext/security/bean/UserInfo;
      //   339: invokevirtual 130	com/alipay/mobile/framework/service/ext/security/bean/UserInfo:getLogonId	()Ljava/lang/String;
      //   342: invokestatic 136	com/alipay/mobile/common/utils/StringUtils:equals	(Ljava/lang/String;Ljava/lang/String;)Z
      //   345: ifeq +64 -> 409
      //   348: aload_0
      //   349: getfield 12	com/alipay/android/widget/security/app/ForgotMobilePwdApp$a:a	Lcom/alipay/android/widget/security/app/ForgotMobilePwdApp;
      //   352: getfield 101	com/alipay/android/widget/security/app/ForgotMobilePwdApp:a	Lcom/alipay/mobile/framework/service/ext/security/AuthService;
      //   355: invokevirtual 139	com/alipay/mobile/framework/service/ext/security/AuthService:isLogin	()Z
      //   358: ifne +90 -> 448
      //   361: aload_0
      //   362: getfield 12	com/alipay/android/widget/security/app/ForgotMobilePwdApp$a:a	Lcom/alipay/android/widget/security/app/ForgotMobilePwdApp;
      //   365: getfield 101	com/alipay/android/widget/security/app/ForgotMobilePwdApp:a	Lcom/alipay/mobile/framework/service/ext/security/AuthService;
      //   368: new 33	android/os/Bundle
      //   371: dup
      //   372: invokespecial 80	android/os/Bundle:<init>	()V
      //   375: invokevirtual 125	com/alipay/mobile/framework/service/ext/security/AuthService:auth	(Landroid/os/Bundle;)Z
      //   378: ifne +70 -> 448
      //   381: aload_0
      //   382: getfield 12	com/alipay/android/widget/security/app/ForgotMobilePwdApp$a:a	Lcom/alipay/android/widget/security/app/ForgotMobilePwdApp;
      //   385: invokestatic 54	com/alipay/android/widget/security/app/ForgotMobilePwdApp:access$300	(Lcom/alipay/android/widget/security/app/ForgotMobilePwdApp;)Lcom/alipay/mobile/framework/MicroApplicationContext;
      //   388: aload_0
      //   389: getfield 12	com/alipay/android/widget/security/app/ForgotMobilePwdApp$a:a	Lcom/alipay/android/widget/security/app/ForgotMobilePwdApp;
      //   392: invokevirtual 92	com/alipay/android/widget/security/app/ForgotMobilePwdApp:getAppId	()Ljava/lang/String;
      //   395: aload_0
      //   396: getfield 12	com/alipay/android/widget/security/app/ForgotMobilePwdApp$a:a	Lcom/alipay/android/widget/security/app/ForgotMobilePwdApp;
      //   399: invokevirtual 92	com/alipay/android/widget/security/app/ForgotMobilePwdApp:getAppId	()Ljava/lang/String;
      //   402: aconst_null
      //   403: invokeinterface 104 4 0
      //   408: return
      //   409: aload_0
      //   410: getfield 12	com/alipay/android/widget/security/app/ForgotMobilePwdApp$a:a	Lcom/alipay/android/widget/security/app/ForgotMobilePwdApp;
      //   413: aload_1
      //   414: aconst_null
      //   415: iconst_0
      //   416: iconst_0
      //   417: invokestatic 143	com/alipay/android/widget/security/app/ForgotMobilePwdApp:access$600	(Lcom/alipay/android/widget/security/app/ForgotMobilePwdApp;Ljava/lang/String;Ljava/lang/String;ZZ)V
      //   420: aload_0
      //   421: getfield 12	com/alipay/android/widget/security/app/ForgotMobilePwdApp$a:a	Lcom/alipay/android/widget/security/app/ForgotMobilePwdApp;
      //   424: invokestatic 54	com/alipay/android/widget/security/app/ForgotMobilePwdApp:access$300	(Lcom/alipay/android/widget/security/app/ForgotMobilePwdApp;)Lcom/alipay/mobile/framework/MicroApplicationContext;
      //   427: aload_0
      //   428: getfield 12	com/alipay/android/widget/security/app/ForgotMobilePwdApp$a:a	Lcom/alipay/android/widget/security/app/ForgotMobilePwdApp;
      //   431: invokevirtual 92	com/alipay/android/widget/security/app/ForgotMobilePwdApp:getAppId	()Ljava/lang/String;
      //   434: aload_0
      //   435: getfield 12	com/alipay/android/widget/security/app/ForgotMobilePwdApp$a:a	Lcom/alipay/android/widget/security/app/ForgotMobilePwdApp;
      //   438: invokevirtual 92	com/alipay/android/widget/security/app/ForgotMobilePwdApp:getAppId	()Ljava/lang/String;
      //   441: aconst_null
      //   442: invokeinterface 104 4 0
      //   447: return
      //   448: aload_0
      //   449: getfield 12	com/alipay/android/widget/security/app/ForgotMobilePwdApp$a:a	Lcom/alipay/android/widget/security/app/ForgotMobilePwdApp;
      //   452: aload_0
      //   453: getfield 12	com/alipay/android/widget/security/app/ForgotMobilePwdApp$a:a	Lcom/alipay/android/widget/security/app/ForgotMobilePwdApp;
      //   456: getfield 101	com/alipay/android/widget/security/app/ForgotMobilePwdApp:a	Lcom/alipay/mobile/framework/service/ext/security/AuthService;
      //   459: invokevirtual 113	com/alipay/mobile/framework/service/ext/security/AuthService:getUserInfo	()Lcom/alipay/mobile/framework/service/ext/security/bean/UserInfo;
      //   462: invokestatic 117	com/alipay/android/widget/security/app/ForgotMobilePwdApp:access$502	(Lcom/alipay/android/widget/security/app/ForgotMobilePwdApp;Lcom/alipay/mobile/framework/service/ext/security/bean/UserInfo;)Lcom/alipay/mobile/framework/service/ext/security/bean/UserInfo;
      //   465: pop
      //   466: aload_0
      //   467: getfield 12	com/alipay/android/widget/security/app/ForgotMobilePwdApp$a:a	Lcom/alipay/android/widget/security/app/ForgotMobilePwdApp;
      //   470: invokestatic 121	com/alipay/android/widget/security/app/ForgotMobilePwdApp:access$500	(Lcom/alipay/android/widget/security/app/ForgotMobilePwdApp;)Lcom/alipay/mobile/framework/service/ext/security/bean/UserInfo;
      //   473: ifnull +78 -> 551
      //   476: aload_1
      //   477: aload_0
      //   478: getfield 12	com/alipay/android/widget/security/app/ForgotMobilePwdApp$a:a	Lcom/alipay/android/widget/security/app/ForgotMobilePwdApp;
      //   481: invokestatic 121	com/alipay/android/widget/security/app/ForgotMobilePwdApp:access$500	(Lcom/alipay/android/widget/security/app/ForgotMobilePwdApp;)Lcom/alipay/mobile/framework/service/ext/security/bean/UserInfo;
      //   484: invokevirtual 130	com/alipay/mobile/framework/service/ext/security/bean/UserInfo:getLogonId	()Ljava/lang/String;
      //   487: invokestatic 136	com/alipay/mobile/common/utils/StringUtils:equals	(Ljava/lang/String;Ljava/lang/String;)Z
      //   490: ifeq +61 -> 551
      //   493: new 33	android/os/Bundle
      //   496: dup
      //   497: invokespecial 80	android/os/Bundle:<init>	()V
      //   500: astore 11
      //   502: aload 11
      //   504: ldc 44
      //   506: aload_0
      //   507: getfield 12	com/alipay/android/widget/security/app/ForgotMobilePwdApp$a:a	Lcom/alipay/android/widget/security/app/ForgotMobilePwdApp;
      //   510: invokestatic 88	com/alipay/android/widget/security/app/ForgotMobilePwdApp:access$200	(Lcom/alipay/android/widget/security/app/ForgotMobilePwdApp;)Ljava/lang/String;
      //   513: invokevirtual 84	android/os/Bundle:putString	(Ljava/lang/String;Ljava/lang/String;)V
      //   516: aload 11
      //   518: ldc 145
      //   520: iconst_1
      //   521: invokevirtual 149	android/os/Bundle:putBoolean	(Ljava/lang/String;Z)V
      //   524: aload_0
      //   525: getfield 12	com/alipay/android/widget/security/app/ForgotMobilePwdApp$a:a	Lcom/alipay/android/widget/security/app/ForgotMobilePwdApp;
      //   528: invokestatic 54	com/alipay/android/widget/security/app/ForgotMobilePwdApp:access$300	(Lcom/alipay/android/widget/security/app/ForgotMobilePwdApp;)Lcom/alipay/mobile/framework/MicroApplicationContext;
      //   531: aload_0
      //   532: getfield 12	com/alipay/android/widget/security/app/ForgotMobilePwdApp$a:a	Lcom/alipay/android/widget/security/app/ForgotMobilePwdApp;
      //   535: invokevirtual 92	com/alipay/android/widget/security/app/ForgotMobilePwdApp:getAppId	()Ljava/lang/String;
      //   538: ldc 151
      //   540: aload 11
      //   542: invokeinterface 98 4 0
      //   547: return
      //   548: astore 12
      //   550: return
      //   551: new 153	java/lang/StringBuilder
      //   554: dup
      //   555: ldc 155
      //   557: invokespecial 157	java/lang/StringBuilder:<init>	(Ljava/lang/String;)V
      //   560: aload_1
      //   561: invokevirtual 161	java/lang/StringBuilder:append	(Ljava/lang/String;)Ljava/lang/StringBuilder;
      //   564: invokevirtual 164	java/lang/StringBuilder:toString	()Ljava/lang/String;
      //   567: pop
      //   568: aload_0
      //   569: getfield 12	com/alipay/android/widget/security/app/ForgotMobilePwdApp$a:a	Lcom/alipay/android/widget/security/app/ForgotMobilePwdApp;
      //   572: invokestatic 54	com/alipay/android/widget/security/app/ForgotMobilePwdApp:access$300	(Lcom/alipay/android/widget/security/app/ForgotMobilePwdApp;)Lcom/alipay/mobile/framework/MicroApplicationContext;
      //   575: aload_0
      //   576: getfield 12	com/alipay/android/widget/security/app/ForgotMobilePwdApp$a:a	Lcom/alipay/android/widget/security/app/ForgotMobilePwdApp;
      //   579: invokevirtual 92	com/alipay/android/widget/security/app/ForgotMobilePwdApp:getAppId	()Ljava/lang/String;
      //   582: aload_0
      //   583: getfield 12	com/alipay/android/widget/security/app/ForgotMobilePwdApp$a:a	Lcom/alipay/android/widget/security/app/ForgotMobilePwdApp;
      //   586: invokevirtual 92	com/alipay/android/widget/security/app/ForgotMobilePwdApp:getAppId	()Ljava/lang/String;
      //   589: aconst_null
      //   590: invokeinterface 104 4 0
      //   595: return
      //   596: aload_0
      //   597: getfield 12	com/alipay/android/widget/security/app/ForgotMobilePwdApp$a:a	Lcom/alipay/android/widget/security/app/ForgotMobilePwdApp;
      //   600: invokestatic 54	com/alipay/android/widget/security/app/ForgotMobilePwdApp:access$300	(Lcom/alipay/android/widget/security/app/ForgotMobilePwdApp;)Lcom/alipay/mobile/framework/MicroApplicationContext;
      //   603: aload_0
      //   604: getfield 12	com/alipay/android/widget/security/app/ForgotMobilePwdApp$a:a	Lcom/alipay/android/widget/security/app/ForgotMobilePwdApp;
      //   607: invokevirtual 92	com/alipay/android/widget/security/app/ForgotMobilePwdApp:getAppId	()Ljava/lang/String;
      //   610: aload_0
      //   611: getfield 12	com/alipay/android/widget/security/app/ForgotMobilePwdApp$a:a	Lcom/alipay/android/widget/security/app/ForgotMobilePwdApp;
      //   614: invokevirtual 92	com/alipay/android/widget/security/app/ForgotMobilePwdApp:getAppId	()Ljava/lang/String;
      //   617: aconst_null
      //   618: invokeinterface 104 4 0
      //   623: return
      //   624: astore 7
      //   626: return
      //
      // Exception table:
      //   from	to	target	type
      //   82	107	236	com/alipay/mobile/common/rpc/RpcException
      //   112	151	236	com/alipay/mobile/common/rpc/RpcException
      //   151	174	236	com/alipay/mobile/common/rpc/RpcException
      //   198	235	236	com/alipay/mobile/common/rpc/RpcException
      //   255	330	236	com/alipay/mobile/common/rpc/RpcException
      //   331	408	236	com/alipay/mobile/common/rpc/RpcException
      //   409	447	236	com/alipay/mobile/common/rpc/RpcException
      //   448	524	236	com/alipay/mobile/common/rpc/RpcException
      //   524	547	236	com/alipay/mobile/common/rpc/RpcException
      //   551	595	236	com/alipay/mobile/common/rpc/RpcException
      //   524	547	548	com/alipay/mobile/framework/app/AppLoadException
      //   151	174	624	com/alipay/mobile/framework/app/AppLoadException
    }
  }
}

/* Location:           /Users/don/DeSources/alipay/backup/zhifubaoqianbao_52/classes-dex2jar.jar
 * Qualified Name:     com.alipay.android.widget.security.app.ForgotMobilePwdApp
 * JD-Core Version:    0.6.2
 */