package com.aps;

import android.net.NetworkInfo;
import android.telephony.TelephonyManager;
import android.text.TextUtils;
import android.util.SparseArray;
import org.apache.http.Header;
import org.apache.http.HttpResponse;
import org.json.JSONException;
import org.json.JSONObject;

public class j
{
  private static j a = null;

  public static int a(NetworkInfo paramNetworkInfo)
  {
    if (paramNetworkInfo == null);
    while ((!paramNetworkInfo.isAvailable()) || (!paramNetworkInfo.isConnected()))
      return -1;
    return paramNetworkInfo.getType();
  }

  public static j a()
  {
    try
    {
      if (a == null)
        a = new j();
      j localj = a;
      return localj;
    }
    finally
    {
    }
  }

  public static String a(TelephonyManager paramTelephonyManager)
  {
    int i = 0;
    if (paramTelephonyManager != null)
      i = paramTelephonyManager.getNetworkType();
    return (String)f.l.get(i, "UNKNOWN");
  }

  // ERROR //
  public static org.apache.http.client.HttpClient a(android.content.Context paramContext, NetworkInfo paramNetworkInfo)
  {
    // Byte code:
    //   0: new 58	org/apache/http/params/BasicHttpParams
    //   3: dup
    //   4: invokespecial 59	org/apache/http/params/BasicHttpParams:<init>	()V
    //   7: astore_2
    //   8: aload_1
    //   9: invokevirtual 27	android/net/NetworkInfo:getType	()I
    //   12: ifne +592 -> 604
    //   15: ldc 61
    //   17: invokestatic 67	android/net/Uri:parse	(Ljava/lang/String;)Landroid/net/Uri;
    //   20: astore 9
    //   22: aload_0
    //   23: invokevirtual 73	android/content/Context:getContentResolver	()Landroid/content/ContentResolver;
    //   26: astore 10
    //   28: aload 10
    //   30: aload 9
    //   32: aconst_null
    //   33: aconst_null
    //   34: aconst_null
    //   35: aconst_null
    //   36: invokevirtual 79	android/content/ContentResolver:query	(Landroid/net/Uri;[Ljava/lang/String;Ljava/lang/String;[Ljava/lang/String;Ljava/lang/String;)Landroid/database/Cursor;
    //   39: astore 20
    //   41: aload 20
    //   43: astore 12
    //   45: aload 12
    //   47: ifnull +539 -> 586
    //   50: aload 12
    //   52: invokeinterface 84 1 0
    //   57: ifeq +529 -> 586
    //   60: aload 12
    //   62: aload 12
    //   64: ldc 86
    //   66: invokeinterface 90 2 0
    //   71: invokeinterface 94 2 0
    //   76: astore 23
    //   78: aload 23
    //   80: ifnull +27 -> 107
    //   83: aload 23
    //   85: invokevirtual 98	java/lang/String:toLowerCase	()Ljava/lang/String;
    //   88: astore 23
    //   90: iconst_2
    //   91: anewarray 4	java/lang/Object
    //   94: dup
    //   95: iconst_0
    //   96: ldc 100
    //   98: aastore
    //   99: dup
    //   100: iconst_1
    //   101: aload 23
    //   103: aastore
    //   104: invokestatic 105	com/aps/n:a	([Ljava/lang/Object;)V
    //   107: aload 23
    //   109: ifnull +182 -> 291
    //   112: aload 23
    //   114: ldc 107
    //   116: invokevirtual 111	java/lang/String:contains	(Ljava/lang/CharSequence;)Z
    //   119: ifeq +172 -> 291
    //   122: invokestatic 114	com/aps/j:b	()Ljava/lang/String;
    //   125: astore 27
    //   127: aload 27
    //   129: invokestatic 119	android/text/TextUtils:isEmpty	(Ljava/lang/CharSequence;)Z
    //   132: ifne +463 -> 595
    //   135: aload 27
    //   137: ldc 121
    //   139: invokevirtual 125	java/lang/String:equals	(Ljava/lang/Object;)Z
    //   142: istore 29
    //   144: iload 29
    //   146: ifne +449 -> 595
    //   149: iconst_1
    //   150: istore 28
    //   152: iload 28
    //   154: ifne +7 -> 161
    //   157: ldc 127
    //   159: astore 27
    //   161: aload 27
    //   163: astore 4
    //   165: bipush 80
    //   167: istore 21
    //   169: aload 12
    //   171: ifnull +10 -> 181
    //   174: aload 12
    //   176: invokeinterface 130 1 0
    //   181: iload 21
    //   183: istore_3
    //   184: aload 4
    //   186: ifnull +343 -> 529
    //   189: aload 4
    //   191: invokevirtual 133	java/lang/String:length	()I
    //   194: ifle +335 -> 529
    //   197: iload_3
    //   198: iconst_m1
    //   199: if_icmpeq +330 -> 529
    //   202: iconst_1
    //   203: istore 5
    //   205: iload 5
    //   207: ifeq +24 -> 231
    //   210: aload_2
    //   211: ldc 135
    //   213: new 137	org/apache/http/HttpHost
    //   216: dup
    //   217: aload 4
    //   219: iload_3
    //   220: ldc 139
    //   222: invokespecial 142	org/apache/http/HttpHost:<init>	(Ljava/lang/String;ILjava/lang/String;)V
    //   225: invokeinterface 148 3 0
    //   230: pop
    //   231: aload_2
    //   232: sipush 30000
    //   235: invokestatic 151	com/aps/n:a	(Lorg/apache/http/params/HttpParams;I)V
    //   238: aload_2
    //   239: iconst_0
    //   240: invokestatic 157	org/apache/http/params/HttpProtocolParams:setUseExpectContinue	(Lorg/apache/http/params/HttpParams;Z)V
    //   243: new 159	org/apache/http/conn/scheme/SchemeRegistry
    //   246: dup
    //   247: invokespecial 160	org/apache/http/conn/scheme/SchemeRegistry:<init>	()V
    //   250: astore 6
    //   252: aload 6
    //   254: new 162	org/apache/http/conn/scheme/Scheme
    //   257: dup
    //   258: ldc 139
    //   260: invokestatic 168	org/apache/http/conn/scheme/PlainSocketFactory:getSocketFactory	()Lorg/apache/http/conn/scheme/PlainSocketFactory;
    //   263: bipush 80
    //   265: invokespecial 171	org/apache/http/conn/scheme/Scheme:<init>	(Ljava/lang/String;Lorg/apache/http/conn/scheme/SocketFactory;I)V
    //   268: invokevirtual 175	org/apache/http/conn/scheme/SchemeRegistry:register	(Lorg/apache/http/conn/scheme/Scheme;)Lorg/apache/http/conn/scheme/Scheme;
    //   271: pop
    //   272: new 177	org/apache/http/impl/client/DefaultHttpClient
    //   275: dup
    //   276: new 179	org/apache/http/impl/conn/SingleClientConnManager
    //   279: dup
    //   280: aload_2
    //   281: aload 6
    //   283: invokespecial 182	org/apache/http/impl/conn/SingleClientConnManager:<init>	(Lorg/apache/http/params/HttpParams;Lorg/apache/http/conn/scheme/SchemeRegistry;)V
    //   286: aload_2
    //   287: invokespecial 185	org/apache/http/impl/client/DefaultHttpClient:<init>	(Lorg/apache/http/conn/ClientConnectionManager;Lorg/apache/http/params/HttpParams;)V
    //   290: areturn
    //   291: aload 23
    //   293: ifnull +293 -> 586
    //   296: aload 23
    //   298: ldc 187
    //   300: invokevirtual 111	java/lang/String:contains	(Ljava/lang/CharSequence;)Z
    //   303: ifeq +283 -> 586
    //   306: invokestatic 114	com/aps/j:b	()Ljava/lang/String;
    //   309: astore 24
    //   311: aload 24
    //   313: invokestatic 119	android/text/TextUtils:isEmpty	(Ljava/lang/CharSequence;)Z
    //   316: ifne +261 -> 577
    //   319: aload 24
    //   321: ldc 121
    //   323: invokevirtual 125	java/lang/String:equals	(Ljava/lang/Object;)Z
    //   326: istore 26
    //   328: iload 26
    //   330: ifne +247 -> 577
    //   333: iconst_1
    //   334: istore 25
    //   336: iload 25
    //   338: ifne +7 -> 345
    //   341: ldc 189
    //   343: astore 24
    //   345: aload 24
    //   347: astore 4
    //   349: bipush 80
    //   351: istore 21
    //   353: goto -184 -> 169
    //   356: astore 14
    //   358: aconst_null
    //   359: astore 12
    //   361: aload_1
    //   362: invokevirtual 192	android/net/NetworkInfo:getExtraInfo	()Ljava/lang/String;
    //   365: ifnull +194 -> 559
    //   368: aload_1
    //   369: invokevirtual 192	android/net/NetworkInfo:getExtraInfo	()Ljava/lang/String;
    //   372: invokevirtual 98	java/lang/String:toLowerCase	()Ljava/lang/String;
    //   375: astore 16
    //   377: invokestatic 114	com/aps/j:b	()Ljava/lang/String;
    //   380: astore 17
    //   382: aload 16
    //   384: ldc 107
    //   386: invokevirtual 195	java/lang/String:indexOf	(Ljava/lang/String;)I
    //   389: iconst_m1
    //   390: if_icmpeq +59 -> 449
    //   393: aload 17
    //   395: invokestatic 119	android/text/TextUtils:isEmpty	(Ljava/lang/CharSequence;)Z
    //   398: ifne +170 -> 568
    //   401: aload 17
    //   403: ldc 121
    //   405: invokevirtual 125	java/lang/String:equals	(Ljava/lang/Object;)Z
    //   408: ifne +160 -> 568
    //   411: iconst_1
    //   412: istore 19
    //   414: iload 19
    //   416: ifne +7 -> 423
    //   419: ldc 127
    //   421: astore 17
    //   423: aload 17
    //   425: astore 4
    //   427: bipush 80
    //   429: istore 15
    //   431: aload 12
    //   433: ifnull +10 -> 443
    //   436: aload 12
    //   438: invokeinterface 130 1 0
    //   443: iload 15
    //   445: istore_3
    //   446: goto -262 -> 184
    //   449: aload 16
    //   451: ldc 187
    //   453: invokevirtual 195	java/lang/String:indexOf	(Ljava/lang/String;)I
    //   456: iconst_m1
    //   457: if_icmpeq +102 -> 559
    //   460: aload 17
    //   462: invokestatic 119	android/text/TextUtils:isEmpty	(Ljava/lang/CharSequence;)Z
    //   465: ifne +85 -> 550
    //   468: aload 17
    //   470: ldc 121
    //   472: invokevirtual 125	java/lang/String:equals	(Ljava/lang/Object;)Z
    //   475: ifne +75 -> 550
    //   478: iconst_1
    //   479: istore 18
    //   481: goto +131 -> 612
    //   484: aload 13
    //   486: invokestatic 198	com/aps/n:a	(Ljava/lang/Throwable;)V
    //   489: aload 12
    //   491: ifnull +10 -> 501
    //   494: aload 12
    //   496: invokeinterface 130 1 0
    //   501: iconst_m1
    //   502: istore_3
    //   503: aconst_null
    //   504: astore 4
    //   506: goto -322 -> 184
    //   509: astore 11
    //   511: aconst_null
    //   512: astore 12
    //   514: aload 12
    //   516: ifnull +10 -> 526
    //   519: aload 12
    //   521: invokeinterface 130 1 0
    //   526: aload 11
    //   528: athrow
    //   529: iconst_0
    //   530: istore 5
    //   532: goto -327 -> 205
    //   535: astore 11
    //   537: goto -23 -> 514
    //   540: astore 13
    //   542: goto -58 -> 484
    //   545: astore 22
    //   547: goto -186 -> 361
    //   550: aconst_null
    //   551: astore 17
    //   553: iconst_0
    //   554: istore 18
    //   556: goto +56 -> 612
    //   559: iconst_m1
    //   560: istore 15
    //   562: aconst_null
    //   563: astore 4
    //   565: goto -134 -> 431
    //   568: aconst_null
    //   569: astore 17
    //   571: iconst_0
    //   572: istore 19
    //   574: goto -160 -> 414
    //   577: aconst_null
    //   578: astore 24
    //   580: iconst_0
    //   581: istore 25
    //   583: goto -247 -> 336
    //   586: iconst_m1
    //   587: istore 21
    //   589: aconst_null
    //   590: astore 4
    //   592: goto -423 -> 169
    //   595: aconst_null
    //   596: astore 27
    //   598: iconst_0
    //   599: istore 28
    //   601: goto -449 -> 152
    //   604: iconst_m1
    //   605: istore_3
    //   606: aconst_null
    //   607: astore 4
    //   609: goto -425 -> 184
    //   612: iload 18
    //   614: ifne +7 -> 621
    //   617: ldc 127
    //   619: astore 17
    //   621: aload 17
    //   623: astore 4
    //   625: bipush 80
    //   627: istore 15
    //   629: goto -198 -> 431
    //   632: astore 13
    //   634: aconst_null
    //   635: astore 12
    //   637: goto -153 -> 484
    //
    // Exception table:
    //   from	to	target	type
    //   28	41	356	java/lang/SecurityException
    //   28	41	509	finally
    //   50	78	535	finally
    //   83	107	535	finally
    //   112	144	535	finally
    //   296	328	535	finally
    //   361	411	535	finally
    //   449	478	535	finally
    //   484	489	535	finally
    //   50	78	540	java/lang/Exception
    //   83	107	540	java/lang/Exception
    //   112	144	540	java/lang/Exception
    //   296	328	540	java/lang/Exception
    //   50	78	545	java/lang/SecurityException
    //   83	107	545	java/lang/SecurityException
    //   112	144	545	java/lang/SecurityException
    //   296	328	545	java/lang/SecurityException
    //   28	41	632	java/lang/Exception
  }

  private static boolean a(HttpResponse paramHttpResponse)
  {
    Header localHeader = paramHttpResponse.getFirstHeader("Content-Encoding");
    return (localHeader != null) && (localHeader.getValue().equalsIgnoreCase("gzip"));
  }

  public static String[] a(JSONObject paramJSONObject)
  {
    String[] arrayOfString = { null, null, null, null, null };
    if (paramJSONObject == null)
      arrayOfString[0] = "false";
    while (true)
    {
      return arrayOfString;
      try
      {
        String str1 = paramJSONObject.getString("key");
        String str2 = paramJSONObject.getString("X-INFO");
        String str3 = paramJSONObject.getString("X-BIZ");
        String str4 = paramJSONObject.getString("User-Agent");
        if ((!TextUtils.isEmpty(str1)) && (!TextUtils.isEmpty(str2)) && (!TextUtils.isEmpty(str4)))
        {
          arrayOfString[0] = "true";
          arrayOfString[1] = str1;
          arrayOfString[2] = str2;
          arrayOfString[3] = str3;
          arrayOfString[4] = str4;
        }
        label114: if ((arrayOfString[0] != null) && (arrayOfString[0].equals("true")))
          continue;
        arrayOfString[0] = "false";
        return arrayOfString;
      }
      catch (JSONException localJSONException)
      {
        break label114;
      }
    }
  }

  private static String b()
  {
    try
    {
      String str2 = ((String)l.a("android.net.Proxy", "getDefaultHost", null, null)).toString();
      str1 = str2;
      if (str1 == null)
        str1 = "null";
      return str1;
    }
    catch (Exception localException)
    {
      while (true)
        String str1 = null;
    }
  }

  // ERROR //
  public String a(android.content.Context paramContext, String paramString, byte[] paramArrayOfByte)
  {
    // Byte code:
    //   0: aload_0
    //   1: monitorenter
    //   2: aload_2
    //   3: invokestatic 119	android/text/TextUtils:isEmpty	(Ljava/lang/CharSequence;)Z
    //   6: istore 5
    //   8: aconst_null
    //   9: astore 6
    //   11: iload 5
    //   13: ifne +10 -> 23
    //   16: aconst_null
    //   17: astore 6
    //   19: aload_3
    //   20: ifnonnull +8 -> 28
    //   23: aload_0
    //   24: monitorexit
    //   25: aload 6
    //   27: areturn
    //   28: aload_1
    //   29: invokestatic 262	com/aps/n:b	(Landroid/content/Context;)Landroid/net/NetworkInfo;
    //   32: astore 7
    //   34: aload 7
    //   36: invokestatic 264	com/aps/j:a	(Landroid/net/NetworkInfo;)I
    //   39: istore 8
    //   41: aconst_null
    //   42: astore 6
    //   44: iload 8
    //   46: iconst_m1
    //   47: if_icmpeq -24 -> 23
    //   50: new 266	java/lang/StringBuffer
    //   53: dup
    //   54: invokespecial 267	java/lang/StringBuffer:<init>	()V
    //   57: astore 9
    //   59: ldc_w 269
    //   62: astore 10
    //   64: aload_1
    //   65: aload 7
    //   67: invokestatic 271	com/aps/j:a	(Landroid/content/Context;Landroid/net/NetworkInfo;)Lorg/apache/http/client/HttpClient;
    //   70: astore 45
    //   72: aload 45
    //   74: astore 17
    //   76: new 273	org/apache/http/client/methods/HttpPost
    //   79: dup
    //   80: aload_2
    //   81: invokespecial 276	org/apache/http/client/methods/HttpPost:<init>	(Ljava/lang/String;)V
    //   84: astore 16
    //   86: new 278	org/apache/http/entity/ByteArrayEntity
    //   89: dup
    //   90: aload_3
    //   91: invokespecial 281	org/apache/http/entity/ByteArrayEntity:<init>	([B)V
    //   94: astore 46
    //   96: aload 16
    //   98: ldc_w 283
    //   101: ldc_w 285
    //   104: invokevirtual 289	org/apache/http/client/methods/HttpPost:addHeader	(Ljava/lang/String;Ljava/lang/String;)V
    //   107: aload 16
    //   109: ldc 236
    //   111: getstatic 294	com/amap/api/location/core/c:b	Ljava/lang/String;
    //   114: invokevirtual 289	org/apache/http/client/methods/HttpPost:addHeader	(Ljava/lang/String;Ljava/lang/String;)V
    //   117: aload 16
    //   119: ldc_w 296
    //   122: ldc 214
    //   124: invokevirtual 289	org/apache/http/client/methods/HttpPost:addHeader	(Ljava/lang/String;Ljava/lang/String;)V
    //   127: aload 16
    //   129: ldc_w 298
    //   132: ldc_w 300
    //   135: invokevirtual 289	org/apache/http/client/methods/HttpPost:addHeader	(Ljava/lang/String;Ljava/lang/String;)V
    //   138: aload 16
    //   140: ldc 232
    //   142: aconst_null
    //   143: invokestatic 305	com/amap/api/location/core/b:a	(Landroid/content/Context;)Lcom/amap/api/location/core/b;
    //   146: invokevirtual 306	com/amap/api/location/core/b:b	()Ljava/lang/String;
    //   149: invokevirtual 289	org/apache/http/client/methods/HttpPost:addHeader	(Ljava/lang/String;Ljava/lang/String;)V
    //   152: aload 16
    //   154: ldc_w 308
    //   157: ldc_w 310
    //   160: invokevirtual 289	org/apache/http/client/methods/HttpPost:addHeader	(Ljava/lang/String;Ljava/lang/String;)V
    //   163: aload 16
    //   165: ldc 225
    //   167: getstatic 312	com/amap/api/location/core/b:a	Ljava/lang/String;
    //   170: invokevirtual 289	org/apache/http/client/methods/HttpPost:addHeader	(Ljava/lang/String;Ljava/lang/String;)V
    //   173: aload 9
    //   175: iconst_0
    //   176: aload 9
    //   178: invokevirtual 313	java/lang/StringBuffer:length	()I
    //   181: invokevirtual 317	java/lang/StringBuffer:delete	(II)Ljava/lang/StringBuffer;
    //   184: pop
    //   185: aload 16
    //   187: aload 46
    //   189: invokevirtual 321	org/apache/http/client/methods/HttpPost:setEntity	(Lorg/apache/http/HttpEntity;)V
    //   192: aload 17
    //   194: aload 16
    //   196: invokeinterface 327 2 0
    //   201: astore 54
    //   203: aload 54
    //   205: invokeinterface 331 1 0
    //   210: invokeinterface 336 1 0
    //   215: sipush 200
    //   218: if_icmpne +1426 -> 1644
    //   221: aload 54
    //   223: invokeinterface 340 1 0
    //   228: invokeinterface 346 1 0
    //   233: astore 58
    //   235: aload 58
    //   237: astore 15
    //   239: aload 54
    //   241: invokeinterface 340 1 0
    //   246: invokeinterface 350 1 0
    //   251: invokeinterface 212 1 0
    //   256: astore 65
    //   258: ldc_w 269
    //   261: astore 66
    //   263: aload 65
    //   265: ldc_w 352
    //   268: invokevirtual 195	java/lang/String:indexOf	(Ljava/lang/String;)I
    //   271: istore 67
    //   273: iload 67
    //   275: iconst_m1
    //   276: if_icmpeq +15 -> 291
    //   279: aload 65
    //   281: iload 67
    //   283: bipush 8
    //   285: iadd
    //   286: invokevirtual 355	java/lang/String:substring	(I)Ljava/lang/String;
    //   289: astore 66
    //   291: aload 66
    //   293: invokestatic 119	android/text/TextUtils:isEmpty	(Ljava/lang/CharSequence;)Z
    //   296: ifeq +8 -> 304
    //   299: ldc_w 357
    //   302: astore 66
    //   304: aload 54
    //   306: invokestatic 359	com/aps/j:a	(Lorg/apache/http/HttpResponse;)Z
    //   309: ifeq +1329 -> 1638
    //   312: new 361	java/util/zip/GZIPInputStream
    //   315: dup
    //   316: aload 15
    //   318: invokespecial 364	java/util/zip/GZIPInputStream:<init>	(Ljava/io/InputStream;)V
    //   321: astore 14
    //   323: aload 14
    //   325: ifnull +144 -> 469
    //   328: new 366	java/io/InputStreamReader
    //   331: dup
    //   332: aload 14
    //   334: aload 66
    //   336: invokespecial 369	java/io/InputStreamReader:<init>	(Ljava/io/InputStream;Ljava/lang/String;)V
    //   339: astore 13
    //   341: new 371	java/io/BufferedReader
    //   344: dup
    //   345: aload 13
    //   347: sipush 2048
    //   350: invokespecial 374	java/io/BufferedReader:<init>	(Ljava/io/Reader;I)V
    //   353: astore 12
    //   355: aload 12
    //   357: invokevirtual 377	java/io/BufferedReader:readLine	()Ljava/lang/String;
    //   360: astore 73
    //   362: aload 73
    //   364: ifnull +132 -> 496
    //   367: aload 9
    //   369: aload 73
    //   371: invokevirtual 381	java/lang/StringBuffer:append	(Ljava/lang/String;)Ljava/lang/StringBuffer;
    //   374: pop
    //   375: goto -20 -> 355
    //   378: astore 72
    //   380: aload 16
    //   382: ifnull +8 -> 390
    //   385: aload 16
    //   387: invokevirtual 384	org/apache/http/client/methods/HttpPost:abort	()V
    //   390: aload 17
    //   392: ifnull +15 -> 407
    //   395: aload 17
    //   397: invokeinterface 388 1 0
    //   402: invokeinterface 393 1 0
    //   407: aload 14
    //   409: ifnull +8 -> 417
    //   412: aload 14
    //   414: invokevirtual 394	java/util/zip/GZIPInputStream:close	()V
    //   417: aload 15
    //   419: ifnull +8 -> 427
    //   422: aload 15
    //   424: invokevirtual 397	java/io/InputStream:close	()V
    //   427: aload 13
    //   429: ifnull +8 -> 437
    //   432: aload 13
    //   434: invokevirtual 398	java/io/InputStreamReader:close	()V
    //   437: aload 12
    //   439: ifnull +8 -> 447
    //   442: aload 12
    //   444: invokevirtual 399	java/io/BufferedReader:close	()V
    //   447: aload 10
    //   449: invokestatic 119	android/text/TextUtils:isEmpty	(Ljava/lang/CharSequence;)Z
    //   452: istore 18
    //   454: aconst_null
    //   455: astore 6
    //   457: iload 18
    //   459: ifne -436 -> 23
    //   462: aload 10
    //   464: astore 6
    //   466: goto -443 -> 23
    //   469: new 366	java/io/InputStreamReader
    //   472: dup
    //   473: aload 15
    //   475: aload 66
    //   477: invokespecial 369	java/io/InputStreamReader:<init>	(Ljava/io/InputStream;Ljava/lang/String;)V
    //   480: astore 13
    //   482: goto -141 -> 341
    //   485: astore 87
    //   487: aconst_null
    //   488: astore 12
    //   490: aconst_null
    //   491: astore 13
    //   493: goto -113 -> 380
    //   496: aload 9
    //   498: invokevirtual 400	java/lang/StringBuffer:toString	()Ljava/lang/String;
    //   501: astore 10
    //   503: aload 9
    //   505: iconst_0
    //   506: aload 9
    //   508: invokevirtual 313	java/lang/StringBuffer:length	()I
    //   511: invokevirtual 317	java/lang/StringBuffer:delete	(II)Ljava/lang/StringBuffer;
    //   514: pop
    //   515: aload 16
    //   517: ifnull +8 -> 525
    //   520: aload 16
    //   522: invokevirtual 384	org/apache/http/client/methods/HttpPost:abort	()V
    //   525: aload 17
    //   527: ifnull +15 -> 542
    //   530: aload 17
    //   532: invokeinterface 388 1 0
    //   537: invokeinterface 393 1 0
    //   542: aload 14
    //   544: ifnull +8 -> 552
    //   547: aload 14
    //   549: invokevirtual 394	java/util/zip/GZIPInputStream:close	()V
    //   552: aload 15
    //   554: ifnull +8 -> 562
    //   557: aload 15
    //   559: invokevirtual 397	java/io/InputStream:close	()V
    //   562: aload 13
    //   564: ifnull +8 -> 572
    //   567: aload 13
    //   569: invokevirtual 398	java/io/InputStreamReader:close	()V
    //   572: aload 12
    //   574: ifnull -127 -> 447
    //   577: aload 12
    //   579: invokevirtual 399	java/io/BufferedReader:close	()V
    //   582: goto -135 -> 447
    //   585: astore 19
    //   587: goto -140 -> 447
    //   590: astore 39
    //   592: aconst_null
    //   593: astore 12
    //   595: aconst_null
    //   596: astore 13
    //   598: aconst_null
    //   599: astore 14
    //   601: aconst_null
    //   602: astore 15
    //   604: aconst_null
    //   605: astore 16
    //   607: aconst_null
    //   608: astore 17
    //   610: aload 39
    //   612: astore 40
    //   614: aload 16
    //   616: ifnull +8 -> 624
    //   619: aload 16
    //   621: invokevirtual 384	org/apache/http/client/methods/HttpPost:abort	()V
    //   624: aload 17
    //   626: ifnull +15 -> 641
    //   629: aload 17
    //   631: invokeinterface 388 1 0
    //   636: invokeinterface 393 1 0
    //   641: aload 14
    //   643: ifnull +8 -> 651
    //   646: aload 14
    //   648: invokevirtual 394	java/util/zip/GZIPInputStream:close	()V
    //   651: aload 15
    //   653: ifnull +8 -> 661
    //   656: aload 15
    //   658: invokevirtual 397	java/io/InputStream:close	()V
    //   661: aload 13
    //   663: ifnull +8 -> 671
    //   666: aload 13
    //   668: invokevirtual 398	java/io/InputStreamReader:close	()V
    //   671: aload 12
    //   673: ifnull +8 -> 681
    //   676: aload 12
    //   678: invokevirtual 399	java/io/BufferedReader:close	()V
    //   681: aload 40
    //   683: athrow
    //   684: astore 4
    //   686: aload_0
    //   687: monitorexit
    //   688: aload 4
    //   690: athrow
    //   691: astore 22
    //   693: goto -276 -> 417
    //   696: astore 21
    //   698: goto -271 -> 427
    //   701: astore 20
    //   703: goto -266 -> 437
    //   706: astore 35
    //   708: aconst_null
    //   709: astore 12
    //   711: aconst_null
    //   712: astore 13
    //   714: aconst_null
    //   715: astore 14
    //   717: aconst_null
    //   718: astore 15
    //   720: aconst_null
    //   721: astore 16
    //   723: aconst_null
    //   724: astore 17
    //   726: aload 16
    //   728: ifnull +8 -> 736
    //   731: aload 16
    //   733: invokevirtual 384	org/apache/http/client/methods/HttpPost:abort	()V
    //   736: aload 17
    //   738: ifnull +15 -> 753
    //   741: aload 17
    //   743: invokeinterface 388 1 0
    //   748: invokeinterface 393 1 0
    //   753: aload 14
    //   755: ifnull +8 -> 763
    //   758: aload 14
    //   760: invokevirtual 394	java/util/zip/GZIPInputStream:close	()V
    //   763: aload 15
    //   765: ifnull +8 -> 773
    //   768: aload 15
    //   770: invokevirtual 397	java/io/InputStream:close	()V
    //   773: aload 13
    //   775: ifnull +8 -> 783
    //   778: aload 13
    //   780: invokevirtual 398	java/io/InputStreamReader:close	()V
    //   783: aload 12
    //   785: ifnull -338 -> 447
    //   788: aload 12
    //   790: invokevirtual 399	java/io/BufferedReader:close	()V
    //   793: goto -346 -> 447
    //   796: astore 38
    //   798: goto -35 -> 763
    //   801: astore 37
    //   803: goto -30 -> 773
    //   806: astore 36
    //   808: goto -25 -> 783
    //   811: astore 31
    //   813: aconst_null
    //   814: astore 12
    //   816: aconst_null
    //   817: astore 13
    //   819: aconst_null
    //   820: astore 14
    //   822: aconst_null
    //   823: astore 15
    //   825: aconst_null
    //   826: astore 16
    //   828: aconst_null
    //   829: astore 17
    //   831: aload 16
    //   833: ifnull +8 -> 841
    //   836: aload 16
    //   838: invokevirtual 384	org/apache/http/client/methods/HttpPost:abort	()V
    //   841: aload 17
    //   843: ifnull +15 -> 858
    //   846: aload 17
    //   848: invokeinterface 388 1 0
    //   853: invokeinterface 393 1 0
    //   858: aload 14
    //   860: ifnull +8 -> 868
    //   863: aload 14
    //   865: invokevirtual 394	java/util/zip/GZIPInputStream:close	()V
    //   868: aload 15
    //   870: ifnull +8 -> 878
    //   873: aload 15
    //   875: invokevirtual 397	java/io/InputStream:close	()V
    //   878: aload 13
    //   880: ifnull +8 -> 888
    //   883: aload 13
    //   885: invokevirtual 398	java/io/InputStreamReader:close	()V
    //   888: aload 12
    //   890: ifnull -443 -> 447
    //   893: aload 12
    //   895: invokevirtual 399	java/io/BufferedReader:close	()V
    //   898: goto -451 -> 447
    //   901: astore 34
    //   903: goto -35 -> 868
    //   906: astore 33
    //   908: goto -30 -> 878
    //   911: astore 32
    //   913: goto -25 -> 888
    //   916: astore 27
    //   918: aconst_null
    //   919: astore 12
    //   921: aconst_null
    //   922: astore 13
    //   924: aconst_null
    //   925: astore 14
    //   927: aconst_null
    //   928: astore 15
    //   930: aconst_null
    //   931: astore 16
    //   933: aconst_null
    //   934: astore 17
    //   936: aload 16
    //   938: ifnull +8 -> 946
    //   941: aload 16
    //   943: invokevirtual 384	org/apache/http/client/methods/HttpPost:abort	()V
    //   946: aload 17
    //   948: ifnull +15 -> 963
    //   951: aload 17
    //   953: invokeinterface 388 1 0
    //   958: invokeinterface 393 1 0
    //   963: aload 14
    //   965: ifnull +8 -> 973
    //   968: aload 14
    //   970: invokevirtual 394	java/util/zip/GZIPInputStream:close	()V
    //   973: aload 15
    //   975: ifnull +8 -> 983
    //   978: aload 15
    //   980: invokevirtual 397	java/io/InputStream:close	()V
    //   983: aload 13
    //   985: ifnull +8 -> 993
    //   988: aload 13
    //   990: invokevirtual 398	java/io/InputStreamReader:close	()V
    //   993: aload 12
    //   995: ifnull -548 -> 447
    //   998: aload 12
    //   1000: invokevirtual 399	java/io/BufferedReader:close	()V
    //   1003: goto -556 -> 447
    //   1006: astore 30
    //   1008: goto -35 -> 973
    //   1011: astore 29
    //   1013: goto -30 -> 983
    //   1016: astore 28
    //   1018: goto -25 -> 993
    //   1021: astore 23
    //   1023: aconst_null
    //   1024: astore 12
    //   1026: aconst_null
    //   1027: astore 13
    //   1029: aconst_null
    //   1030: astore 14
    //   1032: aconst_null
    //   1033: astore 15
    //   1035: aconst_null
    //   1036: astore 16
    //   1038: aconst_null
    //   1039: astore 17
    //   1041: aload 16
    //   1043: ifnull +8 -> 1051
    //   1046: aload 16
    //   1048: invokevirtual 384	org/apache/http/client/methods/HttpPost:abort	()V
    //   1051: aload 17
    //   1053: ifnull +15 -> 1068
    //   1056: aload 17
    //   1058: invokeinterface 388 1 0
    //   1063: invokeinterface 393 1 0
    //   1068: aload 14
    //   1070: ifnull +8 -> 1078
    //   1073: aload 14
    //   1075: invokevirtual 394	java/util/zip/GZIPInputStream:close	()V
    //   1078: aload 15
    //   1080: ifnull +8 -> 1088
    //   1083: aload 15
    //   1085: invokevirtual 397	java/io/InputStream:close	()V
    //   1088: aload 13
    //   1090: ifnull +8 -> 1098
    //   1093: aload 13
    //   1095: invokevirtual 398	java/io/InputStreamReader:close	()V
    //   1098: aload 12
    //   1100: ifnull -653 -> 447
    //   1103: aload 12
    //   1105: invokevirtual 399	java/io/BufferedReader:close	()V
    //   1108: goto -661 -> 447
    //   1111: astore 26
    //   1113: goto -35 -> 1078
    //   1116: astore 25
    //   1118: goto -30 -> 1088
    //   1121: astore 24
    //   1123: goto -25 -> 1098
    //   1126: astore 44
    //   1128: goto -477 -> 651
    //   1131: astore 43
    //   1133: goto -472 -> 661
    //   1136: astore 42
    //   1138: goto -467 -> 671
    //   1141: astore 41
    //   1143: goto -462 -> 681
    //   1146: astore 57
    //   1148: goto -596 -> 552
    //   1151: astore 56
    //   1153: goto -591 -> 562
    //   1156: astore 55
    //   1158: goto -586 -> 572
    //   1161: astore 93
    //   1163: aload 93
    //   1165: astore 40
    //   1167: aconst_null
    //   1168: astore 12
    //   1170: aconst_null
    //   1171: astore 13
    //   1173: aconst_null
    //   1174: astore 14
    //   1176: aconst_null
    //   1177: astore 15
    //   1179: aconst_null
    //   1180: astore 16
    //   1182: goto -568 -> 614
    //   1185: astore 52
    //   1187: aload 52
    //   1189: astore 40
    //   1191: aconst_null
    //   1192: astore 12
    //   1194: aconst_null
    //   1195: astore 13
    //   1197: aconst_null
    //   1198: astore 14
    //   1200: aconst_null
    //   1201: astore 15
    //   1203: goto -589 -> 614
    //   1206: astore 64
    //   1208: aload 64
    //   1210: astore 40
    //   1212: aconst_null
    //   1213: astore 12
    //   1215: aconst_null
    //   1216: astore 13
    //   1218: aconst_null
    //   1219: astore 14
    //   1221: goto -607 -> 614
    //   1224: astore 86
    //   1226: aload 86
    //   1228: astore 40
    //   1230: aconst_null
    //   1231: astore 12
    //   1233: aconst_null
    //   1234: astore 13
    //   1236: goto -622 -> 614
    //   1239: astore 81
    //   1241: aload 81
    //   1243: astore 40
    //   1245: aconst_null
    //   1246: astore 12
    //   1248: goto -634 -> 614
    //   1251: astore 40
    //   1253: goto -639 -> 614
    //   1256: astore 92
    //   1258: aconst_null
    //   1259: astore 12
    //   1261: aconst_null
    //   1262: astore 13
    //   1264: aconst_null
    //   1265: astore 14
    //   1267: aconst_null
    //   1268: astore 15
    //   1270: aconst_null
    //   1271: astore 16
    //   1273: goto -232 -> 1041
    //   1276: astore 51
    //   1278: aconst_null
    //   1279: astore 12
    //   1281: aconst_null
    //   1282: astore 13
    //   1284: aconst_null
    //   1285: astore 14
    //   1287: aconst_null
    //   1288: astore 15
    //   1290: goto -249 -> 1041
    //   1293: astore 63
    //   1295: aconst_null
    //   1296: astore 12
    //   1298: aconst_null
    //   1299: astore 13
    //   1301: aconst_null
    //   1302: astore 14
    //   1304: goto -263 -> 1041
    //   1307: astore 85
    //   1309: aconst_null
    //   1310: astore 12
    //   1312: aconst_null
    //   1313: astore 13
    //   1315: goto -274 -> 1041
    //   1318: astore 80
    //   1320: aconst_null
    //   1321: astore 12
    //   1323: goto -282 -> 1041
    //   1326: astore 71
    //   1328: goto -287 -> 1041
    //   1331: astore 91
    //   1333: aconst_null
    //   1334: astore 12
    //   1336: aconst_null
    //   1337: astore 13
    //   1339: aconst_null
    //   1340: astore 14
    //   1342: aconst_null
    //   1343: astore 15
    //   1345: aconst_null
    //   1346: astore 16
    //   1348: goto -412 -> 936
    //   1351: astore 50
    //   1353: aconst_null
    //   1354: astore 12
    //   1356: aconst_null
    //   1357: astore 13
    //   1359: aconst_null
    //   1360: astore 14
    //   1362: aconst_null
    //   1363: astore 15
    //   1365: goto -429 -> 936
    //   1368: astore 62
    //   1370: aconst_null
    //   1371: astore 12
    //   1373: aconst_null
    //   1374: astore 13
    //   1376: aconst_null
    //   1377: astore 14
    //   1379: goto -443 -> 936
    //   1382: astore 84
    //   1384: aconst_null
    //   1385: astore 12
    //   1387: aconst_null
    //   1388: astore 13
    //   1390: goto -454 -> 936
    //   1393: astore 79
    //   1395: aconst_null
    //   1396: astore 12
    //   1398: goto -462 -> 936
    //   1401: astore 70
    //   1403: goto -467 -> 936
    //   1406: astore 90
    //   1408: aconst_null
    //   1409: astore 12
    //   1411: aconst_null
    //   1412: astore 13
    //   1414: aconst_null
    //   1415: astore 14
    //   1417: aconst_null
    //   1418: astore 15
    //   1420: aconst_null
    //   1421: astore 16
    //   1423: goto -592 -> 831
    //   1426: astore 49
    //   1428: aconst_null
    //   1429: astore 12
    //   1431: aconst_null
    //   1432: astore 13
    //   1434: aconst_null
    //   1435: astore 14
    //   1437: aconst_null
    //   1438: astore 15
    //   1440: goto -609 -> 831
    //   1443: astore 61
    //   1445: aconst_null
    //   1446: astore 12
    //   1448: aconst_null
    //   1449: astore 13
    //   1451: aconst_null
    //   1452: astore 14
    //   1454: goto -623 -> 831
    //   1457: astore 83
    //   1459: aconst_null
    //   1460: astore 12
    //   1462: aconst_null
    //   1463: astore 13
    //   1465: goto -634 -> 831
    //   1468: astore 78
    //   1470: aconst_null
    //   1471: astore 12
    //   1473: goto -642 -> 831
    //   1476: astore 69
    //   1478: goto -647 -> 831
    //   1481: astore 89
    //   1483: aconst_null
    //   1484: astore 12
    //   1486: aconst_null
    //   1487: astore 13
    //   1489: aconst_null
    //   1490: astore 14
    //   1492: aconst_null
    //   1493: astore 15
    //   1495: aconst_null
    //   1496: astore 16
    //   1498: goto -772 -> 726
    //   1501: astore 48
    //   1503: aconst_null
    //   1504: astore 12
    //   1506: aconst_null
    //   1507: astore 13
    //   1509: aconst_null
    //   1510: astore 14
    //   1512: aconst_null
    //   1513: astore 15
    //   1515: goto -789 -> 726
    //   1518: astore 60
    //   1520: aconst_null
    //   1521: astore 12
    //   1523: aconst_null
    //   1524: astore 13
    //   1526: aconst_null
    //   1527: astore 14
    //   1529: goto -803 -> 726
    //   1532: astore 82
    //   1534: aconst_null
    //   1535: astore 12
    //   1537: aconst_null
    //   1538: astore 13
    //   1540: goto -814 -> 726
    //   1543: astore 77
    //   1545: aconst_null
    //   1546: astore 12
    //   1548: goto -822 -> 726
    //   1551: astore 68
    //   1553: goto -827 -> 726
    //   1556: astore 11
    //   1558: aconst_null
    //   1559: astore 12
    //   1561: aconst_null
    //   1562: astore 13
    //   1564: aconst_null
    //   1565: astore 14
    //   1567: aconst_null
    //   1568: astore 15
    //   1570: aconst_null
    //   1571: astore 16
    //   1573: aconst_null
    //   1574: astore 17
    //   1576: goto -1196 -> 380
    //   1579: astore 88
    //   1581: aconst_null
    //   1582: astore 12
    //   1584: aconst_null
    //   1585: astore 13
    //   1587: aconst_null
    //   1588: astore 14
    //   1590: aconst_null
    //   1591: astore 15
    //   1593: aconst_null
    //   1594: astore 16
    //   1596: goto -1216 -> 380
    //   1599: astore 47
    //   1601: aconst_null
    //   1602: astore 12
    //   1604: aconst_null
    //   1605: astore 13
    //   1607: aconst_null
    //   1608: astore 14
    //   1610: aconst_null
    //   1611: astore 15
    //   1613: goto -1233 -> 380
    //   1616: astore 59
    //   1618: aconst_null
    //   1619: astore 12
    //   1621: aconst_null
    //   1622: astore 13
    //   1624: aconst_null
    //   1625: astore 14
    //   1627: goto -1247 -> 380
    //   1630: astore 76
    //   1632: aconst_null
    //   1633: astore 12
    //   1635: goto -1255 -> 380
    //   1638: aconst_null
    //   1639: astore 14
    //   1641: goto -1318 -> 323
    //   1644: aconst_null
    //   1645: astore 12
    //   1647: aconst_null
    //   1648: astore 13
    //   1650: aconst_null
    //   1651: astore 14
    //   1653: aconst_null
    //   1654: astore 15
    //   1656: goto -1141 -> 515
    //
    // Exception table:
    //   from	to	target	type
    //   355	362	378	java/net/UnknownHostException
    //   367	375	378	java/net/UnknownHostException
    //   496	515	378	java/net/UnknownHostException
    //   328	341	485	java/net/UnknownHostException
    //   469	482	485	java/net/UnknownHostException
    //   442	447	585	java/lang/Exception
    //   577	582	585	java/lang/Exception
    //   788	793	585	java/lang/Exception
    //   893	898	585	java/lang/Exception
    //   998	1003	585	java/lang/Exception
    //   1103	1108	585	java/lang/Exception
    //   64	72	590	finally
    //   2	8	684	finally
    //   28	41	684	finally
    //   50	59	684	finally
    //   385	390	684	finally
    //   395	407	684	finally
    //   412	417	684	finally
    //   422	427	684	finally
    //   432	437	684	finally
    //   442	447	684	finally
    //   447	454	684	finally
    //   520	525	684	finally
    //   530	542	684	finally
    //   547	552	684	finally
    //   557	562	684	finally
    //   567	572	684	finally
    //   577	582	684	finally
    //   619	624	684	finally
    //   629	641	684	finally
    //   646	651	684	finally
    //   656	661	684	finally
    //   666	671	684	finally
    //   676	681	684	finally
    //   681	684	684	finally
    //   731	736	684	finally
    //   741	753	684	finally
    //   758	763	684	finally
    //   768	773	684	finally
    //   778	783	684	finally
    //   788	793	684	finally
    //   836	841	684	finally
    //   846	858	684	finally
    //   863	868	684	finally
    //   873	878	684	finally
    //   883	888	684	finally
    //   893	898	684	finally
    //   941	946	684	finally
    //   951	963	684	finally
    //   968	973	684	finally
    //   978	983	684	finally
    //   988	993	684	finally
    //   998	1003	684	finally
    //   1046	1051	684	finally
    //   1056	1068	684	finally
    //   1073	1078	684	finally
    //   1083	1088	684	finally
    //   1093	1098	684	finally
    //   1103	1108	684	finally
    //   412	417	691	java/lang/Exception
    //   422	427	696	java/lang/Exception
    //   432	437	701	java/lang/Exception
    //   64	72	706	java/net/SocketException
    //   758	763	796	java/lang/Exception
    //   768	773	801	java/lang/Exception
    //   778	783	806	java/lang/Exception
    //   64	72	811	java/net/SocketTimeoutException
    //   863	868	901	java/lang/Exception
    //   873	878	906	java/lang/Exception
    //   883	888	911	java/lang/Exception
    //   64	72	916	org/apache/http/conn/ConnectTimeoutException
    //   968	973	1006	java/lang/Exception
    //   978	983	1011	java/lang/Exception
    //   988	993	1016	java/lang/Exception
    //   64	72	1021	java/lang/Exception
    //   1073	1078	1111	java/lang/Exception
    //   1083	1088	1116	java/lang/Exception
    //   1093	1098	1121	java/lang/Exception
    //   646	651	1126	java/lang/Exception
    //   656	661	1131	java/lang/Exception
    //   666	671	1136	java/lang/Exception
    //   676	681	1141	java/lang/Exception
    //   547	552	1146	java/lang/Exception
    //   557	562	1151	java/lang/Exception
    //   567	572	1156	java/lang/Exception
    //   76	86	1161	finally
    //   86	235	1185	finally
    //   239	258	1206	finally
    //   263	273	1206	finally
    //   279	291	1206	finally
    //   291	299	1206	finally
    //   304	323	1206	finally
    //   328	341	1224	finally
    //   469	482	1224	finally
    //   341	355	1239	finally
    //   355	362	1251	finally
    //   367	375	1251	finally
    //   496	515	1251	finally
    //   76	86	1256	java/lang/Exception
    //   86	235	1276	java/lang/Exception
    //   239	258	1293	java/lang/Exception
    //   263	273	1293	java/lang/Exception
    //   279	291	1293	java/lang/Exception
    //   291	299	1293	java/lang/Exception
    //   304	323	1293	java/lang/Exception
    //   328	341	1307	java/lang/Exception
    //   469	482	1307	java/lang/Exception
    //   341	355	1318	java/lang/Exception
    //   355	362	1326	java/lang/Exception
    //   367	375	1326	java/lang/Exception
    //   496	515	1326	java/lang/Exception
    //   76	86	1331	org/apache/http/conn/ConnectTimeoutException
    //   86	235	1351	org/apache/http/conn/ConnectTimeoutException
    //   239	258	1368	org/apache/http/conn/ConnectTimeoutException
    //   263	273	1368	org/apache/http/conn/ConnectTimeoutException
    //   279	291	1368	org/apache/http/conn/ConnectTimeoutException
    //   291	299	1368	org/apache/http/conn/ConnectTimeoutException
    //   304	323	1368	org/apache/http/conn/ConnectTimeoutException
    //   328	341	1382	org/apache/http/conn/ConnectTimeoutException
    //   469	482	1382	org/apache/http/conn/ConnectTimeoutException
    //   341	355	1393	org/apache/http/conn/ConnectTimeoutException
    //   355	362	1401	org/apache/http/conn/ConnectTimeoutException
    //   367	375	1401	org/apache/http/conn/ConnectTimeoutException
    //   496	515	1401	org/apache/http/conn/ConnectTimeoutException
    //   76	86	1406	java/net/SocketTimeoutException
    //   86	235	1426	java/net/SocketTimeoutException
    //   239	258	1443	java/net/SocketTimeoutException
    //   263	273	1443	java/net/SocketTimeoutException
    //   279	291	1443	java/net/SocketTimeoutException
    //   291	299	1443	java/net/SocketTimeoutException
    //   304	323	1443	java/net/SocketTimeoutException
    //   328	341	1457	java/net/SocketTimeoutException
    //   469	482	1457	java/net/SocketTimeoutException
    //   341	355	1468	java/net/SocketTimeoutException
    //   355	362	1476	java/net/SocketTimeoutException
    //   367	375	1476	java/net/SocketTimeoutException
    //   496	515	1476	java/net/SocketTimeoutException
    //   76	86	1481	java/net/SocketException
    //   86	235	1501	java/net/SocketException
    //   239	258	1518	java/net/SocketException
    //   263	273	1518	java/net/SocketException
    //   279	291	1518	java/net/SocketException
    //   291	299	1518	java/net/SocketException
    //   304	323	1518	java/net/SocketException
    //   328	341	1532	java/net/SocketException
    //   469	482	1532	java/net/SocketException
    //   341	355	1543	java/net/SocketException
    //   355	362	1551	java/net/SocketException
    //   367	375	1551	java/net/SocketException
    //   496	515	1551	java/net/SocketException
    //   64	72	1556	java/net/UnknownHostException
    //   76	86	1579	java/net/UnknownHostException
    //   86	235	1599	java/net/UnknownHostException
    //   239	258	1616	java/net/UnknownHostException
    //   263	273	1616	java/net/UnknownHostException
    //   279	291	1616	java/net/UnknownHostException
    //   291	299	1616	java/net/UnknownHostException
    //   304	323	1616	java/net/UnknownHostException
    //   341	355	1630	java/net/UnknownHostException
  }

  // ERROR //
  public String a(String paramString, android.content.Context paramContext, JSONObject paramJSONObject)
  {
    // Byte code:
    //   0: aload_0
    //   1: monitorenter
    //   2: aload_2
    //   3: invokestatic 262	com/aps/n:b	(Landroid/content/Context;)Landroid/net/NetworkInfo;
    //   6: astore 5
    //   8: aload 5
    //   10: invokestatic 264	com/aps/j:a	(Landroid/net/NetworkInfo;)I
    //   13: istore 6
    //   15: iload 6
    //   17: iconst_m1
    //   18: if_icmpne +11 -> 29
    //   21: aconst_null
    //   22: astore 19
    //   24: aload_0
    //   25: monitorexit
    //   26: aload 19
    //   28: areturn
    //   29: new 266	java/lang/StringBuffer
    //   32: dup
    //   33: invokespecial 267	java/lang/StringBuffer:<init>	()V
    //   36: astore 7
    //   38: iconst_0
    //   39: istore 8
    //   41: iconst_0
    //   42: istore 9
    //   44: ldc_w 269
    //   47: astore 10
    //   49: aload 7
    //   51: astore 11
    //   53: aconst_null
    //   54: astore 12
    //   56: aconst_null
    //   57: astore 13
    //   59: aconst_null
    //   60: astore 14
    //   62: aconst_null
    //   63: astore 15
    //   65: aconst_null
    //   66: astore 16
    //   68: aconst_null
    //   69: astore 17
    //   71: aload_1
    //   72: astore 18
    //   74: iload 8
    //   76: iconst_2
    //   77: if_icmpge +815 -> 892
    //   80: iload 9
    //   82: ifne +810 -> 892
    //   85: aload_2
    //   86: aload 5
    //   88: invokestatic 271	com/aps/j:a	(Landroid/content/Context;Landroid/net/NetworkInfo;)Lorg/apache/http/client/HttpClient;
    //   91: astore 37
    //   93: aload 37
    //   95: astore 24
    //   97: aload_3
    //   98: invokestatic 403	com/aps/j:a	(Lorg/json/JSONObject;)[Ljava/lang/String;
    //   101: astore 42
    //   103: aload 42
    //   105: iconst_0
    //   106: aaload
    //   107: ldc 238
    //   109: invokevirtual 125	java/lang/String:equals	(Ljava/lang/Object;)Z
    //   112: ifeq +488 -> 600
    //   115: iconst_1
    //   116: istore 43
    //   118: iload 43
    //   120: ifeq +486 -> 606
    //   123: new 273	org/apache/http/client/methods/HttpPost
    //   126: dup
    //   127: ldc_w 405
    //   130: invokespecial 276	org/apache/http/client/methods/HttpPost:<init>	(Ljava/lang/String;)V
    //   133: astore 25
    //   135: iload 43
    //   137: ifeq +493 -> 630
    //   140: ldc_w 357
    //   143: astore 44
    //   145: iload 43
    //   147: ifeq +33 -> 180
    //   150: iconst_2
    //   151: anewarray 4	java/lang/Object
    //   154: astore 49
    //   156: aload 49
    //   158: iconst_0
    //   159: aload 42
    //   161: iconst_1
    //   162: aaload
    //   163: aastore
    //   164: aload 49
    //   166: iconst_1
    //   167: aload 18
    //   169: aastore
    //   170: ldc_w 407
    //   173: aload 49
    //   175: invokestatic 411	java/lang/String:format	(Ljava/lang/String;[Ljava/lang/Object;)Ljava/lang/String;
    //   178: astore 18
    //   180: aload 18
    //   182: aload 44
    //   184: invokevirtual 415	java/lang/String:getBytes	(Ljava/lang/String;)[B
    //   187: invokestatic 418	com/aps/n:a	([B)[B
    //   190: astore 50
    //   192: new 278	org/apache/http/entity/ByteArrayEntity
    //   195: dup
    //   196: aload 50
    //   198: invokespecial 281	org/apache/http/entity/ByteArrayEntity:<init>	([B)V
    //   201: astore 51
    //   203: aload 51
    //   205: ldc_w 420
    //   208: invokevirtual 423	org/apache/http/entity/ByteArrayEntity:setContentType	(Ljava/lang/String;)V
    //   211: aload 25
    //   213: ldc_w 296
    //   216: ldc 214
    //   218: invokevirtual 289	org/apache/http/client/methods/HttpPost:addHeader	(Ljava/lang/String;Ljava/lang/String;)V
    //   221: aload 25
    //   223: ldc_w 425
    //   226: ldc_w 310
    //   229: invokevirtual 289	org/apache/http/client/methods/HttpPost:addHeader	(Ljava/lang/String;Ljava/lang/String;)V
    //   232: iload 43
    //   234: ifeq +53 -> 287
    //   237: aload 25
    //   239: ldc 232
    //   241: aload 42
    //   243: iconst_2
    //   244: aaload
    //   245: invokevirtual 289	org/apache/http/client/methods/HttpPost:addHeader	(Ljava/lang/String;Ljava/lang/String;)V
    //   248: aload 25
    //   250: ldc 234
    //   252: aload 42
    //   254: iconst_3
    //   255: aaload
    //   256: invokevirtual 289	org/apache/http/client/methods/HttpPost:addHeader	(Ljava/lang/String;Ljava/lang/String;)V
    //   259: aload 42
    //   261: iconst_4
    //   262: aaload
    //   263: ifnull +24 -> 287
    //   266: aload 42
    //   268: iconst_4
    //   269: aaload
    //   270: invokevirtual 133	java/lang/String:length	()I
    //   273: ifle +14 -> 287
    //   276: aload 25
    //   278: ldc 236
    //   280: aload 42
    //   282: iconst_4
    //   283: aaload
    //   284: invokevirtual 289	org/apache/http/client/methods/HttpPost:addHeader	(Ljava/lang/String;Ljava/lang/String;)V
    //   287: aload 11
    //   289: iconst_0
    //   290: aload 11
    //   292: invokevirtual 313	java/lang/StringBuffer:length	()I
    //   295: invokevirtual 317	java/lang/StringBuffer:delete	(II)Ljava/lang/StringBuffer;
    //   298: pop
    //   299: aload 25
    //   301: aload 51
    //   303: invokevirtual 321	org/apache/http/client/methods/HttpPost:setEntity	(Lorg/apache/http/HttpEntity;)V
    //   306: aload 24
    //   308: aload 25
    //   310: invokeinterface 327 2 0
    //   315: astore 53
    //   317: aload 53
    //   319: invokeinterface 331 1 0
    //   324: invokeinterface 336 1 0
    //   329: sipush 200
    //   332: if_icmpne +1267 -> 1599
    //   335: aload 53
    //   337: invokeinterface 340 1 0
    //   342: invokeinterface 346 1 0
    //   347: astore 58
    //   349: aload 53
    //   351: invokeinterface 340 1 0
    //   356: invokeinterface 350 1 0
    //   361: invokeinterface 212 1 0
    //   366: astore 63
    //   368: ldc_w 269
    //   371: astore 64
    //   373: aload 63
    //   375: ldc_w 352
    //   378: invokevirtual 195	java/lang/String:indexOf	(Ljava/lang/String;)I
    //   381: istore 65
    //   383: iload 65
    //   385: iconst_m1
    //   386: if_icmpeq +15 -> 401
    //   389: aload 63
    //   391: iload 65
    //   393: bipush 8
    //   395: iadd
    //   396: invokevirtual 355	java/lang/String:substring	(I)Ljava/lang/String;
    //   399: astore 64
    //   401: aload 64
    //   403: invokestatic 119	android/text/TextUtils:isEmpty	(Ljava/lang/CharSequence;)Z
    //   406: ifeq +1186 -> 1592
    //   409: aload 53
    //   411: invokestatic 359	com/aps/j:a	(Lorg/apache/http/HttpResponse;)Z
    //   414: ifeq +1171 -> 1585
    //   417: new 361	java/util/zip/GZIPInputStream
    //   420: dup
    //   421: aload 58
    //   423: invokespecial 364	java/util/zip/GZIPInputStream:<init>	(Ljava/io/InputStream;)V
    //   426: astore 55
    //   428: aload 55
    //   430: ifnull +208 -> 638
    //   433: new 366	java/io/InputStreamReader
    //   436: dup
    //   437: aload 55
    //   439: aload 44
    //   441: invokespecial 369	java/io/InputStreamReader:<init>	(Ljava/io/InputStream;Ljava/lang/String;)V
    //   444: astore 66
    //   446: new 371	java/io/BufferedReader
    //   449: dup
    //   450: aload 66
    //   452: sipush 2048
    //   455: invokespecial 374	java/io/BufferedReader:<init>	(Ljava/io/Reader;I)V
    //   458: astore 67
    //   460: aload 67
    //   462: invokevirtual 377	java/io/BufferedReader:readLine	()Ljava/lang/String;
    //   465: astore 72
    //   467: aload 72
    //   469: ifnull +206 -> 675
    //   472: aload 11
    //   474: aload 72
    //   476: invokevirtual 381	java/lang/StringBuffer:append	(Ljava/lang/String;)Ljava/lang/StringBuffer;
    //   479: pop
    //   480: goto -20 -> 460
    //   483: astore 71
    //   485: aload 67
    //   487: astore 12
    //   489: aload 66
    //   491: astore 13
    //   493: aload 55
    //   495: astore 14
    //   497: aload 58
    //   499: astore 15
    //   501: aload 25
    //   503: astore 16
    //   505: aload 24
    //   507: astore 17
    //   509: aload 16
    //   511: ifnull +11 -> 522
    //   514: aload 16
    //   516: invokevirtual 384	org/apache/http/client/methods/HttpPost:abort	()V
    //   519: aconst_null
    //   520: astore 16
    //   522: aload 17
    //   524: ifnull +18 -> 542
    //   527: aload 17
    //   529: invokeinterface 388 1 0
    //   534: invokeinterface 393 1 0
    //   539: aconst_null
    //   540: astore 17
    //   542: aload 14
    //   544: ifnull +11 -> 555
    //   547: aload 14
    //   549: invokevirtual 394	java/util/zip/GZIPInputStream:close	()V
    //   552: aconst_null
    //   553: astore 14
    //   555: aload 15
    //   557: ifnull +11 -> 568
    //   560: aload 15
    //   562: invokevirtual 397	java/io/InputStream:close	()V
    //   565: aconst_null
    //   566: astore 15
    //   568: aload 13
    //   570: ifnull +11 -> 581
    //   573: aload 13
    //   575: invokevirtual 398	java/io/InputStreamReader:close	()V
    //   578: aconst_null
    //   579: astore 13
    //   581: aload 12
    //   583: ifnull +11 -> 594
    //   586: aload 12
    //   588: invokevirtual 399	java/io/BufferedReader:close	()V
    //   591: aconst_null
    //   592: astore 12
    //   594: iinc 8 1
    //   597: goto -523 -> 74
    //   600: iconst_0
    //   601: istore 43
    //   603: goto -485 -> 118
    //   606: new 273	org/apache/http/client/methods/HttpPost
    //   609: dup
    //   610: ldc_w 427
    //   613: invokespecial 276	org/apache/http/client/methods/HttpPost:<init>	(Ljava/lang/String;)V
    //   616: astore 25
    //   618: goto -483 -> 135
    //   621: astore 41
    //   623: aload 24
    //   625: astore 17
    //   627: goto -118 -> 509
    //   630: ldc_w 429
    //   633: astore 44
    //   635: goto -490 -> 145
    //   638: new 366	java/io/InputStreamReader
    //   641: dup
    //   642: aload 58
    //   644: aload 44
    //   646: invokespecial 369	java/io/InputStreamReader:<init>	(Ljava/io/InputStream;Ljava/lang/String;)V
    //   649: astore 66
    //   651: goto -205 -> 446
    //   654: astore 82
    //   656: aload 55
    //   658: astore 14
    //   660: aload 58
    //   662: astore 15
    //   664: aload 25
    //   666: astore 16
    //   668: aload 24
    //   670: astore 17
    //   672: goto -163 -> 509
    //   675: aload 11
    //   677: invokevirtual 400	java/lang/StringBuffer:toString	()Ljava/lang/String;
    //   680: astore 10
    //   682: aload 11
    //   684: iconst_0
    //   685: aload 11
    //   687: invokevirtual 313	java/lang/StringBuffer:length	()I
    //   690: invokevirtual 317	java/lang/StringBuffer:delete	(II)Ljava/lang/StringBuffer;
    //   693: pop
    //   694: aconst_null
    //   695: astore 11
    //   697: iconst_1
    //   698: istore 9
    //   700: aload 67
    //   702: astore 12
    //   704: aload 58
    //   706: astore 54
    //   708: aload 66
    //   710: astore 13
    //   712: aload 25
    //   714: ifnull +822 -> 1536
    //   717: aload 25
    //   719: invokevirtual 384	org/apache/http/client/methods/HttpPost:abort	()V
    //   722: aconst_null
    //   723: astore 16
    //   725: aload 24
    //   727: ifnull +802 -> 1529
    //   730: aload 24
    //   732: invokeinterface 388 1 0
    //   737: invokeinterface 393 1 0
    //   742: aconst_null
    //   743: astore 17
    //   745: aload 55
    //   747: ifnull +775 -> 1522
    //   750: aload 55
    //   752: invokevirtual 394	java/util/zip/GZIPInputStream:close	()V
    //   755: aconst_null
    //   756: astore 14
    //   758: aload 54
    //   760: ifnull +755 -> 1515
    //   763: aload 54
    //   765: invokevirtual 397	java/io/InputStream:close	()V
    //   768: aconst_null
    //   769: astore 15
    //   771: aload 13
    //   773: ifnull +11 -> 784
    //   776: aload 13
    //   778: invokevirtual 398	java/io/InputStreamReader:close	()V
    //   781: aconst_null
    //   782: astore 13
    //   784: aload 12
    //   786: ifnull -192 -> 594
    //   789: aload 12
    //   791: invokevirtual 399	java/io/BufferedReader:close	()V
    //   794: goto -203 -> 591
    //   797: astore 4
    //   799: aload_0
    //   800: monitorexit
    //   801: aload 4
    //   803: athrow
    //   804: astore 34
    //   806: aload 67
    //   808: astore 12
    //   810: aload 66
    //   812: astore 13
    //   814: aload 55
    //   816: astore 14
    //   818: aload 58
    //   820: astore 15
    //   822: aload 25
    //   824: ifnull +8 -> 832
    //   827: aload 25
    //   829: invokevirtual 384	org/apache/http/client/methods/HttpPost:abort	()V
    //   832: aload 24
    //   834: ifnull +15 -> 849
    //   837: aload 24
    //   839: invokeinterface 388 1 0
    //   844: invokeinterface 393 1 0
    //   849: aload 14
    //   851: ifnull +8 -> 859
    //   854: aload 14
    //   856: invokevirtual 394	java/util/zip/GZIPInputStream:close	()V
    //   859: aload 15
    //   861: ifnull +8 -> 869
    //   864: aload 15
    //   866: invokevirtual 397	java/io/InputStream:close	()V
    //   869: aload 13
    //   871: ifnull +8 -> 879
    //   874: aload 13
    //   876: invokevirtual 398	java/io/InputStreamReader:close	()V
    //   879: aload 12
    //   881: ifnull +8 -> 889
    //   884: aload 12
    //   886: invokevirtual 399	java/io/BufferedReader:close	()V
    //   889: aload 34
    //   891: athrow
    //   892: aload 10
    //   894: invokestatic 119	android/text/TextUtils:isEmpty	(Ljava/lang/CharSequence;)Z
    //   897: ifeq +713 -> 1610
    //   900: aconst_null
    //   901: astore 19
    //   903: goto -879 -> 24
    //   906: aload 25
    //   908: ifnull +670 -> 1578
    //   911: aload 25
    //   913: invokevirtual 384	org/apache/http/client/methods/HttpPost:abort	()V
    //   916: aconst_null
    //   917: astore 16
    //   919: aload 24
    //   921: ifnull +650 -> 1571
    //   924: aload 24
    //   926: invokeinterface 388 1 0
    //   931: invokeinterface 393 1 0
    //   936: aconst_null
    //   937: astore 17
    //   939: aload 14
    //   941: ifnull +11 -> 952
    //   944: aload 14
    //   946: invokevirtual 394	java/util/zip/GZIPInputStream:close	()V
    //   949: aconst_null
    //   950: astore 14
    //   952: aload 15
    //   954: ifnull +11 -> 965
    //   957: aload 15
    //   959: invokevirtual 397	java/io/InputStream:close	()V
    //   962: aconst_null
    //   963: astore 15
    //   965: aload 13
    //   967: ifnull +11 -> 978
    //   970: aload 13
    //   972: invokevirtual 398	java/io/InputStreamReader:close	()V
    //   975: aconst_null
    //   976: astore 13
    //   978: aload 12
    //   980: ifnull -386 -> 594
    //   983: aload 12
    //   985: invokevirtual 399	java/io/BufferedReader:close	()V
    //   988: goto -397 -> 591
    //   991: aload 25
    //   993: ifnull +571 -> 1564
    //   996: aload 25
    //   998: invokevirtual 384	org/apache/http/client/methods/HttpPost:abort	()V
    //   1001: aconst_null
    //   1002: astore 16
    //   1004: aload 24
    //   1006: ifnull +551 -> 1557
    //   1009: aload 24
    //   1011: invokeinterface 388 1 0
    //   1016: invokeinterface 393 1 0
    //   1021: aconst_null
    //   1022: astore 17
    //   1024: aload 14
    //   1026: ifnull +11 -> 1037
    //   1029: aload 14
    //   1031: invokevirtual 394	java/util/zip/GZIPInputStream:close	()V
    //   1034: aconst_null
    //   1035: astore 14
    //   1037: aload 15
    //   1039: ifnull +11 -> 1050
    //   1042: aload 15
    //   1044: invokevirtual 397	java/io/InputStream:close	()V
    //   1047: aconst_null
    //   1048: astore 15
    //   1050: aload 13
    //   1052: ifnull +11 -> 1063
    //   1055: aload 13
    //   1057: invokevirtual 398	java/io/InputStreamReader:close	()V
    //   1060: aconst_null
    //   1061: astore 13
    //   1063: aload 12
    //   1065: ifnull -471 -> 594
    //   1068: aload 12
    //   1070: invokevirtual 399	java/io/BufferedReader:close	()V
    //   1073: goto -482 -> 591
    //   1076: aload 25
    //   1078: ifnull +472 -> 1550
    //   1081: aload 25
    //   1083: invokevirtual 384	org/apache/http/client/methods/HttpPost:abort	()V
    //   1086: aconst_null
    //   1087: astore 16
    //   1089: aload 24
    //   1091: ifnull +452 -> 1543
    //   1094: aload 24
    //   1096: invokeinterface 388 1 0
    //   1101: invokeinterface 393 1 0
    //   1106: aconst_null
    //   1107: astore 17
    //   1109: aload 14
    //   1111: ifnull +11 -> 1122
    //   1114: aload 14
    //   1116: invokevirtual 394	java/util/zip/GZIPInputStream:close	()V
    //   1119: aconst_null
    //   1120: astore 14
    //   1122: aload 15
    //   1124: ifnull +11 -> 1135
    //   1127: aload 15
    //   1129: invokevirtual 397	java/io/InputStream:close	()V
    //   1132: aconst_null
    //   1133: astore 15
    //   1135: aload 13
    //   1137: ifnull +11 -> 1148
    //   1140: aload 13
    //   1142: invokevirtual 398	java/io/InputStreamReader:close	()V
    //   1145: aconst_null
    //   1146: astore 13
    //   1148: aload 12
    //   1150: ifnull -556 -> 594
    //   1153: aload 12
    //   1155: invokevirtual 399	java/io/BufferedReader:close	()V
    //   1158: goto -567 -> 591
    //   1161: astore 33
    //   1163: goto -44 -> 1119
    //   1166: astore 32
    //   1168: goto -36 -> 1132
    //   1171: astore 36
    //   1173: goto -314 -> 859
    //   1176: astore 35
    //   1178: goto -309 -> 869
    //   1181: astore 57
    //   1183: goto -428 -> 755
    //   1186: astore 56
    //   1188: goto -420 -> 768
    //   1191: astore 34
    //   1193: aload 17
    //   1195: astore 24
    //   1197: aload 16
    //   1199: astore 25
    //   1201: goto -379 -> 822
    //   1204: astore 34
    //   1206: aload 16
    //   1208: astore 25
    //   1210: goto -388 -> 822
    //   1213: astore 34
    //   1215: goto -393 -> 822
    //   1218: astore 34
    //   1220: aload 58
    //   1222: astore 15
    //   1224: goto -402 -> 822
    //   1227: astore 34
    //   1229: aload 55
    //   1231: astore 14
    //   1233: aload 58
    //   1235: astore 15
    //   1237: goto -415 -> 822
    //   1240: astore 34
    //   1242: aload 66
    //   1244: astore 13
    //   1246: aload 55
    //   1248: astore 14
    //   1250: aload 58
    //   1252: astore 15
    //   1254: goto -432 -> 822
    //   1257: astore 31
    //   1259: aload 17
    //   1261: astore 24
    //   1263: aload 16
    //   1265: astore 25
    //   1267: goto -191 -> 1076
    //   1270: astore 40
    //   1272: aload 16
    //   1274: astore 25
    //   1276: goto -200 -> 1076
    //   1279: astore 48
    //   1281: goto -205 -> 1076
    //   1284: astore 62
    //   1286: aload 58
    //   1288: astore 15
    //   1290: goto -214 -> 1076
    //   1293: astore 81
    //   1295: aload 55
    //   1297: astore 14
    //   1299: aload 58
    //   1301: astore 15
    //   1303: goto -227 -> 1076
    //   1306: astore 78
    //   1308: aload 66
    //   1310: astore 13
    //   1312: aload 55
    //   1314: astore 14
    //   1316: aload 58
    //   1318: astore 15
    //   1320: goto -244 -> 1076
    //   1323: astore 28
    //   1325: aload 17
    //   1327: astore 24
    //   1329: aload 16
    //   1331: astore 25
    //   1333: goto -342 -> 991
    //   1336: astore 39
    //   1338: aload 16
    //   1340: astore 25
    //   1342: goto -351 -> 991
    //   1345: astore 47
    //   1347: goto -356 -> 991
    //   1350: astore 61
    //   1352: aload 58
    //   1354: astore 15
    //   1356: goto -365 -> 991
    //   1359: astore 80
    //   1361: aload 55
    //   1363: astore 14
    //   1365: aload 58
    //   1367: astore 15
    //   1369: goto -378 -> 991
    //   1372: astore 77
    //   1374: aload 66
    //   1376: astore 13
    //   1378: aload 55
    //   1380: astore 14
    //   1382: aload 58
    //   1384: astore 15
    //   1386: goto -395 -> 991
    //   1389: astore 23
    //   1391: aload 17
    //   1393: astore 24
    //   1395: aload 16
    //   1397: astore 25
    //   1399: goto -493 -> 906
    //   1402: astore 38
    //   1404: aload 16
    //   1406: astore 25
    //   1408: goto -502 -> 906
    //   1411: astore 46
    //   1413: goto -507 -> 906
    //   1416: astore 60
    //   1418: aload 58
    //   1420: astore 15
    //   1422: goto -516 -> 906
    //   1425: astore 79
    //   1427: aload 55
    //   1429: astore 14
    //   1431: aload 58
    //   1433: astore 15
    //   1435: goto -529 -> 906
    //   1438: astore 76
    //   1440: aload 66
    //   1442: astore 13
    //   1444: aload 55
    //   1446: astore 14
    //   1448: aload 58
    //   1450: astore 15
    //   1452: goto -546 -> 906
    //   1455: astore 20
    //   1457: goto -948 -> 509
    //   1460: astore 45
    //   1462: aload 25
    //   1464: astore 16
    //   1466: aload 24
    //   1468: astore 17
    //   1470: goto -961 -> 509
    //   1473: astore 59
    //   1475: aload 58
    //   1477: astore 15
    //   1479: aload 25
    //   1481: astore 16
    //   1483: aload 24
    //   1485: astore 17
    //   1487: goto -978 -> 509
    //   1490: astore 75
    //   1492: aload 66
    //   1494: astore 13
    //   1496: aload 55
    //   1498: astore 14
    //   1500: aload 58
    //   1502: astore 15
    //   1504: aload 25
    //   1506: astore 16
    //   1508: aload 24
    //   1510: astore 17
    //   1512: goto -1003 -> 509
    //   1515: aload 54
    //   1517: astore 15
    //   1519: goto -748 -> 771
    //   1522: aload 55
    //   1524: astore 14
    //   1526: goto -768 -> 758
    //   1529: aload 24
    //   1531: astore 17
    //   1533: goto -788 -> 745
    //   1536: aload 25
    //   1538: astore 16
    //   1540: goto -815 -> 725
    //   1543: aload 24
    //   1545: astore 17
    //   1547: goto -438 -> 1109
    //   1550: aload 25
    //   1552: astore 16
    //   1554: goto -465 -> 1089
    //   1557: aload 24
    //   1559: astore 17
    //   1561: goto -537 -> 1024
    //   1564: aload 25
    //   1566: astore 16
    //   1568: goto -564 -> 1004
    //   1571: aload 24
    //   1573: astore 17
    //   1575: goto -636 -> 939
    //   1578: aload 25
    //   1580: astore 16
    //   1582: goto -663 -> 919
    //   1585: aload 14
    //   1587: astore 55
    //   1589: goto -1161 -> 428
    //   1592: aload 64
    //   1594: astore 44
    //   1596: goto -1187 -> 409
    //   1599: aload 15
    //   1601: astore 54
    //   1603: aload 14
    //   1605: astore 55
    //   1607: goto -895 -> 712
    //   1610: aload 10
    //   1612: astore 19
    //   1614: goto -1590 -> 24
    //   1617: astore 22
    //   1619: goto -1067 -> 552
    //   1622: astore 21
    //   1624: goto -1059 -> 565
    //   1627: astore 70
    //   1629: aload 67
    //   1631: astore 12
    //   1633: aload 66
    //   1635: astore 13
    //   1637: aload 55
    //   1639: astore 14
    //   1641: aload 58
    //   1643: astore 15
    //   1645: goto -739 -> 906
    //   1648: astore 27
    //   1650: goto -701 -> 949
    //   1653: astore 26
    //   1655: goto -693 -> 962
    //   1658: astore 69
    //   1660: aload 67
    //   1662: astore 12
    //   1664: aload 66
    //   1666: astore 13
    //   1668: aload 55
    //   1670: astore 14
    //   1672: aload 58
    //   1674: astore 15
    //   1676: goto -685 -> 991
    //   1679: astore 30
    //   1681: goto -647 -> 1034
    //   1684: astore 29
    //   1686: goto -639 -> 1047
    //   1689: astore 68
    //   1691: aload 67
    //   1693: astore 12
    //   1695: aload 66
    //   1697: astore 13
    //   1699: aload 55
    //   1701: astore 14
    //   1703: aload 58
    //   1705: astore 15
    //   1707: goto -631 -> 1076
    //
    // Exception table:
    //   from	to	target	type
    //   460	467	483	java/net/UnknownHostException
    //   472	480	483	java/net/UnknownHostException
    //   675	694	483	java/net/UnknownHostException
    //   97	115	621	java/net/UnknownHostException
    //   123	135	621	java/net/UnknownHostException
    //   606	618	621	java/net/UnknownHostException
    //   433	446	654	java/net/UnknownHostException
    //   638	651	654	java/net/UnknownHostException
    //   2	15	797	finally
    //   29	38	797	finally
    //   514	519	797	finally
    //   527	539	797	finally
    //   547	552	797	finally
    //   560	565	797	finally
    //   573	578	797	finally
    //   586	591	797	finally
    //   717	722	797	finally
    //   730	742	797	finally
    //   750	755	797	finally
    //   763	768	797	finally
    //   776	781	797	finally
    //   789	794	797	finally
    //   827	832	797	finally
    //   837	849	797	finally
    //   854	859	797	finally
    //   864	869	797	finally
    //   874	879	797	finally
    //   884	889	797	finally
    //   889	892	797	finally
    //   892	900	797	finally
    //   911	916	797	finally
    //   924	936	797	finally
    //   944	949	797	finally
    //   957	962	797	finally
    //   970	975	797	finally
    //   983	988	797	finally
    //   996	1001	797	finally
    //   1009	1021	797	finally
    //   1029	1034	797	finally
    //   1042	1047	797	finally
    //   1055	1060	797	finally
    //   1068	1073	797	finally
    //   1081	1086	797	finally
    //   1094	1106	797	finally
    //   1114	1119	797	finally
    //   1127	1132	797	finally
    //   1140	1145	797	finally
    //   1153	1158	797	finally
    //   460	467	804	finally
    //   472	480	804	finally
    //   675	694	804	finally
    //   1114	1119	1161	java/lang/Exception
    //   1127	1132	1166	java/lang/Exception
    //   854	859	1171	java/lang/Exception
    //   864	869	1176	java/lang/Exception
    //   750	755	1181	java/lang/Exception
    //   763	768	1186	java/lang/Exception
    //   85	93	1191	finally
    //   97	115	1204	finally
    //   123	135	1204	finally
    //   606	618	1204	finally
    //   150	180	1213	finally
    //   180	232	1213	finally
    //   237	287	1213	finally
    //   287	349	1213	finally
    //   349	368	1218	finally
    //   373	383	1218	finally
    //   389	401	1218	finally
    //   401	409	1218	finally
    //   409	428	1218	finally
    //   433	446	1227	finally
    //   638	651	1227	finally
    //   446	460	1240	finally
    //   85	93	1257	org/apache/http/conn/ConnectTimeoutException
    //   97	115	1270	org/apache/http/conn/ConnectTimeoutException
    //   123	135	1270	org/apache/http/conn/ConnectTimeoutException
    //   606	618	1270	org/apache/http/conn/ConnectTimeoutException
    //   150	180	1279	org/apache/http/conn/ConnectTimeoutException
    //   180	232	1279	org/apache/http/conn/ConnectTimeoutException
    //   237	287	1279	org/apache/http/conn/ConnectTimeoutException
    //   287	349	1279	org/apache/http/conn/ConnectTimeoutException
    //   349	368	1284	org/apache/http/conn/ConnectTimeoutException
    //   373	383	1284	org/apache/http/conn/ConnectTimeoutException
    //   389	401	1284	org/apache/http/conn/ConnectTimeoutException
    //   401	409	1284	org/apache/http/conn/ConnectTimeoutException
    //   409	428	1284	org/apache/http/conn/ConnectTimeoutException
    //   433	446	1293	org/apache/http/conn/ConnectTimeoutException
    //   638	651	1293	org/apache/http/conn/ConnectTimeoutException
    //   446	460	1306	org/apache/http/conn/ConnectTimeoutException
    //   85	93	1323	java/net/SocketTimeoutException
    //   97	115	1336	java/net/SocketTimeoutException
    //   123	135	1336	java/net/SocketTimeoutException
    //   606	618	1336	java/net/SocketTimeoutException
    //   150	180	1345	java/net/SocketTimeoutException
    //   180	232	1345	java/net/SocketTimeoutException
    //   237	287	1345	java/net/SocketTimeoutException
    //   287	349	1345	java/net/SocketTimeoutException
    //   349	368	1350	java/net/SocketTimeoutException
    //   373	383	1350	java/net/SocketTimeoutException
    //   389	401	1350	java/net/SocketTimeoutException
    //   401	409	1350	java/net/SocketTimeoutException
    //   409	428	1350	java/net/SocketTimeoutException
    //   433	446	1359	java/net/SocketTimeoutException
    //   638	651	1359	java/net/SocketTimeoutException
    //   446	460	1372	java/net/SocketTimeoutException
    //   85	93	1389	java/net/SocketException
    //   97	115	1402	java/net/SocketException
    //   123	135	1402	java/net/SocketException
    //   606	618	1402	java/net/SocketException
    //   150	180	1411	java/net/SocketException
    //   180	232	1411	java/net/SocketException
    //   237	287	1411	java/net/SocketException
    //   287	349	1411	java/net/SocketException
    //   349	368	1416	java/net/SocketException
    //   373	383	1416	java/net/SocketException
    //   389	401	1416	java/net/SocketException
    //   401	409	1416	java/net/SocketException
    //   409	428	1416	java/net/SocketException
    //   433	446	1425	java/net/SocketException
    //   638	651	1425	java/net/SocketException
    //   446	460	1438	java/net/SocketException
    //   85	93	1455	java/net/UnknownHostException
    //   150	180	1460	java/net/UnknownHostException
    //   180	232	1460	java/net/UnknownHostException
    //   237	287	1460	java/net/UnknownHostException
    //   287	349	1460	java/net/UnknownHostException
    //   349	368	1473	java/net/UnknownHostException
    //   373	383	1473	java/net/UnknownHostException
    //   389	401	1473	java/net/UnknownHostException
    //   401	409	1473	java/net/UnknownHostException
    //   409	428	1473	java/net/UnknownHostException
    //   446	460	1490	java/net/UnknownHostException
    //   547	552	1617	java/lang/Exception
    //   560	565	1622	java/lang/Exception
    //   460	467	1627	java/net/SocketException
    //   472	480	1627	java/net/SocketException
    //   675	694	1627	java/net/SocketException
    //   944	949	1648	java/lang/Exception
    //   957	962	1653	java/lang/Exception
    //   460	467	1658	java/net/SocketTimeoutException
    //   472	480	1658	java/net/SocketTimeoutException
    //   675	694	1658	java/net/SocketTimeoutException
    //   1029	1034	1679	java/lang/Exception
    //   1042	1047	1684	java/lang/Exception
    //   460	467	1689	org/apache/http/conn/ConnectTimeoutException
    //   472	480	1689	org/apache/http/conn/ConnectTimeoutException
    //   675	694	1689	org/apache/http/conn/ConnectTimeoutException
  }
}

/* Location:           /Users/don/DeSources/alipay/backup/zhifubaoqianbao_52/classes-dex2jar.jar
 * Qualified Name:     com.aps.j
 * JD-Core Version:    0.6.2
 */