package com.alipay.android.app.data;

final class i
  implements Runnable
{
  i(h paramh, String paramString1, int paramInt1, String[] paramArrayOfString, String paramString2, int paramInt2, String paramString3)
  {
  }

  // ERROR //
  public final void run()
  {
    // Byte code:
    //   0: invokestatic 44	com/alipay/android/app/sys/GlobalContext:a	()Lcom/alipay/android/app/sys/GlobalContext;
    //   3: invokevirtual 47	com/alipay/android/app/sys/GlobalContext:b	()Landroid/content/Context;
    //   6: astore_1
    //   7: invokestatic 53	java/lang/System:currentTimeMillis	()J
    //   10: pop2
    //   11: aload_0
    //   12: getfield 23	com/alipay/android/app/data/i:a	Ljava/lang/String;
    //   15: invokestatic 59	java/lang/Long:parseLong	(Ljava/lang/String;)J
    //   18: pop2
    //   19: invokestatic 53	java/lang/System:currentTimeMillis	()J
    //   22: lstore 9
    //   24: sipush 1000
    //   27: aload_0
    //   28: getfield 25	com/alipay/android/app/data/i:b	I
    //   31: imul
    //   32: i2l
    //   33: lstore 11
    //   35: aload_0
    //   36: getfield 21	com/alipay/android/app/data/i:g	Lcom/alipay/android/app/data/h;
    //   39: aload_0
    //   40: getfield 27	com/alipay/android/app/data/i:c	[Ljava/lang/String;
    //   43: aload_0
    //   44: getfield 29	com/alipay/android/app/data/i:d	Ljava/lang/String;
    //   47: aload_0
    //   48: getfield 31	com/alipay/android/app/data/i:e	I
    //   51: aload_0
    //   52: getfield 33	com/alipay/android/app/data/i:f	Ljava/lang/String;
    //   55: aload_1
    //   56: lload 9
    //   58: lload 11
    //   60: invokestatic 64	com/alipay/android/app/data/h:a	(Lcom/alipay/android/app/data/h;[Ljava/lang/String;Ljava/lang/String;ILjava/lang/String;Landroid/content/Context;JJ)V
    //   63: aload_0
    //   64: getfield 21	com/alipay/android/app/data/i:g	Lcom/alipay/android/app/data/h;
    //   67: invokestatic 67	com/alipay/android/app/data/h:a	(Lcom/alipay/android/app/data/h;)Z
    //   70: pop
    //   71: return
    //   72: astore 4
    //   74: aload_0
    //   75: getfield 21	com/alipay/android/app/data/i:g	Lcom/alipay/android/app/data/h;
    //   78: invokestatic 67	com/alipay/android/app/data/h:a	(Lcom/alipay/android/app/data/h;)Z
    //   81: pop
    //   82: return
    //   83: astore_2
    //   84: aload_0
    //   85: getfield 21	com/alipay/android/app/data/i:g	Lcom/alipay/android/app/data/h;
    //   88: invokestatic 67	com/alipay/android/app/data/h:a	(Lcom/alipay/android/app/data/h;)Z
    //   91: pop
    //   92: aload_2
    //   93: athrow
    //   94: astore 8
    //   96: goto -77 -> 19
    //
    // Exception table:
    //   from	to	target	type
    //   7	11	72	java/lang/Exception
    //   19	63	72	java/lang/Exception
    //   7	11	83	finally
    //   11	19	83	finally
    //   19	63	83	finally
    //   11	19	94	java/lang/Exception
  }
}

/* Location:           /Users/don/DeSources/alipay/backup/zhifubaoqianbao_52/classes-dex2jar.jar
 * Qualified Name:     com.alipay.android.app.data.i
 * JD-Core Version:    0.6.2
 */