package com.alipay.android.mini.util;

final class e
  implements Runnable
{
  e(MiniSmsReader paramMiniSmsReader, int paramInt1, String[] paramArrayOfString, String paramString, int paramInt2)
  {
  }

  // ERROR //
  public final void run()
  {
    // Byte code:
    //   0: invokestatic 38	com/alipay/android/app/sys/GlobalContext:a	()Lcom/alipay/android/app/sys/GlobalContext;
    //   3: invokevirtual 41	com/alipay/android/app/sys/GlobalContext:b	()Landroid/content/Context;
    //   6: astore_1
    //   7: invokestatic 47	java/lang/System:currentTimeMillis	()J
    //   10: lstore 6
    //   12: sipush 1000
    //   15: aload_0
    //   16: getfield 21	com/alipay/android/mini/util/e:a	I
    //   19: imul
    //   20: i2l
    //   21: lstore 8
    //   23: new 49	java/lang/StringBuilder
    //   26: dup
    //   27: ldc 51
    //   29: invokespecial 54	java/lang/StringBuilder:<init>	(Ljava/lang/String;)V
    //   32: lload 8
    //   34: invokevirtual 58	java/lang/StringBuilder:append	(J)Ljava/lang/StringBuilder;
    //   37: ldc 60
    //   39: invokevirtual 63	java/lang/StringBuilder:append	(Ljava/lang/String;)Ljava/lang/StringBuilder;
    //   42: lload 6
    //   44: invokevirtual 58	java/lang/StringBuilder:append	(J)Ljava/lang/StringBuilder;
    //   47: invokevirtual 67	java/lang/StringBuilder:toString	()Ljava/lang/String;
    //   50: pop
    //   51: invokestatic 71	com/alipay/android/app/util/LogUtils:b	()V
    //   54: aload_0
    //   55: getfield 19	com/alipay/android/mini/util/e:e	Lcom/alipay/android/mini/util/MiniSmsReader;
    //   58: invokestatic 77	com/alipay/android/mini/util/MiniSmsReader:g	(Lcom/alipay/android/mini/util/MiniSmsReader;)Lcom/alipay/android/mini/event/MiniReadSmsArgs;
    //   61: aload_0
    //   62: getfield 19	com/alipay/android/mini/util/e:e	Lcom/alipay/android/mini/util/MiniSmsReader;
    //   65: invokestatic 81	com/alipay/android/mini/util/MiniSmsReader:h	(Lcom/alipay/android/mini/util/MiniSmsReader;)Lcom/alipay/android/lib/phone/SmsReader;
    //   68: aload_0
    //   69: getfield 23	com/alipay/android/mini/util/e:b	[Ljava/lang/String;
    //   72: aload_0
    //   73: getfield 25	com/alipay/android/mini/util/e:c	Ljava/lang/String;
    //   76: aload_0
    //   77: getfield 27	com/alipay/android/mini/util/e:d	I
    //   80: aload_1
    //   81: lload 6
    //   83: lload 8
    //   85: aload_0
    //   86: getfield 19	com/alipay/android/mini/util/e:e	Lcom/alipay/android/mini/util/MiniSmsReader;
    //   89: invokestatic 85	com/alipay/android/mini/util/MiniSmsReader:i	(Lcom/alipay/android/mini/util/MiniSmsReader;)Lcom/alipay/android/app/data/ValidatedFrameData;
    //   92: invokestatic 88	com/alipay/android/mini/util/MiniSmsReader:a	(Lcom/alipay/android/mini/event/MiniReadSmsArgs;Lcom/alipay/android/lib/phone/SmsReader;[Ljava/lang/String;Ljava/lang/String;ILandroid/content/Context;JJLcom/alipay/android/app/data/ValidatedFrameData;)V
    //   95: aload_0
    //   96: getfield 19	com/alipay/android/mini/util/e:e	Lcom/alipay/android/mini/util/MiniSmsReader;
    //   99: invokestatic 92	com/alipay/android/mini/util/MiniSmsReader:j	(Lcom/alipay/android/mini/util/MiniSmsReader;)Z
    //   102: pop
    //   103: return
    //   104: astore 4
    //   106: aload_0
    //   107: getfield 19	com/alipay/android/mini/util/e:e	Lcom/alipay/android/mini/util/MiniSmsReader;
    //   110: invokestatic 92	com/alipay/android/mini/util/MiniSmsReader:j	(Lcom/alipay/android/mini/util/MiniSmsReader;)Z
    //   113: pop
    //   114: return
    //   115: astore_2
    //   116: aload_0
    //   117: getfield 19	com/alipay/android/mini/util/e:e	Lcom/alipay/android/mini/util/MiniSmsReader;
    //   120: invokestatic 92	com/alipay/android/mini/util/MiniSmsReader:j	(Lcom/alipay/android/mini/util/MiniSmsReader;)Z
    //   123: pop
    //   124: aload_2
    //   125: athrow
    //
    // Exception table:
    //   from	to	target	type
    //   7	95	104	java/lang/Exception
    //   7	95	115	finally
  }
}

/* Location:           /Users/don/DeSources/alipay/backup/zhifubaoqianbao_52/classes-dex2jar.jar
 * Qualified Name:     com.alipay.android.mini.util.e
 * JD-Core Version:    0.6.2
 */