package com.alipay.android.app.pay;

final class l
  implements Runnable
{
  l(PageForBrowser paramPageForBrowser, String paramString)
  {
  }

  // ERROR //
  public final void run()
  {
    // Byte code:
    //   0: aload_0
    //   1: getfield 14	com/alipay/android/app/pay/l:b	Lcom/alipay/android/app/pay/PageForBrowser;
    //   4: invokestatic 31	com/alipay/android/app/pay/PageForBrowser:b	(Lcom/alipay/android/app/pay/PageForBrowser;)Lcom/alipay/android/app/IAlixPay;
    //   7: ifnonnull +115 -> 122
    //   10: aload_0
    //   11: getfield 14	com/alipay/android/app/pay/l:b	Lcom/alipay/android/app/pay/PageForBrowser;
    //   14: invokestatic 35	com/alipay/android/app/pay/PageForBrowser:c	(Lcom/alipay/android/app/pay/PageForBrowser;)Ljava/lang/Integer;
    //   17: astore 4
    //   19: aload 4
    //   21: monitorenter
    //   22: aload_0
    //   23: getfield 14	com/alipay/android/app/pay/l:b	Lcom/alipay/android/app/pay/PageForBrowser;
    //   26: invokestatic 35	com/alipay/android/app/pay/PageForBrowser:c	(Lcom/alipay/android/app/pay/PageForBrowser;)Ljava/lang/Integer;
    //   29: invokevirtual 38	java/lang/Object:wait	()V
    //   32: aload 4
    //   34: monitorexit
    //   35: invokestatic 43	com/alipay/android/app/util/LogUtils:g	()V
    //   38: aload_0
    //   39: getfield 14	com/alipay/android/app/pay/l:b	Lcom/alipay/android/app/pay/PageForBrowser;
    //   42: invokestatic 31	com/alipay/android/app/pay/PageForBrowser:b	(Lcom/alipay/android/app/pay/PageForBrowser;)Lcom/alipay/android/app/IAlixPay;
    //   45: aload_0
    //   46: getfield 16	com/alipay/android/app/pay/l:a	Ljava/lang/String;
    //   49: invokeinterface 49 2 0
    //   54: astore 6
    //   56: new 51	java/lang/StringBuilder
    //   59: dup
    //   60: ldc 53
    //   62: invokespecial 56	java/lang/StringBuilder:<init>	(Ljava/lang/String;)V
    //   65: aload 6
    //   67: invokevirtual 60	java/lang/StringBuilder:append	(Ljava/lang/String;)Ljava/lang/StringBuilder;
    //   70: invokevirtual 64	java/lang/StringBuilder:toString	()Ljava/lang/String;
    //   73: pop
    //   74: invokestatic 43	com/alipay/android/app/util/LogUtils:g	()V
    //   77: invokestatic 43	com/alipay/android/app/util/LogUtils:g	()V
    //   80: aload_0
    //   81: getfield 14	com/alipay/android/app/pay/l:b	Lcom/alipay/android/app/pay/PageForBrowser;
    //   84: pop
    //   85: aload 6
    //   87: invokestatic 66	com/alipay/android/app/pay/PageForBrowser:a	(Ljava/lang/String;)Ljava/lang/String;
    //   90: astore 9
    //   92: aload 9
    //   94: ifnull +28 -> 122
    //   97: new 68	android/content/Intent
    //   100: dup
    //   101: ldc 70
    //   103: aload 9
    //   105: invokestatic 76	android/net/Uri:parse	(Ljava/lang/String;)Landroid/net/Uri;
    //   108: invokespecial 79	android/content/Intent:<init>	(Ljava/lang/String;Landroid/net/Uri;)V
    //   111: astore 10
    //   113: aload_0
    //   114: getfield 14	com/alipay/android/app/pay/l:b	Lcom/alipay/android/app/pay/PageForBrowser;
    //   117: aload 10
    //   119: invokevirtual 83	com/alipay/android/app/pay/PageForBrowser:startActivity	(Landroid/content/Intent;)V
    //   122: aload_0
    //   123: getfield 14	com/alipay/android/app/pay/l:b	Lcom/alipay/android/app/pay/PageForBrowser;
    //   126: invokestatic 87	com/alipay/android/app/pay/PageForBrowser:d	(Lcom/alipay/android/app/pay/PageForBrowser;)Z
    //   129: pop
    //   130: return
    //   131: astore 5
    //   133: aload 4
    //   135: monitorexit
    //   136: aload 5
    //   138: athrow
    //   139: astore_2
    //   140: aload_2
    //   141: invokevirtual 90	java/lang/InterruptedException:printStackTrace	()V
    //   144: return
    //   145: astore 11
    //   147: aload 11
    //   149: invokevirtual 91	java/lang/Exception:printStackTrace	()V
    //   152: goto -30 -> 122
    //   155: astore_1
    //   156: aload_1
    //   157: invokevirtual 92	android/os/RemoteException:printStackTrace	()V
    //   160: return
    //
    // Exception table:
    //   from	to	target	type
    //   22	35	131	finally
    //   0	22	139	java/lang/InterruptedException
    //   35	92	139	java/lang/InterruptedException
    //   97	122	139	java/lang/InterruptedException
    //   122	130	139	java/lang/InterruptedException
    //   133	139	139	java/lang/InterruptedException
    //   147	152	139	java/lang/InterruptedException
    //   97	122	145	java/lang/Exception
    //   0	22	155	android/os/RemoteException
    //   35	92	155	android/os/RemoteException
    //   97	122	155	android/os/RemoteException
    //   122	130	155	android/os/RemoteException
    //   133	139	155	android/os/RemoteException
    //   147	152	155	android/os/RemoteException
  }
}

/* Location:           /Users/don/DeSources/alipay/backup/zhifubaoqianbao_52/classes-dex2jar.jar
 * Qualified Name:     com.alipay.android.app.pay.l
 * JD-Core Version:    0.6.2
 */