package com.alipay.pushsdk.push;

final class n
  implements Runnable
{
  final j a;

  private n(j paramj)
  {
    this.a = paramj;
  }

  // ERROR //
  public final void run()
  {
    // Byte code:
    //   0: iconst_3
    //   1: invokestatic 32	com/alipay/pushsdk/push/j:z	()Ljava/lang/String;
    //   4: ldc 34
    //   6: invokestatic 39	com/alipay/pushsdk/c/a/c:a	(ILjava/lang/String;Ljava/lang/String;)V
    //   9: aload_0
    //   10: getfield 18	com/alipay/pushsdk/push/n:a	Lcom/alipay/pushsdk/push/j;
    //   13: invokevirtual 43	com/alipay/pushsdk/push/j:s	()Z
    //   16: ifne +445 -> 461
    //   19: aload_0
    //   20: getfield 13	com/alipay/pushsdk/push/n:b	Lcom/alipay/pushsdk/push/j;
    //   23: invokestatic 47	com/alipay/pushsdk/push/j:j	(Lcom/alipay/pushsdk/push/j;)I
    //   26: invokestatic 52	com/alipay/pushsdk/push/c/c:a	(I)Lcom/alipay/pushsdk/push/c/a;
    //   29: astore_2
    //   30: aload_2
    //   31: iconst_0
    //   32: invokevirtual 57	com/alipay/pushsdk/push/c/a:a	(I)V
    //   35: aload_2
    //   36: iconst_0
    //   37: invokevirtual 59	com/alipay/pushsdk/push/c/a:b	(I)V
    //   40: new 61	com/alipay/pushsdk/c/b
    //   43: dup
    //   44: aload_0
    //   45: getfield 13	com/alipay/pushsdk/push/n:b	Lcom/alipay/pushsdk/push/j;
    //   48: invokestatic 65	com/alipay/pushsdk/push/j:k	(Lcom/alipay/pushsdk/push/j;)Landroid/content/Context;
    //   51: invokespecial 68	com/alipay/pushsdk/c/b:<init>	(Landroid/content/Context;)V
    //   54: invokevirtual 71	com/alipay/pushsdk/c/b:b	()Lorg/json/JSONObject;
    //   57: astore_3
    //   58: aload_3
    //   59: ifnull +392 -> 451
    //   62: aload_0
    //   63: getfield 18	com/alipay/pushsdk/push/n:a	Lcom/alipay/pushsdk/push/j;
    //   66: invokevirtual 74	com/alipay/pushsdk/push/j:e	()Ljava/lang/String;
    //   69: invokevirtual 80	java/lang/String:length	()I
    //   72: ifle +335 -> 407
    //   75: aload_3
    //   76: ldc 82
    //   78: aload_0
    //   79: getfield 18	com/alipay/pushsdk/push/n:a	Lcom/alipay/pushsdk/push/j;
    //   82: invokevirtual 74	com/alipay/pushsdk/push/j:e	()Ljava/lang/String;
    //   85: invokevirtual 88	org/json/JSONObject:put	(Ljava/lang/String;Ljava/lang/Object;)Lorg/json/JSONObject;
    //   88: pop
    //   89: ldc 90
    //   91: astore 6
    //   93: aload_0
    //   94: getfield 18	com/alipay/pushsdk/push/n:a	Lcom/alipay/pushsdk/push/j;
    //   97: invokevirtual 93	com/alipay/pushsdk/push/j:a	()Landroid/content/Context;
    //   100: invokevirtual 98	android/content/Context:getPackageName	()Ljava/lang/String;
    //   103: astore 7
    //   105: aload 7
    //   107: ifnull +322 -> 429
    //   110: aload 7
    //   112: ldc 100
    //   114: invokevirtual 104	java/lang/String:equals	(Ljava/lang/Object;)Z
    //   117: ifeq +312 -> 429
    //   120: ldc 106
    //   122: astore 6
    //   124: aload_3
    //   125: ldc 108
    //   127: aload 6
    //   129: invokevirtual 88	org/json/JSONObject:put	(Ljava/lang/String;Ljava/lang/Object;)Lorg/json/JSONObject;
    //   132: pop
    //   133: aload_3
    //   134: ldc 110
    //   136: aload_0
    //   137: getfield 18	com/alipay/pushsdk/push/n:a	Lcom/alipay/pushsdk/push/j;
    //   140: invokevirtual 113	com/alipay/pushsdk/push/j:i	()Ljava/lang/String;
    //   143: invokevirtual 88	org/json/JSONObject:put	(Ljava/lang/String;Ljava/lang/Object;)Lorg/json/JSONObject;
    //   146: pop
    //   147: aload_0
    //   148: getfield 18	com/alipay/pushsdk/push/n:a	Lcom/alipay/pushsdk/push/j;
    //   151: invokevirtual 117	com/alipay/pushsdk/push/j:g	()J
    //   154: lstore 10
    //   156: aload_0
    //   157: getfield 18	com/alipay/pushsdk/push/n:a	Lcom/alipay/pushsdk/push/j;
    //   160: invokevirtual 120	com/alipay/pushsdk/push/j:f	()J
    //   163: lstore 12
    //   165: lload 12
    //   167: lload 10
    //   169: lsub
    //   170: ldc2_w 121
    //   173: ldiv
    //   174: lstore 14
    //   176: aload_3
    //   177: ldc 124
    //   179: lload 12
    //   181: invokevirtual 127	org/json/JSONObject:put	(Ljava/lang/String;J)Lorg/json/JSONObject;
    //   184: pop
    //   185: aload_3
    //   186: ldc 129
    //   188: lload 10
    //   190: invokevirtual 127	org/json/JSONObject:put	(Ljava/lang/String;J)Lorg/json/JSONObject;
    //   193: pop
    //   194: iconst_3
    //   195: invokestatic 32	com/alipay/pushsdk/push/j:z	()Ljava/lang/String;
    //   198: new 131	java/lang/StringBuilder
    //   201: dup
    //   202: ldc 133
    //   204: invokespecial 136	java/lang/StringBuilder:<init>	(Ljava/lang/String;)V
    //   207: aload_3
    //   208: ldc 82
    //   210: invokevirtual 140	org/json/JSONObject:getString	(Ljava/lang/String;)Ljava/lang/String;
    //   213: invokevirtual 144	java/lang/StringBuilder:append	(Ljava/lang/String;)Ljava/lang/StringBuilder;
    //   216: ldc 146
    //   218: invokevirtual 144	java/lang/StringBuilder:append	(Ljava/lang/String;)Ljava/lang/StringBuilder;
    //   221: lload 14
    //   223: invokevirtual 149	java/lang/StringBuilder:append	(J)Ljava/lang/StringBuilder;
    //   226: invokevirtual 152	java/lang/StringBuilder:toString	()Ljava/lang/String;
    //   229: invokestatic 39	com/alipay/pushsdk/c/a/c:a	(ILjava/lang/String;Ljava/lang/String;)V
    //   232: aload_2
    //   233: aload_3
    //   234: invokevirtual 153	org/json/JSONObject:toString	()Ljava/lang/String;
    //   237: invokevirtual 155	com/alipay/pushsdk/push/c/a:a	(Ljava/lang/String;)V
    //   240: iconst_4
    //   241: invokestatic 32	com/alipay/pushsdk/push/j:z	()Ljava/lang/String;
    //   244: new 131	java/lang/StringBuilder
    //   247: dup
    //   248: ldc 157
    //   250: invokespecial 136	java/lang/StringBuilder:<init>	(Ljava/lang/String;)V
    //   253: aload_2
    //   254: invokevirtual 160	com/alipay/pushsdk/push/c/a:h	()Ljava/lang/String;
    //   257: invokevirtual 144	java/lang/StringBuilder:append	(Ljava/lang/String;)Ljava/lang/StringBuilder;
    //   260: invokevirtual 152	java/lang/StringBuilder:toString	()Ljava/lang/String;
    //   263: invokestatic 39	com/alipay/pushsdk/c/a/c:a	(ILjava/lang/String;Ljava/lang/String;)V
    //   266: aload_0
    //   267: getfield 13	com/alipay/pushsdk/push/n:b	Lcom/alipay/pushsdk/push/j;
    //   270: invokestatic 163	com/alipay/pushsdk/push/j:a	(Lcom/alipay/pushsdk/push/j;)Lcom/alipay/pushsdk/push/a/m;
    //   273: aload_0
    //   274: getfield 18	com/alipay/pushsdk/push/n:a	Lcom/alipay/pushsdk/push/j;
    //   277: invokevirtual 167	com/alipay/pushsdk/push/j:l	()Lcom/alipay/pushsdk/push/d/c;
    //   280: invokevirtual 172	com/alipay/pushsdk/push/a/m:a	(Lcom/alipay/pushsdk/push/d/c;)V
    //   283: aload_0
    //   284: getfield 13	com/alipay/pushsdk/push/n:b	Lcom/alipay/pushsdk/push/j;
    //   287: invokestatic 163	com/alipay/pushsdk/push/j:a	(Lcom/alipay/pushsdk/push/j;)Lcom/alipay/pushsdk/push/a/m;
    //   290: aload_0
    //   291: getfield 18	com/alipay/pushsdk/push/n:a	Lcom/alipay/pushsdk/push/j;
    //   294: invokevirtual 175	com/alipay/pushsdk/push/j:m	()Lcom/alipay/pushsdk/push/d/c;
    //   297: invokevirtual 172	com/alipay/pushsdk/push/a/m:a	(Lcom/alipay/pushsdk/push/d/c;)V
    //   300: aload_0
    //   301: getfield 13	com/alipay/pushsdk/push/n:b	Lcom/alipay/pushsdk/push/j;
    //   304: invokestatic 163	com/alipay/pushsdk/push/j:a	(Lcom/alipay/pushsdk/push/j;)Lcom/alipay/pushsdk/push/a/m;
    //   307: aload_0
    //   308: getfield 18	com/alipay/pushsdk/push/n:a	Lcom/alipay/pushsdk/push/j;
    //   311: invokevirtual 178	com/alipay/pushsdk/push/j:n	()Lcom/alipay/pushsdk/push/d/c;
    //   314: invokevirtual 172	com/alipay/pushsdk/push/a/m:a	(Lcom/alipay/pushsdk/push/d/c;)V
    //   317: aload_0
    //   318: getfield 13	com/alipay/pushsdk/push/n:b	Lcom/alipay/pushsdk/push/j;
    //   321: invokestatic 163	com/alipay/pushsdk/push/j:a	(Lcom/alipay/pushsdk/push/j;)Lcom/alipay/pushsdk/push/a/m;
    //   324: aload_0
    //   325: getfield 18	com/alipay/pushsdk/push/n:a	Lcom/alipay/pushsdk/push/j;
    //   328: invokevirtual 181	com/alipay/pushsdk/push/j:o	()Lcom/alipay/pushsdk/push/d/c;
    //   331: invokevirtual 172	com/alipay/pushsdk/push/a/m:a	(Lcom/alipay/pushsdk/push/d/c;)V
    //   334: iconst_4
    //   335: invokestatic 32	com/alipay/pushsdk/push/j:z	()Ljava/lang/String;
    //   338: new 131	java/lang/StringBuilder
    //   341: dup
    //   342: ldc 183
    //   344: invokespecial 136	java/lang/StringBuilder:<init>	(Ljava/lang/String;)V
    //   347: aload_2
    //   348: invokevirtual 185	com/alipay/pushsdk/push/c/a:g	()I
    //   351: invokevirtual 188	java/lang/StringBuilder:append	(I)Ljava/lang/StringBuilder;
    //   354: invokevirtual 152	java/lang/StringBuilder:toString	()Ljava/lang/String;
    //   357: invokestatic 39	com/alipay/pushsdk/c/a/c:a	(ILjava/lang/String;Ljava/lang/String;)V
    //   360: iconst_5
    //   361: invokestatic 32	com/alipay/pushsdk/push/j:z	()Ljava/lang/String;
    //   364: new 131	java/lang/StringBuilder
    //   367: dup
    //   368: ldc 190
    //   370: invokespecial 136	java/lang/StringBuilder:<init>	(Ljava/lang/String;)V
    //   373: aload_0
    //   374: getfield 18	com/alipay/pushsdk/push/n:a	Lcom/alipay/pushsdk/push/j;
    //   377: invokevirtual 193	java/lang/Object:hashCode	()I
    //   380: invokevirtual 188	java/lang/StringBuilder:append	(I)Ljava/lang/StringBuilder;
    //   383: invokevirtual 152	java/lang/StringBuilder:toString	()Ljava/lang/String;
    //   386: invokestatic 39	com/alipay/pushsdk/c/a/c:a	(ILjava/lang/String;Ljava/lang/String;)V
    //   389: aload_0
    //   390: getfield 18	com/alipay/pushsdk/push/n:a	Lcom/alipay/pushsdk/push/j;
    //   393: invokevirtual 197	com/alipay/pushsdk/push/j:d	()Lcom/alipay/pushsdk/push/a/m;
    //   396: aload_2
    //   397: invokevirtual 200	com/alipay/pushsdk/push/a/m:a	(Lcom/alipay/pushsdk/push/c/a;)V
    //   400: return
    //   401: astore_1
    //   402: aload_1
    //   403: invokevirtual 203	java/lang/Exception:printStackTrace	()V
    //   406: return
    //   407: aload_3
    //   408: ldc 82
    //   410: ldc 90
    //   412: invokevirtual 88	org/json/JSONObject:put	(Ljava/lang/String;Ljava/lang/Object;)Lorg/json/JSONObject;
    //   415: pop
    //   416: goto -327 -> 89
    //   419: astore 4
    //   421: aload 4
    //   423: invokevirtual 204	org/json/JSONException:printStackTrace	()V
    //   426: goto -160 -> 266
    //   429: aload 7
    //   431: ifnull -307 -> 124
    //   434: aload 7
    //   436: ldc 206
    //   438: invokevirtual 104	java/lang/String:equals	(Ljava/lang/Object;)Z
    //   441: ifeq -317 -> 124
    //   444: ldc 208
    //   446: astore 6
    //   448: goto -324 -> 124
    //   451: iconst_2
    //   452: invokestatic 32	com/alipay/pushsdk/push/j:z	()Ljava/lang/String;
    //   455: ldc 210
    //   457: invokestatic 39	com/alipay/pushsdk/c/a/c:a	(ILjava/lang/String;Ljava/lang/String;)V
    //   460: return
    //   461: iconst_3
    //   462: invokestatic 32	com/alipay/pushsdk/push/j:z	()Ljava/lang/String;
    //   465: ldc 212
    //   467: invokestatic 39	com/alipay/pushsdk/c/a/c:a	(ILjava/lang/String;Ljava/lang/String;)V
    //   470: return
    //
    // Exception table:
    //   from	to	target	type
    //   19	40	401	java/lang/Exception
    //   62	89	419	org/json/JSONException
    //   93	105	419	org/json/JSONException
    //   110	120	419	org/json/JSONException
    //   124	266	419	org/json/JSONException
    //   407	416	419	org/json/JSONException
    //   434	444	419	org/json/JSONException
  }
}

/* Location:           /Users/don/DeSources/alipay/backup/zhifubaoqianbao_52/classes-dex2jar.jar
 * Qualified Name:     com.alipay.pushsdk.push.n
 * JD-Core Version:    0.6.2
 */