package com.alipay.mobile.logmonitor;

final class a
  implements Runnable
{
  // ERROR //
  public final void run()
  {
    // Byte code:
    //   0: invokestatic 27	java/lang/Thread:currentThread	()Ljava/lang/Thread;
    //   3: new 29	com/alipay/mobile/logmonitor/b
    //   6: dup
    //   7: aload_0
    //   8: invokespecial 32	com/alipay/mobile/logmonitor/b:<init>	(Lcom/alipay/mobile/logmonitor/a;)V
    //   11: invokevirtual 36	java/lang/Thread:setUncaughtExceptionHandler	(Ljava/lang/Thread$UncaughtExceptionHandler;)V
    //   14: invokestatic 42	java/lang/System:currentTimeMillis	()J
    //   17: ldc2_w 43
    //   20: lsub
    //   21: lstore_1
    //   22: new 46	java/util/ArrayList
    //   25: dup
    //   26: invokespecial 47	java/util/ArrayList:<init>	()V
    //   29: astore_3
    //   30: invokestatic 53	android/os/Environment:getExternalStorageState	()Ljava/lang/String;
    //   33: ifnull +87 -> 120
    //   36: invokestatic 53	android/os/Environment:getExternalStorageState	()Ljava/lang/String;
    //   39: ldc 55
    //   41: invokevirtual 61	java/lang/String:equals	(Ljava/lang/Object;)Z
    //   44: istore 4
    //   46: iconst_0
    //   47: istore 5
    //   49: iload 4
    //   51: ifeq +69 -> 120
    //   54: invokestatic 67	com/alipay/mobile/logmonitor/Logcat:a	()Z
    //   57: ifeq +63 -> 120
    //   60: iload 5
    //   62: iconst_5
    //   63: if_icmpge +57 -> 120
    //   66: invokestatic 72	com/alipay/mobile/logmonitor/util/LogMonitorUtil:currentTime	()J
    //   69: lstore 15
    //   71: invokestatic 78	com/alipay/mobile/common/info/DeviceInfo:getInstance	()Lcom/alipay/mobile/common/info/DeviceInfo;
    //   74: ldc 80
    //   76: invokevirtual 84	com/alipay/mobile/common/info/DeviceInfo:getExternalStoragePath	(Ljava/lang/String;)Ljava/lang/String;
    //   79: astore 17
    //   81: aload 17
    //   83: ifnonnull +38 -> 121
    //   86: invokestatic 88	com/alipay/mobile/logmonitor/Logcat:d	()Ljava/io/BufferedReader;
    //   89: ifnull +14 -> 103
    //   92: invokestatic 88	com/alipay/mobile/logmonitor/Logcat:d	()Ljava/io/BufferedReader;
    //   95: invokevirtual 93	java/io/BufferedReader:close	()V
    //   98: aconst_null
    //   99: invokestatic 96	com/alipay/mobile/logmonitor/Logcat:a	(Ljava/io/BufferedReader;)Ljava/io/BufferedReader;
    //   102: pop
    //   103: invokestatic 100	com/alipay/mobile/logmonitor/Logcat:b	()Ljava/lang/Process;
    //   106: ifnull +14 -> 120
    //   109: invokestatic 100	com/alipay/mobile/logmonitor/Logcat:b	()Ljava/lang/Process;
    //   112: invokevirtual 105	java/lang/Process:destroy	()V
    //   115: aconst_null
    //   116: invokestatic 108	com/alipay/mobile/logmonitor/Logcat:a	(Ljava/lang/Process;)Ljava/lang/Process;
    //   119: pop
    //   120: return
    //   121: new 110	java/io/File
    //   124: dup
    //   125: aload 17
    //   127: invokespecial 113	java/io/File:<init>	(Ljava/lang/String;)V
    //   130: astore 18
    //   132: aload 18
    //   134: invokevirtual 116	java/io/File:exists	()Z
    //   137: ifne +9 -> 146
    //   140: aload 18
    //   142: invokevirtual 119	java/io/File:mkdirs	()Z
    //   145: pop
    //   146: aload 18
    //   148: invokevirtual 123	java/io/File:listFiles	()[Ljava/io/File;
    //   151: astore 19
    //   153: aload_3
    //   154: invokeinterface 128 1 0
    //   159: invokestatic 131	com/alipay/mobile/logmonitor/util/LogMonitorUtil:currentDate	()Ljava/lang/String;
    //   162: astore 20
    //   164: aload_3
    //   165: new 133	java/lang/StringBuilder
    //   168: dup
    //   169: ldc 135
    //   171: invokespecial 136	java/lang/StringBuilder:<init>	(Ljava/lang/String;)V
    //   174: aload 20
    //   176: invokevirtual 140	java/lang/StringBuilder:append	(Ljava/lang/String;)Ljava/lang/StringBuilder;
    //   179: ldc 142
    //   181: invokevirtual 140	java/lang/StringBuilder:append	(Ljava/lang/String;)Ljava/lang/StringBuilder;
    //   184: invokevirtual 145	java/lang/StringBuilder:toString	()Ljava/lang/String;
    //   187: invokeinterface 148 2 0
    //   192: pop
    //   193: aload_3
    //   194: new 133	java/lang/StringBuilder
    //   197: dup
    //   198: ldc 135
    //   200: invokespecial 136	java/lang/StringBuilder:<init>	(Ljava/lang/String;)V
    //   203: aload 20
    //   205: iconst_m1
    //   206: invokestatic 152	com/alipay/mobile/logmonitor/util/LogMonitorUtil:getSpecifiedDay	(Ljava/lang/String;I)Ljava/lang/String;
    //   209: invokevirtual 140	java/lang/StringBuilder:append	(Ljava/lang/String;)Ljava/lang/StringBuilder;
    //   212: ldc 142
    //   214: invokevirtual 140	java/lang/StringBuilder:append	(Ljava/lang/String;)Ljava/lang/StringBuilder;
    //   217: invokevirtual 145	java/lang/StringBuilder:toString	()Ljava/lang/String;
    //   220: invokeinterface 148 2 0
    //   225: pop
    //   226: aload_3
    //   227: new 133	java/lang/StringBuilder
    //   230: dup
    //   231: ldc 135
    //   233: invokespecial 136	java/lang/StringBuilder:<init>	(Ljava/lang/String;)V
    //   236: aload 20
    //   238: bipush 254
    //   240: invokestatic 152	com/alipay/mobile/logmonitor/util/LogMonitorUtil:getSpecifiedDay	(Ljava/lang/String;I)Ljava/lang/String;
    //   243: invokevirtual 140	java/lang/StringBuilder:append	(Ljava/lang/String;)Ljava/lang/StringBuilder;
    //   246: ldc 142
    //   248: invokevirtual 140	java/lang/StringBuilder:append	(Ljava/lang/String;)Ljava/lang/StringBuilder;
    //   251: invokevirtual 145	java/lang/StringBuilder:toString	()Ljava/lang/String;
    //   254: invokeinterface 148 2 0
    //   259: pop
    //   260: aload 19
    //   262: ifnull +54 -> 316
    //   265: aload 19
    //   267: arraylength
    //   268: ifle +48 -> 316
    //   271: aload 19
    //   273: arraylength
    //   274: istore 72
    //   276: iconst_0
    //   277: istore 73
    //   279: iload 73
    //   281: iload 72
    //   283: if_icmpge +33 -> 316
    //   286: aload 19
    //   288: iload 73
    //   290: aaload
    //   291: astore 74
    //   293: aload_3
    //   294: aload 74
    //   296: invokevirtual 155	java/io/File:getName	()Ljava/lang/String;
    //   299: invokeinterface 158 2 0
    //   304: ifne +741 -> 1045
    //   307: aload 74
    //   309: invokevirtual 161	java/io/File:delete	()Z
    //   312: pop
    //   313: goto +732 -> 1045
    //   316: new 110	java/io/File
    //   319: dup
    //   320: new 133	java/lang/StringBuilder
    //   323: dup
    //   324: invokespecial 162	java/lang/StringBuilder:<init>	()V
    //   327: aload 18
    //   329: invokevirtual 165	java/io/File:getAbsolutePath	()Ljava/lang/String;
    //   332: invokevirtual 140	java/lang/StringBuilder:append	(Ljava/lang/String;)Ljava/lang/StringBuilder;
    //   335: getstatic 169	java/io/File:separatorChar	C
    //   338: invokevirtual 172	java/lang/StringBuilder:append	(C)Ljava/lang/StringBuilder;
    //   341: ldc 135
    //   343: invokevirtual 140	java/lang/StringBuilder:append	(Ljava/lang/String;)Ljava/lang/StringBuilder;
    //   346: aload 20
    //   348: invokevirtual 140	java/lang/StringBuilder:append	(Ljava/lang/String;)Ljava/lang/StringBuilder;
    //   351: ldc 142
    //   353: invokevirtual 140	java/lang/StringBuilder:append	(Ljava/lang/String;)Ljava/lang/StringBuilder;
    //   356: invokevirtual 145	java/lang/StringBuilder:toString	()Ljava/lang/String;
    //   359: invokespecial 113	java/io/File:<init>	(Ljava/lang/String;)V
    //   362: astore 24
    //   364: new 174	com/alipay/mobile/logmonitor/model/LogFileModel
    //   367: dup
    //   368: aload 24
    //   370: invokespecial 177	com/alipay/mobile/logmonitor/model/LogFileModel:<init>	(Ljava/io/File;)V
    //   373: astore 25
    //   375: new 179	java/io/BufferedWriter
    //   378: dup
    //   379: new 181	java/io/FileWriter
    //   382: dup
    //   383: aload 24
    //   385: iconst_1
    //   386: invokespecial 184	java/io/FileWriter:<init>	(Ljava/io/File;Z)V
    //   389: invokespecial 187	java/io/BufferedWriter:<init>	(Ljava/io/Writer;)V
    //   392: astore 26
    //   394: aload 26
    //   396: invokestatic 190	com/alipay/mobile/logmonitor/Logcat:a	(Ljava/io/BufferedWriter;)Ljava/io/BufferedWriter;
    //   399: pop
    //   400: aload 25
    //   402: invokestatic 193	com/alipay/mobile/logmonitor/Logcat:a	(Lcom/alipay/mobile/logmonitor/model/LogFileModel;)Lcom/alipay/mobile/logmonitor/model/LogFileModel;
    //   405: pop
    //   406: invokestatic 199	java/lang/Runtime:getRuntime	()Ljava/lang/Runtime;
    //   409: ldc 201
    //   411: invokevirtual 205	java/lang/Runtime:exec	(Ljava/lang/String;)Ljava/lang/Process;
    //   414: invokestatic 108	com/alipay/mobile/logmonitor/Logcat:a	(Ljava/lang/Process;)Ljava/lang/Process;
    //   417: pop
    //   418: new 90	java/io/BufferedReader
    //   421: dup
    //   422: new 207	java/io/InputStreamReader
    //   425: dup
    //   426: invokestatic 100	com/alipay/mobile/logmonitor/Logcat:b	()Ljava/lang/Process;
    //   429: invokevirtual 211	java/lang/Process:getInputStream	()Ljava/io/InputStream;
    //   432: invokespecial 214	java/io/InputStreamReader:<init>	(Ljava/io/InputStream;)V
    //   435: sipush 1024
    //   438: invokespecial 217	java/io/BufferedReader:<init>	(Ljava/io/Reader;I)V
    //   441: invokestatic 96	com/alipay/mobile/logmonitor/Logcat:a	(Ljava/io/BufferedReader;)Ljava/io/BufferedReader;
    //   444: pop
    //   445: invokestatic 220	com/alipay/mobile/logmonitor/Logcat:c	()Z
    //   448: pop
    //   449: lload_1
    //   450: lstore 35
    //   452: aconst_null
    //   453: astore 49
    //   455: invokestatic 67	com/alipay/mobile/logmonitor/Logcat:a	()Z
    //   458: ifeq +573 -> 1031
    //   461: invokestatic 88	com/alipay/mobile/logmonitor/Logcat:d	()Ljava/io/BufferedReader;
    //   464: invokevirtual 223	java/io/BufferedReader:readLine	()Ljava/lang/String;
    //   467: astore 59
    //   469: aload 59
    //   471: ifnull +550 -> 1021
    //   474: invokestatic 227	com/alipay/mobile/logmonitor/Logcat:e	()Ljava/util/concurrent/atomic/AtomicBoolean;
    //   477: invokevirtual 232	java/util/concurrent/atomic/AtomicBoolean:get	()Z
    //   480: ifeq +20 -> 500
    //   483: invokestatic 227	com/alipay/mobile/logmonitor/Logcat:e	()Ljava/util/concurrent/atomic/AtomicBoolean;
    //   486: astore 69
    //   488: aload 69
    //   490: monitorenter
    //   491: invokestatic 227	com/alipay/mobile/logmonitor/Logcat:e	()Ljava/util/concurrent/atomic/AtomicBoolean;
    //   494: invokevirtual 235	java/lang/Object:wait	()V
    //   497: aload 69
    //   499: monitorexit
    //   500: invokestatic 238	com/alipay/mobile/logmonitor/Logcat:f	()Z
    //   503: istore 60
    //   505: iload 60
    //   507: ifeq +20 -> 527
    //   510: ldc2_w 239
    //   513: invokestatic 244	java/lang/Thread:sleep	(J)V
    //   516: getstatic 250	com/alipay/mobile/logmonitor/util/LogMonitorConstans:GLOBAL_LOCK	Ljava/lang/Object;
    //   519: astore 68
    //   521: aload 68
    //   523: monitorenter
    //   524: aload 68
    //   526: monitorexit
    //   527: invokestatic 220	com/alipay/mobile/logmonitor/Logcat:c	()Z
    //   530: pop
    //   531: aload 59
    //   533: invokestatic 253	com/alipay/mobile/logmonitor/Logcat:a	(Ljava/lang/String;)Z
    //   536: ifeq +478 -> 1014
    //   539: aload 59
    //   541: invokestatic 256	com/alipay/mobile/logmonitor/Logcat:b	(Ljava/lang/String;)J
    //   544: lstore_1
    //   545: lload_1
    //   546: lload 35
    //   548: lcmp
    //   549: ifle +465 -> 1014
    //   552: aload 25
    //   554: aload 59
    //   556: aload 26
    //   558: invokevirtual 259	com/alipay/mobile/logmonitor/model/LogFileModel:a	(Ljava/lang/String;Ljava/io/BufferedWriter;)Z
    //   561: istore 62
    //   563: iload 62
    //   565: ifne +171 -> 736
    //   568: iinc 5 255
    //   571: lload 35
    //   573: lstore_1
    //   574: aload 59
    //   576: astore 53
    //   578: aload 53
    //   580: ifnonnull +210 -> 790
    //   583: aload 26
    //   585: invokevirtual 260	java/io/BufferedWriter:close	()V
    //   588: invokestatic 88	com/alipay/mobile/logmonitor/Logcat:d	()Ljava/io/BufferedReader;
    //   591: ifnull +14 -> 605
    //   594: invokestatic 88	com/alipay/mobile/logmonitor/Logcat:d	()Ljava/io/BufferedReader;
    //   597: invokevirtual 93	java/io/BufferedReader:close	()V
    //   600: aconst_null
    //   601: invokestatic 96	com/alipay/mobile/logmonitor/Logcat:a	(Ljava/io/BufferedReader;)Ljava/io/BufferedReader;
    //   604: pop
    //   605: invokestatic 100	com/alipay/mobile/logmonitor/Logcat:b	()Ljava/lang/Process;
    //   608: ifnull -488 -> 120
    //   611: invokestatic 100	com/alipay/mobile/logmonitor/Logcat:b	()Ljava/lang/Process;
    //   614: invokevirtual 105	java/lang/Process:destroy	()V
    //   617: aconst_null
    //   618: invokestatic 108	com/alipay/mobile/logmonitor/Logcat:a	(Ljava/lang/Process;)Ljava/lang/Process;
    //   621: pop
    //   622: return
    //   623: astore 27
    //   625: new 262	java/lang/RuntimeException
    //   628: dup
    //   629: aload 27
    //   631: invokespecial 265	java/lang/RuntimeException:<init>	(Ljava/lang/Throwable;)V
    //   634: athrow
    //   635: astore 10
    //   637: ldc2_w 266
    //   640: invokestatic 244	java/lang/Thread:sleep	(J)V
    //   643: invokestatic 88	com/alipay/mobile/logmonitor/Logcat:d	()Ljava/io/BufferedReader;
    //   646: ifnull +14 -> 660
    //   649: invokestatic 88	com/alipay/mobile/logmonitor/Logcat:d	()Ljava/io/BufferedReader;
    //   652: invokevirtual 93	java/io/BufferedReader:close	()V
    //   655: aconst_null
    //   656: invokestatic 96	com/alipay/mobile/logmonitor/Logcat:a	(Ljava/io/BufferedReader;)Ljava/io/BufferedReader;
    //   659: pop
    //   660: invokestatic 100	com/alipay/mobile/logmonitor/Logcat:b	()Ljava/lang/Process;
    //   663: ifnull +14 -> 677
    //   666: invokestatic 100	com/alipay/mobile/logmonitor/Logcat:b	()Ljava/lang/Process;
    //   669: invokevirtual 105	java/lang/Process:destroy	()V
    //   672: aconst_null
    //   673: invokestatic 108	com/alipay/mobile/logmonitor/Logcat:a	(Ljava/lang/Process;)Ljava/lang/Process;
    //   676: pop
    //   677: iinc 5 1
    //   680: goto -626 -> 54
    //   683: astore 71
    //   685: aload 69
    //   687: monitorexit
    //   688: aload 71
    //   690: athrow
    //   691: astore 51
    //   693: lload 35
    //   695: lstore_1
    //   696: aload 26
    //   698: invokevirtual 260	java/io/BufferedWriter:close	()V
    //   701: invokestatic 88	com/alipay/mobile/logmonitor/Logcat:d	()Ljava/io/BufferedReader;
    //   704: ifnull +14 -> 718
    //   707: invokestatic 88	com/alipay/mobile/logmonitor/Logcat:d	()Ljava/io/BufferedReader;
    //   710: invokevirtual 93	java/io/BufferedReader:close	()V
    //   713: aconst_null
    //   714: invokestatic 96	com/alipay/mobile/logmonitor/Logcat:a	(Ljava/io/BufferedReader;)Ljava/io/BufferedReader;
    //   717: pop
    //   718: invokestatic 100	com/alipay/mobile/logmonitor/Logcat:b	()Ljava/lang/Process;
    //   721: ifnull -601 -> 120
    //   724: invokestatic 100	com/alipay/mobile/logmonitor/Logcat:b	()Ljava/lang/Process;
    //   727: invokevirtual 105	java/lang/Process:destroy	()V
    //   730: aconst_null
    //   731: invokestatic 108	com/alipay/mobile/logmonitor/Logcat:a	(Ljava/lang/Process;)Ljava/lang/Process;
    //   734: pop
    //   735: return
    //   736: aload 25
    //   738: invokevirtual 269	com/alipay/mobile/logmonitor/model/LogFileModel:b	()Z
    //   741: ifne +16 -> 757
    //   744: invokestatic 72	com/alipay/mobile/logmonitor/util/LogMonitorUtil:currentTime	()J
    //   747: lstore 65
    //   749: lload 15
    //   751: lload 65
    //   753: lcmp
    //   754: ifge +260 -> 1014
    //   757: aload 25
    //   759: aload 26
    //   761: invokestatic 272	com/alipay/mobile/logmonitor/Logcat:a	(Lcom/alipay/mobile/logmonitor/model/LogFileModel;Ljava/io/BufferedWriter;)Z
    //   764: ifeq +243 -> 1007
    //   767: invokestatic 72	com/alipay/mobile/logmonitor/util/LogMonitorUtil:currentTime	()J
    //   770: lstore 63
    //   772: lload 15
    //   774: lload 63
    //   776: lcmp
    //   777: ifge +220 -> 997
    //   780: iinc 5 255
    //   783: aload 59
    //   785: astore 53
    //   787: goto -209 -> 578
    //   790: aload 26
    //   792: invokevirtual 260	java/io/BufferedWriter:close	()V
    //   795: invokestatic 88	com/alipay/mobile/logmonitor/Logcat:d	()Ljava/io/BufferedReader;
    //   798: ifnull +14 -> 812
    //   801: invokestatic 88	com/alipay/mobile/logmonitor/Logcat:d	()Ljava/io/BufferedReader;
    //   804: invokevirtual 93	java/io/BufferedReader:close	()V
    //   807: aconst_null
    //   808: invokestatic 96	com/alipay/mobile/logmonitor/Logcat:a	(Ljava/io/BufferedReader;)Ljava/io/BufferedReader;
    //   811: pop
    //   812: invokestatic 100	com/alipay/mobile/logmonitor/Logcat:b	()Ljava/lang/Process;
    //   815: ifnull +14 -> 829
    //   818: invokestatic 100	com/alipay/mobile/logmonitor/Logcat:b	()Ljava/lang/Process;
    //   821: invokevirtual 105	java/lang/Process:destroy	()V
    //   824: aconst_null
    //   825: invokestatic 108	com/alipay/mobile/logmonitor/Logcat:a	(Ljava/lang/Process;)Ljava/lang/Process;
    //   828: pop
    //   829: iinc 5 1
    //   832: goto -778 -> 54
    //   835: astore 40
    //   837: aload 26
    //   839: invokevirtual 260	java/io/BufferedWriter:close	()V
    //   842: goto -47 -> 795
    //   845: astore 41
    //   847: goto -52 -> 795
    //   850: astore 34
    //   852: lload_1
    //   853: lstore 35
    //   855: aload 34
    //   857: astore 37
    //   859: aload 26
    //   861: invokevirtual 260	java/io/BufferedWriter:close	()V
    //   864: aload 37
    //   866: athrow
    //   867: astore 39
    //   869: lload 35
    //   871: lstore_1
    //   872: goto -235 -> 637
    //   875: astore 6
    //   877: invokestatic 88	com/alipay/mobile/logmonitor/Logcat:d	()Ljava/io/BufferedReader;
    //   880: ifnull +14 -> 894
    //   883: invokestatic 88	com/alipay/mobile/logmonitor/Logcat:d	()Ljava/io/BufferedReader;
    //   886: invokevirtual 93	java/io/BufferedReader:close	()V
    //   889: aconst_null
    //   890: invokestatic 96	com/alipay/mobile/logmonitor/Logcat:a	(Ljava/io/BufferedReader;)Ljava/io/BufferedReader;
    //   893: pop
    //   894: invokestatic 100	com/alipay/mobile/logmonitor/Logcat:b	()Ljava/lang/Process;
    //   897: ifnull +14 -> 911
    //   900: invokestatic 100	com/alipay/mobile/logmonitor/Logcat:b	()Ljava/lang/Process;
    //   903: invokevirtual 105	java/lang/Process:destroy	()V
    //   906: aconst_null
    //   907: invokestatic 108	com/alipay/mobile/logmonitor/Logcat:a	(Ljava/lang/Process;)Ljava/lang/Process;
    //   910: pop
    //   911: aload 6
    //   913: athrow
    //   914: astore 67
    //   916: goto -400 -> 516
    //   919: astore 55
    //   921: goto -333 -> 588
    //   924: astore 54
    //   926: goto -131 -> 795
    //   929: astore 30
    //   931: goto -230 -> 701
    //   934: astore 38
    //   936: goto -72 -> 864
    //   939: astore 11
    //   941: goto -298 -> 643
    //   944: astore 8
    //   946: goto -52 -> 894
    //   949: astore 13
    //   951: goto -291 -> 660
    //   954: astore 43
    //   956: goto -144 -> 812
    //   959: astore 37
    //   961: goto -102 -> 859
    //   964: astore 50
    //   966: lload 35
    //   968: lstore_1
    //   969: goto -132 -> 837
    //   972: astore 32
    //   974: goto -256 -> 718
    //   977: astore 29
    //   979: goto -283 -> 696
    //   982: astore 57
    //   984: goto -379 -> 605
    //   987: astore 70
    //   989: goto -492 -> 497
    //   992: astore 78
    //   994: goto -891 -> 103
    //   997: lload_1
    //   998: lstore 35
    //   1000: aload 59
    //   1002: astore 49
    //   1004: goto -549 -> 455
    //   1007: aload 59
    //   1009: astore 53
    //   1011: goto -433 -> 578
    //   1014: aload 59
    //   1016: astore 49
    //   1018: goto -563 -> 455
    //   1021: lload 35
    //   1023: lstore_1
    //   1024: aload 59
    //   1026: astore 53
    //   1028: goto -450 -> 578
    //   1031: aload 49
    //   1033: astore 52
    //   1035: lload 35
    //   1037: lstore_1
    //   1038: aload 52
    //   1040: astore 53
    //   1042: goto -464 -> 578
    //   1045: iinc 73 1
    //   1048: goto -769 -> 279
    //
    // Exception table:
    //   from	to	target	type
    //   375	400	623	java/io/FileNotFoundException
    //   66	81	635	java/lang/Throwable
    //   121	146	635	java/lang/Throwable
    //   146	260	635	java/lang/Throwable
    //   265	276	635	java/lang/Throwable
    //   286	313	635	java/lang/Throwable
    //   316	375	635	java/lang/Throwable
    //   375	400	635	java/lang/Throwable
    //   583	588	635	java/lang/Throwable
    //   625	635	635	java/lang/Throwable
    //   696	701	635	java/lang/Throwable
    //   790	795	635	java/lang/Throwable
    //   837	842	635	java/lang/Throwable
    //   491	497	683	finally
    //   497	500	683	finally
    //   455	469	691	java/io/IOException
    //   474	491	691	java/io/IOException
    //   500	505	691	java/io/IOException
    //   510	516	691	java/io/IOException
    //   516	527	691	java/io/IOException
    //   527	545	691	java/io/IOException
    //   552	563	691	java/io/IOException
    //   685	691	691	java/io/IOException
    //   736	749	691	java/io/IOException
    //   400	449	835	java/lang/Exception
    //   757	772	835	java/lang/Exception
    //   837	842	845	java/lang/Exception
    //   400	449	850	finally
    //   757	772	850	finally
    //   859	864	867	java/lang/Throwable
    //   864	867	867	java/lang/Throwable
    //   66	81	875	finally
    //   121	146	875	finally
    //   146	260	875	finally
    //   265	276	875	finally
    //   286	313	875	finally
    //   316	375	875	finally
    //   375	400	875	finally
    //   583	588	875	finally
    //   625	635	875	finally
    //   637	643	875	finally
    //   696	701	875	finally
    //   790	795	875	finally
    //   837	842	875	finally
    //   859	864	875	finally
    //   864	867	875	finally
    //   510	516	914	java/lang/Throwable
    //   583	588	919	java/lang/Exception
    //   790	795	924	java/lang/Exception
    //   696	701	929	java/lang/Exception
    //   859	864	934	java/lang/Exception
    //   637	643	939	java/lang/InterruptedException
    //   883	894	944	java/io/IOException
    //   649	660	949	java/io/IOException
    //   801	812	954	java/io/IOException
    //   455	469	959	finally
    //   474	491	959	finally
    //   500	505	959	finally
    //   510	516	959	finally
    //   516	527	959	finally
    //   527	545	959	finally
    //   552	563	959	finally
    //   685	691	959	finally
    //   736	749	959	finally
    //   455	469	964	java/lang/Exception
    //   474	491	964	java/lang/Exception
    //   500	505	964	java/lang/Exception
    //   510	516	964	java/lang/Exception
    //   516	527	964	java/lang/Exception
    //   527	545	964	java/lang/Exception
    //   552	563	964	java/lang/Exception
    //   685	691	964	java/lang/Exception
    //   736	749	964	java/lang/Exception
    //   707	718	972	java/io/IOException
    //   400	449	977	java/io/IOException
    //   757	772	977	java/io/IOException
    //   594	605	982	java/io/IOException
    //   491	497	987	java/lang/Throwable
    //   92	103	992	java/io/IOException
  }
}

/* Location:           /Users/don/DeSources/alipay/backup/zhifubaoqianbao_52/classes-dex2jar.jar
 * Qualified Name:     com.alipay.mobile.logmonitor.a
 * JD-Core Version:    0.6.2
 */