package com.alipay.mobile.security.securitycommon;

final class a
  implements Runnable
{
  a(AutoReadSmsCheckCode paramAutoReadSmsCheckCode, int paramInt1, String[] paramArrayOfString, String paramString1, int paramInt2, String paramString2)
  {
  }

  // ERROR //
  public final void run()
  {
    // Byte code:
    //   0: invokestatic 42	com/alipay/mobile/framework/AlipayApplication:getInstance	()Lcom/alipay/mobile/framework/AlipayApplication;
    //   3: invokevirtual 46	com/alipay/mobile/framework/AlipayApplication:getMicroApplicationContext	()Lcom/alipay/mobile/framework/MicroApplicationContext;
    //   6: invokeinterface 51 1 0
    //   11: astore_1
    //   12: invokestatic 57	java/lang/System:currentTimeMillis	()J
    //   15: lstore 12
    //   17: sipush 1000
    //   20: aload_0
    //   21: getfield 22	com/alipay/mobile/security/securitycommon/a:a	I
    //   24: imul
    //   25: i2l
    //   26: lstore 14
    //   28: aload_0
    //   29: getfield 20	com/alipay/mobile/security/securitycommon/a:f	Lcom/alipay/mobile/security/securitycommon/AutoReadSmsCheckCode;
    //   32: aload_0
    //   33: getfield 20	com/alipay/mobile/security/securitycommon/a:f	Lcom/alipay/mobile/security/securitycommon/AutoReadSmsCheckCode;
    //   36: aload_1
    //   37: invokestatic 63	com/alipay/mobile/security/securitycommon/AutoReadSmsCheckCode:access$100	(Lcom/alipay/mobile/security/securitycommon/AutoReadSmsCheckCode;Landroid/content/Context;)J
    //   40: invokestatic 67	com/alipay/mobile/security/securitycommon/AutoReadSmsCheckCode:access$002	(Lcom/alipay/mobile/security/securitycommon/AutoReadSmsCheckCode;J)J
    //   43: pop2
    //   44: aload_0
    //   45: getfield 20	com/alipay/mobile/security/securitycommon/a:f	Lcom/alipay/mobile/security/securitycommon/AutoReadSmsCheckCode;
    //   48: aload_0
    //   49: getfield 24	com/alipay/mobile/security/securitycommon/a:b	[Ljava/lang/String;
    //   52: aload_0
    //   53: getfield 26	com/alipay/mobile/security/securitycommon/a:c	Ljava/lang/String;
    //   56: aload_0
    //   57: getfield 28	com/alipay/mobile/security/securitycommon/a:d	I
    //   60: aload_0
    //   61: getfield 30	com/alipay/mobile/security/securitycommon/a:e	Ljava/lang/String;
    //   64: aload_1
    //   65: lload 12
    //   67: lload 14
    //   69: invokestatic 71	com/alipay/mobile/security/securitycommon/AutoReadSmsCheckCode:access$200	(Lcom/alipay/mobile/security/securitycommon/AutoReadSmsCheckCode;[Ljava/lang/String;Ljava/lang/String;ILjava/lang/String;Landroid/content/Context;JJ)V
    //   72: aload_0
    //   73: getfield 20	com/alipay/mobile/security/securitycommon/a:f	Lcom/alipay/mobile/security/securitycommon/AutoReadSmsCheckCode;
    //   76: iconst_0
    //   77: invokestatic 75	com/alipay/mobile/security/securitycommon/AutoReadSmsCheckCode:access$302	(Lcom/alipay/mobile/security/securitycommon/AutoReadSmsCheckCode;Z)Z
    //   80: pop
    //   81: aload_0
    //   82: getfield 20	com/alipay/mobile/security/securitycommon/a:f	Lcom/alipay/mobile/security/securitycommon/AutoReadSmsCheckCode;
    //   85: iconst_1
    //   86: invokestatic 78	com/alipay/mobile/security/securitycommon/AutoReadSmsCheckCode:access$402	(Lcom/alipay/mobile/security/securitycommon/AutoReadSmsCheckCode;Z)Z
    //   89: pop
    //   90: aload_0
    //   91: getfield 20	com/alipay/mobile/security/securitycommon/a:f	Lcom/alipay/mobile/security/securitycommon/AutoReadSmsCheckCode;
    //   94: lconst_0
    //   95: invokestatic 81	com/alipay/mobile/security/securitycommon/AutoReadSmsCheckCode:access$502	(Lcom/alipay/mobile/security/securitycommon/AutoReadSmsCheckCode;J)J
    //   98: pop2
    //   99: return
    //   100: astore 7
    //   102: aload_0
    //   103: getfield 20	com/alipay/mobile/security/securitycommon/a:f	Lcom/alipay/mobile/security/securitycommon/AutoReadSmsCheckCode;
    //   106: iconst_0
    //   107: invokestatic 75	com/alipay/mobile/security/securitycommon/AutoReadSmsCheckCode:access$302	(Lcom/alipay/mobile/security/securitycommon/AutoReadSmsCheckCode;Z)Z
    //   110: pop
    //   111: aload_0
    //   112: getfield 20	com/alipay/mobile/security/securitycommon/a:f	Lcom/alipay/mobile/security/securitycommon/AutoReadSmsCheckCode;
    //   115: iconst_1
    //   116: invokestatic 78	com/alipay/mobile/security/securitycommon/AutoReadSmsCheckCode:access$402	(Lcom/alipay/mobile/security/securitycommon/AutoReadSmsCheckCode;Z)Z
    //   119: pop
    //   120: aload_0
    //   121: getfield 20	com/alipay/mobile/security/securitycommon/a:f	Lcom/alipay/mobile/security/securitycommon/AutoReadSmsCheckCode;
    //   124: lconst_0
    //   125: invokestatic 81	com/alipay/mobile/security/securitycommon/AutoReadSmsCheckCode:access$502	(Lcom/alipay/mobile/security/securitycommon/AutoReadSmsCheckCode;J)J
    //   128: pop2
    //   129: return
    //   130: astore_2
    //   131: aload_0
    //   132: getfield 20	com/alipay/mobile/security/securitycommon/a:f	Lcom/alipay/mobile/security/securitycommon/AutoReadSmsCheckCode;
    //   135: iconst_0
    //   136: invokestatic 75	com/alipay/mobile/security/securitycommon/AutoReadSmsCheckCode:access$302	(Lcom/alipay/mobile/security/securitycommon/AutoReadSmsCheckCode;Z)Z
    //   139: pop
    //   140: aload_0
    //   141: getfield 20	com/alipay/mobile/security/securitycommon/a:f	Lcom/alipay/mobile/security/securitycommon/AutoReadSmsCheckCode;
    //   144: iconst_1
    //   145: invokestatic 78	com/alipay/mobile/security/securitycommon/AutoReadSmsCheckCode:access$402	(Lcom/alipay/mobile/security/securitycommon/AutoReadSmsCheckCode;Z)Z
    //   148: pop
    //   149: aload_0
    //   150: getfield 20	com/alipay/mobile/security/securitycommon/a:f	Lcom/alipay/mobile/security/securitycommon/AutoReadSmsCheckCode;
    //   153: lconst_0
    //   154: invokestatic 81	com/alipay/mobile/security/securitycommon/AutoReadSmsCheckCode:access$502	(Lcom/alipay/mobile/security/securitycommon/AutoReadSmsCheckCode;J)J
    //   157: pop2
    //   158: aload_2
    //   159: athrow
    //
    // Exception table:
    //   from	to	target	type
    //   12	72	100	java/lang/Exception
    //   12	72	130	finally
  }
}

/* Location:           /Users/don/DeSources/alipay/backup/zhifubaoqianbao_52/classes-dex2jar.jar
 * Qualified Name:     com.alipay.mobile.security.securitycommon.a
 * JD-Core Version:    0.6.2
 */