package com.alipay.b.a;

public final class c extends Thread
{
  private boolean a = true;

  protected c(b paramb)
  {
  }

  private boolean a()
  {
    try
    {
      boolean bool = this.a;
      return bool;
    }
    finally
    {
      localObject = finally;
      throw localObject;
    }
  }

  public final void a(boolean paramBoolean)
  {
    try
    {
      this.a = paramBoolean;
      return;
    }
    finally
    {
      localObject = finally;
      throw localObject;
    }
  }

  // ERROR //
  public final void run()
  {
    // Byte code:
    //   0: ldc2_w 23
    //   3: invokestatic 28	java/lang/Thread:sleep	(J)V
    //   6: iconst_0
    //   7: istore_2
    //   8: aload_0
    //   9: invokespecial 30	com/alipay/b/a/c:a	()Z
    //   12: ifne +21 -> 33
    //   15: iload_2
    //   16: ifne -16 -> 0
    //   19: aload_0
    //   20: iconst_0
    //   21: invokevirtual 32	com/alipay/b/a/c:a	(Z)V
    //   24: invokestatic 37	com/alipay/b/a/d:a	()Lcom/alipay/b/a/d;
    //   27: invokevirtual 40	com/alipay/b/a/d:c	()V
    //   30: goto -30 -> 0
    //   33: ldc2_w 23
    //   36: invokestatic 28	java/lang/Thread:sleep	(J)V
    //   39: aload_0
    //   40: getfield 12	com/alipay/b/a/c:b	Lcom/alipay/b/a/b;
    //   43: invokevirtual 45	com/alipay/b/a/b:b	()[B
    //   46: astore 5
    //   48: aload 5
    //   50: ifnull +693 -> 743
    //   53: aload_0
    //   54: iconst_0
    //   55: invokevirtual 32	com/alipay/b/a/c:a	(Z)V
    //   58: invokestatic 37	com/alipay/b/a/d:a	()Lcom/alipay/b/a/d;
    //   61: invokevirtual 40	com/alipay/b/a/d:c	()V
    //   64: invokestatic 51	com/alipay/sonicwavenfc/SonicWaveNFC:getInstance	()Lcom/alipay/sonicwavenfc/SonicWaveNFC;
    //   67: invokevirtual 55	com/alipay/sonicwavenfc/SonicWaveNFC:getReceiveDataHandler	()Lcom/alipay/b/a/a;
    //   70: ifnull +787 -> 857
    //   73: aload_0
    //   74: getfield 12	com/alipay/b/a/c:b	Lcom/alipay/b/a/b;
    //   77: getfield 58	com/alipay/b/a/b:c	I
    //   80: ifne +101 -> 181
    //   83: bipush 32
    //   85: newarray byte
    //   87: astore 34
    //   89: iconst_0
    //   90: istore 35
    //   92: iconst_0
    //   93: istore 36
    //   95: iload 35
    //   97: aload_0
    //   98: getfield 12	com/alipay/b/a/c:b	Lcom/alipay/b/a/b;
    //   101: getfield 60	com/alipay/b/a/b:b	I
    //   104: if_icmplt +38 -> 142
    //   107: invokestatic 51	com/alipay/sonicwavenfc/SonicWaveNFC:getInstance	()Lcom/alipay/sonicwavenfc/SonicWaveNFC;
    //   110: invokevirtual 55	com/alipay/sonicwavenfc/SonicWaveNFC:getReceiveDataHandler	()Lcom/alipay/b/a/a;
    //   113: aload 34
    //   115: iload 36
    //   117: aload_0
    //   118: getfield 12	com/alipay/b/a/c:b	Lcom/alipay/b/a/b;
    //   121: getfield 63	com/alipay/b/a/b:e	Z
    //   124: aload_0
    //   125: getfield 12	com/alipay/b/a/c:b	Lcom/alipay/b/a/b;
    //   128: getfield 67	com/alipay/b/a/b:d	F
    //   131: f2d
    //   132: invokeinterface 73 6 0
    //   137: iconst_1
    //   138: istore_2
    //   139: goto -124 -> 15
    //   142: aload_0
    //   143: getfield 12	com/alipay/b/a/c:b	Lcom/alipay/b/a/b;
    //   146: getfield 76	com/alipay/b/a/b:a	[B
    //   149: iload 35
    //   151: baload
    //   152: ifne +8 -> 160
    //   155: iload 36
    //   157: ifeq +694 -> 851
    //   160: aload 34
    //   162: iload 36
    //   164: aload_0
    //   165: getfield 12	com/alipay/b/a/c:b	Lcom/alipay/b/a/b;
    //   168: getfield 76	com/alipay/b/a/b:a	[B
    //   171: iload 35
    //   173: baload
    //   174: bastore
    //   175: iinc 36 1
    //   178: goto +673 -> 851
    //   181: aload_0
    //   182: getfield 12	com/alipay/b/a/c:b	Lcom/alipay/b/a/b;
    //   185: getfield 58	com/alipay/b/a/b:c	I
    //   188: iconst_1
    //   189: if_icmpne +69 -> 258
    //   192: sipush 128
    //   195: newarray byte
    //   197: astore 27
    //   199: ldc 78
    //   201: invokevirtual 84	java/lang/String:length	()I
    //   204: istore 28
    //   206: iconst_0
    //   207: istore 29
    //   209: iload 29
    //   211: aload_0
    //   212: getfield 12	com/alipay/b/a/c:b	Lcom/alipay/b/a/b;
    //   215: getfield 60	com/alipay/b/a/b:b	I
    //   218: if_icmplt +118 -> 336
    //   221: invokestatic 51	com/alipay/sonicwavenfc/SonicWaveNFC:getInstance	()Lcom/alipay/sonicwavenfc/SonicWaveNFC;
    //   224: invokevirtual 55	com/alipay/sonicwavenfc/SonicWaveNFC:getReceiveDataHandler	()Lcom/alipay/b/a/a;
    //   227: aload 27
    //   229: aload_0
    //   230: getfield 12	com/alipay/b/a/c:b	Lcom/alipay/b/a/b;
    //   233: getfield 60	com/alipay/b/a/b:b	I
    //   236: iconst_1
    //   237: ishl
    //   238: aload_0
    //   239: getfield 12	com/alipay/b/a/c:b	Lcom/alipay/b/a/b;
    //   242: getfield 63	com/alipay/b/a/b:e	Z
    //   245: aload_0
    //   246: getfield 12	com/alipay/b/a/c:b	Lcom/alipay/b/a/b;
    //   249: getfield 67	com/alipay/b/a/b:d	F
    //   252: f2d
    //   253: invokeinterface 73 6 0
    //   258: aload_0
    //   259: getfield 12	com/alipay/b/a/c:b	Lcom/alipay/b/a/b;
    //   262: getfield 58	com/alipay/b/a/b:c	I
    //   265: iconst_3
    //   266: if_icmpne +591 -> 857
    //   269: sipush 128
    //   272: newarray byte
    //   274: astore 11
    //   276: ldc 86
    //   278: invokevirtual 84	java/lang/String:length	()I
    //   281: istore 12
    //   283: iconst_0
    //   284: istore 13
    //   286: iconst_0
    //   287: istore 14
    //   289: iload 13
    //   291: aload_0
    //   292: getfield 12	com/alipay/b/a/c:b	Lcom/alipay/b/a/b;
    //   295: getfield 60	com/alipay/b/a/b:b	I
    //   298: iconst_3
    //   299: idiv
    //   300: if_icmplt +148 -> 448
    //   303: invokestatic 51	com/alipay/sonicwavenfc/SonicWaveNFC:getInstance	()Lcom/alipay/sonicwavenfc/SonicWaveNFC;
    //   306: invokevirtual 55	com/alipay/sonicwavenfc/SonicWaveNFC:getReceiveDataHandler	()Lcom/alipay/b/a/a;
    //   309: aload 11
    //   311: iload 14
    //   313: aload_0
    //   314: getfield 12	com/alipay/b/a/c:b	Lcom/alipay/b/a/b;
    //   317: getfield 63	com/alipay/b/a/b:e	Z
    //   320: aload_0
    //   321: getfield 12	com/alipay/b/a/c:b	Lcom/alipay/b/a/b;
    //   324: getfield 67	com/alipay/b/a/b:d	F
    //   327: f2d
    //   328: invokeinterface 73 6 0
    //   333: goto +524 -> 857
    //   336: bipush 15
    //   338: aload_0
    //   339: getfield 12	com/alipay/b/a/c:b	Lcom/alipay/b/a/b;
    //   342: getfield 76	com/alipay/b/a/b:a	[B
    //   345: iload 29
    //   347: baload
    //   348: iconst_4
    //   349: iushr
    //   350: iand
    //   351: i2b
    //   352: istore 30
    //   354: iload 29
    //   356: iconst_1
    //   357: ishl
    //   358: istore 31
    //   360: iload 30
    //   362: iflt +19 -> 381
    //   365: iload 30
    //   367: iload 28
    //   369: if_icmpge +12 -> 381
    //   372: ldc 78
    //   374: iload 30
    //   376: invokevirtual 90	java/lang/String:charAt	(I)C
    //   379: istore 30
    //   381: aload 27
    //   383: iload 31
    //   385: iload 30
    //   387: i2b
    //   388: bastore
    //   389: bipush 15
    //   391: aload_0
    //   392: getfield 12	com/alipay/b/a/c:b	Lcom/alipay/b/a/b;
    //   395: getfield 76	com/alipay/b/a/b:a	[B
    //   398: iload 29
    //   400: baload
    //   401: iand
    //   402: i2b
    //   403: istore 32
    //   405: iconst_1
    //   406: iload 29
    //   408: iconst_1
    //   409: ishl
    //   410: iadd
    //   411: istore 33
    //   413: iload 32
    //   415: iflt +19 -> 434
    //   418: iload 32
    //   420: iload 28
    //   422: if_icmpge +12 -> 434
    //   425: ldc 78
    //   427: iload 32
    //   429: invokevirtual 90	java/lang/String:charAt	(I)C
    //   432: istore 32
    //   434: aload 27
    //   436: iload 33
    //   438: iload 32
    //   440: i2b
    //   441: bastore
    //   442: iinc 29 1
    //   445: goto -236 -> 209
    //   448: bipush 63
    //   450: aload_0
    //   451: getfield 12	com/alipay/b/a/c:b	Lcom/alipay/b/a/b;
    //   454: getfield 76	com/alipay/b/a/b:a	[B
    //   457: iload 13
    //   459: iconst_3
    //   460: imul
    //   461: baload
    //   462: iconst_2
    //   463: iushr
    //   464: iand
    //   465: i2b
    //   466: istore 15
    //   468: iload 15
    //   470: iflt +392 -> 862
    //   473: iload 15
    //   475: iload 12
    //   477: if_icmpge +385 -> 862
    //   480: ldc 86
    //   482: iload 15
    //   484: invokevirtual 90	java/lang/String:charAt	(I)C
    //   487: istore 15
    //   489: goto +373 -> 862
    //   492: iload 14
    //   494: iconst_1
    //   495: iadd
    //   496: istore 17
    //   498: aload 11
    //   500: iload 14
    //   502: iload 16
    //   504: bastore
    //   505: bipush 63
    //   507: aload_0
    //   508: getfield 12	com/alipay/b/a/c:b	Lcom/alipay/b/a/b;
    //   511: getfield 76	com/alipay/b/a/b:a	[B
    //   514: iload 13
    //   516: iconst_3
    //   517: imul
    //   518: baload
    //   519: iconst_4
    //   520: ishl
    //   521: bipush 15
    //   523: aload_0
    //   524: getfield 12	com/alipay/b/a/c:b	Lcom/alipay/b/a/b;
    //   527: getfield 76	com/alipay/b/a/b:a	[B
    //   530: iconst_1
    //   531: iload 13
    //   533: iconst_3
    //   534: imul
    //   535: iadd
    //   536: baload
    //   537: iconst_4
    //   538: iushr
    //   539: iand
    //   540: ior
    //   541: iand
    //   542: i2b
    //   543: istore 18
    //   545: iload 18
    //   547: iflt +335 -> 882
    //   550: iload 18
    //   552: iload 12
    //   554: if_icmpge +328 -> 882
    //   557: ldc 86
    //   559: iload 18
    //   561: invokevirtual 90	java/lang/String:charAt	(I)C
    //   564: istore 18
    //   566: goto +316 -> 882
    //   569: iload 17
    //   571: iconst_1
    //   572: iadd
    //   573: istore 20
    //   575: aload 11
    //   577: iload 17
    //   579: iload 19
    //   581: bastore
    //   582: iload 20
    //   584: istore 17
    //   586: bipush 63
    //   588: bipush 63
    //   590: aload_0
    //   591: getfield 12	com/alipay/b/a/c:b	Lcom/alipay/b/a/b;
    //   594: getfield 76	com/alipay/b/a/b:a	[B
    //   597: iconst_1
    //   598: iload 13
    //   600: iconst_3
    //   601: imul
    //   602: iadd
    //   603: baload
    //   604: iconst_2
    //   605: ishl
    //   606: iand
    //   607: iconst_3
    //   608: aload_0
    //   609: getfield 12	com/alipay/b/a/c:b	Lcom/alipay/b/a/b;
    //   612: getfield 76	com/alipay/b/a/b:a	[B
    //   615: iconst_2
    //   616: iload 13
    //   618: iconst_3
    //   619: imul
    //   620: iadd
    //   621: baload
    //   622: bipush 6
    //   624: iushr
    //   625: iand
    //   626: ior
    //   627: iand
    //   628: i2b
    //   629: istore 21
    //   631: iload 21
    //   633: iflt +269 -> 902
    //   636: iload 21
    //   638: iload 12
    //   640: if_icmpge +262 -> 902
    //   643: ldc 86
    //   645: iload 21
    //   647: invokevirtual 90	java/lang/String:charAt	(I)C
    //   650: istore 21
    //   652: goto +250 -> 902
    //   655: iload 17
    //   657: iconst_1
    //   658: iadd
    //   659: istore 23
    //   661: aload 11
    //   663: iload 17
    //   665: iload 22
    //   667: bastore
    //   668: iload 23
    //   670: istore 17
    //   672: bipush 63
    //   674: aload_0
    //   675: getfield 12	com/alipay/b/a/c:b	Lcom/alipay/b/a/b;
    //   678: getfield 76	com/alipay/b/a/b:a	[B
    //   681: iconst_2
    //   682: iload 13
    //   684: iconst_3
    //   685: imul
    //   686: iadd
    //   687: baload
    //   688: iand
    //   689: i2b
    //   690: istore 24
    //   692: iload 24
    //   694: iflt +228 -> 922
    //   697: iload 24
    //   699: iload 12
    //   701: if_icmpge +221 -> 922
    //   704: ldc 86
    //   706: iload 24
    //   708: invokevirtual 90	java/lang/String:charAt	(I)C
    //   711: istore 24
    //   713: goto +209 -> 922
    //   716: iload 17
    //   718: iconst_1
    //   719: iadd
    //   720: istore 26
    //   722: aload 11
    //   724: iload 17
    //   726: iload 25
    //   728: bastore
    //   729: iload 26
    //   731: istore 17
    //   733: iinc 13 1
    //   736: iload 17
    //   738: istore 14
    //   740: goto -451 -> 289
    //   743: new 92	java/util/Date
    //   746: dup
    //   747: invokespecial 93	java/util/Date:<init>	()V
    //   750: invokevirtual 97	java/util/Date:getTime	()J
    //   753: aload_0
    //   754: getfield 12	com/alipay/b/a/c:b	Lcom/alipay/b/a/b;
    //   757: getfield 101	com/alipay/b/a/b:g	J
    //   760: lsub
    //   761: lstore 6
    //   763: aload_0
    //   764: getfield 12	com/alipay/b/a/c:b	Lcom/alipay/b/a/b;
    //   767: getfield 104	com/alipay/b/a/b:f	I
    //   770: istore 8
    //   772: lload 6
    //   774: iload 8
    //   776: i2l
    //   777: lcmp
    //   778: ifle -770 -> 8
    //   781: aload_0
    //   782: iconst_0
    //   783: invokevirtual 32	com/alipay/b/a/c:a	(Z)V
    //   786: invokestatic 37	com/alipay/b/a/d:a	()Lcom/alipay/b/a/d;
    //   789: invokevirtual 40	com/alipay/b/a/d:c	()V
    //   792: invokestatic 51	com/alipay/sonicwavenfc/SonicWaveNFC:getInstance	()Lcom/alipay/sonicwavenfc/SonicWaveNFC;
    //   795: invokevirtual 55	com/alipay/sonicwavenfc/SonicWaveNFC:getReceiveDataHandler	()Lcom/alipay/b/a/a;
    //   798: ifnull +21 -> 819
    //   801: invokestatic 51	com/alipay/sonicwavenfc/SonicWaveNFC:getInstance	()Lcom/alipay/sonicwavenfc/SonicWaveNFC;
    //   804: invokevirtual 55	com/alipay/sonicwavenfc/SonicWaveNFC:getReceiveDataHandler	()Lcom/alipay/b/a/a;
    //   807: invokeinterface 107 1 0
    //   812: iconst_1
    //   813: istore_2
    //   814: goto -799 -> 15
    //   817: astore 10
    //   819: iconst_1
    //   820: istore_2
    //   821: goto -806 -> 15
    //   824: astore_1
    //   825: goto -819 -> 6
    //   828: astore_3
    //   829: goto -790 -> 39
    //   832: astore 4
    //   834: goto -826 -> 8
    //   837: astore 9
    //   839: iconst_1
    //   840: istore_2
    //   841: goto -833 -> 8
    //   844: iload 14
    //   846: istore 17
    //   848: goto -343 -> 505
    //   851: iinc 35 1
    //   854: goto -759 -> 95
    //   857: iconst_1
    //   858: istore_2
    //   859: goto -844 -> 15
    //   862: iload 15
    //   864: i2b
    //   865: istore 16
    //   867: iload 14
    //   869: ifgt -377 -> 492
    //   872: iload 16
    //   874: bipush 32
    //   876: if_icmpeq -32 -> 844
    //   879: goto -387 -> 492
    //   882: iload 18
    //   884: i2b
    //   885: istore 19
    //   887: iload 17
    //   889: ifgt -320 -> 569
    //   892: iload 19
    //   894: bipush 32
    //   896: if_icmpeq -310 -> 586
    //   899: goto -330 -> 569
    //   902: iload 21
    //   904: i2b
    //   905: istore 22
    //   907: iload 17
    //   909: ifgt -254 -> 655
    //   912: iload 22
    //   914: bipush 32
    //   916: if_icmpeq -244 -> 672
    //   919: goto -264 -> 655
    //   922: iload 24
    //   924: i2b
    //   925: istore 25
    //   927: iload 17
    //   929: ifgt -213 -> 716
    //   932: iload 25
    //   934: bipush 32
    //   936: if_icmpeq -203 -> 733
    //   939: goto -223 -> 716
    //
    // Exception table:
    //   from	to	target	type
    //   792	812	817	java/lang/Exception
    //   0	6	824	java/lang/Exception
    //   33	39	828	java/lang/Exception
    //   39	48	832	java/lang/Exception
    //   743	772	832	java/lang/Exception
    //   53	89	837	java/lang/Exception
    //   95	137	837	java/lang/Exception
    //   142	155	837	java/lang/Exception
    //   160	175	837	java/lang/Exception
    //   181	206	837	java/lang/Exception
    //   209	258	837	java/lang/Exception
    //   258	283	837	java/lang/Exception
    //   289	333	837	java/lang/Exception
    //   336	354	837	java/lang/Exception
    //   372	381	837	java/lang/Exception
    //   381	405	837	java/lang/Exception
    //   425	434	837	java/lang/Exception
    //   434	442	837	java/lang/Exception
    //   448	468	837	java/lang/Exception
    //   480	489	837	java/lang/Exception
    //   498	505	837	java/lang/Exception
    //   505	545	837	java/lang/Exception
    //   557	566	837	java/lang/Exception
    //   575	582	837	java/lang/Exception
    //   586	631	837	java/lang/Exception
    //   643	652	837	java/lang/Exception
    //   661	668	837	java/lang/Exception
    //   672	692	837	java/lang/Exception
    //   704	713	837	java/lang/Exception
    //   722	729	837	java/lang/Exception
    //   781	792	837	java/lang/Exception
  }
}

/* Location:           /Users/don/DeSources/alipay/backup/zhifubaoqianbao_52/classes-dex2jar.jar
 * Qualified Name:     com.alipay.b.a.c
 * JD-Core Version:    0.6.2
 */